Workbook

Sheet ReadMe
B2: Human Resource Analytics - Power BI Training Dataset
B3: Prepared for classroom / self-paced Power BI training use
B5: Prepared by: | C5: Kajola Gbenga - Data Scientist & AI Engineer
B7: AsOfDate | C7: 46254 | D7: <- used by formula columns in the Employees sheet (Age, Tenure)
B9: What this workbook contains
B10: This workbook is a fully relational, star/snowflake-style Human Resource dataset built specifically for teaching Power BI end to end - from Power Query loading, through data modelling and relationships, to DAX measures and dashboard design.
B12: Tables in this workbook
B13: Employees | C13: Main employee record table (1 row per employee). Grain: one row per EmployeeID.
B14: Dim_Department | C14: Lookup table of the 10 departments. One-to-many to Employees.
B15: Dim_JobTitle | C15: Lookup table of 38 job titles across all departments and job levels. One-to-many to Employees.
B16: Dim_Location | C16: Lookup table of 15 company office / remote locations. One-to-many to Employees.
B17: Dim_Education | C17: Lookup table of education level x field combinations. One-to-many to Employees.
B18: Dim_Date | C18: A full calendar table (2018-01-01 to 2026-12-31) for time intelligence DAX. One-to-many to Employees (via HireDate/TerminationDate) and to Fact_PerformanceReviews (via ReviewDate).
B19: Fact_PerformanceReviews | C19: One row per employee per review year (multiple rows per employee). Many-to-one back to Employees.
B21: How to use this workbook
B22: Step 1 | C22: Open Power BI Desktop and use Get Data > Excel Workbook to import every sheet listed above (except this ReadMe and the Data_Dictionary sheet).
B23: Step 2 | C23: Build the data model in Model view: create relationships as described in the Data_Dictionary sheet and in the accompanying Word document / HTML files.
B24: Step 3 | C24: Write the DAX measures described in the training documents.
B25: Step 4 | C25: Build the five dashboard pages described in the training documents.
B27: Companion files | C27: This dataset ships together with: (1) a Word document containing the full curriculum - problems, column-by-column explanations and solutions; (2) an HTML task brief listing every task to complete; (3) an HTML full solution walkthrough.

Sheet Data_Dictionary
A1: Data Dictionary - every column, every table
A2: Reference this sheet while building your Power Query steps and DAX measures.
A4: Table | B4: Column | C4: Data Type | D4: Description
A5: Employees | B5: EmployeeID | C5: Text (PK) | D5: Unique employee identifier, format EMP0001. Primary key of the Employees table.
A6: Employees | B6: FirstName | C6: Text | D6: Employee's given name.
A7: Employees | B7: LastName | C7: Text | D7: Employee's family name.
A8: Employees | B8: Gender | C8: Text | D8: Self-identified gender: Female, Male, or Non-Binary. Used for diversity dashboards.
A9: Employees | B9: DateOfBirth | C9: Date | D9: Date of birth. Used to compute Age via DAX or the AgeYears formula column.
A10: Employees | B10: MaritalStatus | C10: Text | D10: Single, Married, Divorced, or Widowed.
A11: Employees | B11: DepartmentID | C11: Text (FK) | D11: Foreign key to Dim_Department.DepartmentID.
A12: Employees | B12: DepartmentName | C12: Text | D12: Denormalised department name, kept for quick filtering without a relationship.
A13: Employees | B13: JobTitleID | C13: Text (FK) | D13: Foreign key to Dim_JobTitle.JobTitleID.
A14: Employees | B14: JobTitle | C14: Text | D14: Denormalised job title text.
A15: Employees | B15: JobLevel | C15: Text | D15: Entry, Mid, Senior, Lead, Manager, Director, or Executive.
... A94: Fact_PerformanceReviews | B94: PromotionRecommended | C94: Text (Yes/No) | D94: Whether the manager recommended promotion at that review.

Sheet Employees
A1: EmployeeID | B1: FirstName | C1: LastName | D1: Gender | E1: DateOfBirth | F1: MaritalStatus | G1: DepartmentID | H1: DepartmentName | I1: JobTitleID | J1: JobTitle | K1: JobLevel | L1: LocationID | M1: EducationID | N1: ManagerID | O1: HireDate | P1: TerminationDate | Q1: EmploymentStatus | R1: TerminationReason | S1: AttritionFlag | T1: AnnualSalaryUSD | U1: StockOptionLevel | V1: OvertimeEligible | W1: WorkModel | X1: BusinessTravelFrequency | Y1: DistanceFromHomeKM | Z1: NumCompaniesWorkedPrevious | AA1: RecruitmentSource | AB1: YearsSinceLastPromotion | AC1: YearsInCurrentRole | AD1: YearsWithCurrentManager | AE1: TrainingHoursLastYear | AF1: AbsenteeismDaysLastYear | AG1: OvertimeHoursLastYear | AH1: WorkLifeBalanceScore | AI1: JobSatisfactionScore | AJ1: EnvironmentSatisfactionScore | AK1: RelationshipSatisfactionScore | AL1: PerformanceRatingLastReview | AM1: EngagementScorePercent | AN1: BenefitsEnrolled | AO1: HealthInsurancePlan | AP1: RemoteEquipmentProvided | AQ1: FullName | AR1: AgeYears | AS1: TenureYears
A2: EMP0001 | B2: Mark | C2: Johnson | D2: Male | E2: 1989-04-11 | F2: Single | G2: D09 | H2: Legal | I2: JT34 | J2: General Counsel | K2: Director | L2: L03 | M2: E42 | N2: EMP0693 | O2: 2024-03-29 | Q2: Active | S2: No | T2: 141400 | U2: 0 | V2: No | W2: Onsite | Y2: 14 | Z2: 3 | AA2: Recruitment Agency | AB2: 1.75 | AC2: 1.29 | AD2: 1.77 | AE2: 25 | AF2: 1 | AG2: 23 | AH2: 2 | AI2: 2 | AJ2: 3 | AK2: 4 | AL2: 2 | AM2: 60 | AN2: Yes | AO2: Standard | AP2: No | AQ2: =B2&" "&C2 -> Mark Johnson | AR2: =DATEDIF(E2,ReadMe!$C$7,"y") -> 37 | AS2: =ROUND(DATEDIF(O2,IF(Q2="Active",ReadMe!$C$7,P2),"m")/12,2) -> 2.33
A3: EMP0002 | B3: Denise | C3: Walker | D3: Female | E3: 1993-05-09 | F3: Widowed | G3: D09 | H3: Legal | I3: JT33 | J3: Legal Counsel | K3: Senior | L3: L13 | M3: E13 | N3: EMP0734 | O3: 2024-07-06 | Q3: Active | S3: No | T3: 79000 | U3: 0 | V3: Yes | W3: Remote | X3: Rarely | Y3: 20 | Z3: 3 | AA3: LinkedIn | AB3: 1.22 | AC3: 1.16 | AD3: 0.53 | AE3: 25 | AF3: 1 | AG3: 2 | AH3: 3 | AI3: 2 | AJ3: 3 | AK3: 2 | AL3: 1 | AM3: 81 | AN3: Yes | AO3: Premium | AP3: No | AQ3: =B3&" "&C3 -> Denise Walker | AR3: =DATEDIF(E3,ReadMe!$C$7,"y") -> 33 | AS3: =ROUND(DATEDIF(O3,IF(Q3="Active",ReadMe!$C$7,P3),"m")/12,2) -> 2.08
A4: EMP0003 | B4: Nancy | C4: Rhodes | D4: Female | E4: 1998-08-24 | F4: Married | G4: D03 | H4: Engineering | I4: JT10 | J4: Software Engineer I | K4: Entry | L4: L09 | M4: E42 | N4: EMP0349 | O4: 2020-05-07 | Q4: Active | S4: No | T4: 43600 | U4: 0 | V4: Yes | W4: Hybrid | Y4: 6 | Z4: 0 | AA4: Career Fair | AB4: 0.31 | AC4: 5.47 | AD4: 0.17 | AE4: 30 | AF4: 3 | AG4: 3 | AH4: 2 | AI4: 3 | AJ4: 1 | AK4: 2 | AL4: 3 | AM4: 46 | AN4: Yes | AO4: Standard | AP4: Yes | AQ4: =B4&" "&C4 -> Nancy Rhodes | AR4: =DATEDIF(E4,ReadMe!$C$7,"y") -> 27 | AS4: =ROUND(DATEDIF(O4,IF(Q4="Active",ReadMe!$C$7,P4),"m")/12,2) -> 6.25
A5: EMP0004 | B5: Stephanie | C5: Miller | D5: Female | E5: 1998-07-09 | F5: Widowed | G5: D04 | H5: Information Technology | I5: JT18 | J5: IT Manager | K5: Manager | L5: L12 | M5: E15 | N5: EMP0827 | O5: 2023-04-15 | Q5: Active | S5: No | T5: 99600 | U5: 0 | V5: No | W5: Onsite | X5: Rarely | Y5: 14 | Z5: 2 | AA5: Recruitment Agency | AB5: 1.87 | AC5: 2.61 | AD5: 2.18 | AE5: 30 | AF5: 7 | AG5: 0 | AH5: 2 | AI5: 3 | AJ5: 3 | AK5: 3 | AL5: 5 | AM5: 81 | AN5: Yes | AO5: Standard | AP5: Yes | AQ5: =B5&" "&C5 -> Stephanie Miller | AR5: =DATEDIF(E5,ReadMe!$C$7,"y") -> 28 | AS5: =ROUND(DATEDIF(O5,IF(Q5="Active",ReadMe!$C$7,P5),"m")/12,2) -> 3.33
A6: EMP0005 | B6: Jennifer | C6: Johnson | D6: Female | E6: 1989-07-20 | F6: Married | G6: D03 | H6: Engineering | I6: JT11 | J6: Software Engineer II | K6: Mid | L6: L13 | M6: E24 | N6: EMP0722 | O6: 2021-02-28 | Q6: Active | S6: No | T6: 78100 | U6: 3 | V6: Yes | W6: Remote | Y6: 11 | Z6: 4 | AA6: Career Fair | AB6: 2.96 | AC6: 4.57 | AD6: 0.23 | AE6: 41 | AF6: 0 | AG6: 14 | AH6: 3 | AI6: 2 | AJ6: 2 | AK6: 3 | AL6: 3 | AM6: 51 | AN6: Yes | AP6: Yes | AQ6: =B6&" "&C6 -> Jennifer Johnson | AR6: =DATEDIF(E6,ReadMe!$C$7,"y") -> 37 | AS6: =ROUND(DATEDIF(O6,IF(Q6="Active",ReadMe!$C$7,P6),"m")/12,2) -> 5.42
A7: EMP0006 | B7: Colleen | C7: Wagner | D7: Female | E7: 1988-05-02 | F7: Married | G7: D07 | H7: Operations | I7: JT29 | J7: Operations Manager | K7: Manager | L7: L08 | M7: E20 | N7: EMP0651 | O7: 2018-04-23 | Q7: Active | S7: No | T7: 99000 | U7: 0 | V7: No | W7: Hybrid | Y7: 1 | Z7: 4 | AA7: Job Portal | AB7: 4.9 | AC7: 2.74 | AD7: 1.65 | AE7: 26 | AF7: 2 | AG7: 21 | AH7: 3 | AI7: 3 | AJ7: 3 | AK7: 4 | AL7: 5 | AM7: 59 | AN7: Yes | AO7: Standard | AP7: No | AQ7: =B7&" "&C7 -> Colleen Wagner | AR7: =DATEDIF(E7,ReadMe!$C$7,"y") -> 38 | AS7: =ROUND(DATEDIF(O7,IF(Q7="Active",ReadMe!$C$7,P7),"m")/12,2) -> 8.25
A8: EMP0007 | B8: Alyssa | C8: Gonzalez | D8: Female | E8: 1982-09-06 | F8: Married | G8: D03 | H8: Engineering | I8: JT13 | J8: Lead Software Engineer | K8: Lead | L8: L11 | M8: E11 | N8: EMP0176 | O8: 2018-02-11 | Q8: Active | S8: No | T8: 125100 | U8: 0 | V8: Yes | W8: Hybrid | X8: Rarely | Y8: 21 | Z8: 4 | AA8: LinkedIn | AB8: 1.75 | AC8: 8.26 | AD8: 6.06 | AE8: 30 | AF8: 14 | AG8: 12 | AH8: 3 | AI8: 3 | AJ8: 2 | AK8: 1 | AL8: 3 | AM8: 78 | AN8: Yes | AO8: Premium | AP8: Yes | AQ8: =B8&" "&C8 -> Alyssa Gonzalez | AR8: =DATEDIF(E8,ReadMe!$C$7,"y") -> 43 | AS8: =ROUND(DATEDIF(O8,IF(Q8="Active",ReadMe!$C$7,P8),"m")/12,2) -> 8.5
A9: EMP0008 | B9: Marie | C9: Gardner | D9: Female | E9: 1985-10-07 | F9: Single | G9: D06 | H9: Finance | I9: JT26 | J9: Finance Manager | K9: Manager | L9: L12 | M9: E27 | N9: EMP0864 | O9: 2020-02-22 | Q9: Active | S9: No | T9: 108500 | U9: 0 | V9: No | W9: Hybrid | X9: Rarely | Y9: 9 | Z9: 2 | AA9: LinkedIn | AB9: 3.06 | AC9: 2.57 | AD9: 4.86 | AE9: 27 | AF9: 3 | AG9: 8 | AH9: 4 | AI9: 3 | AJ9: 3 | AK9: 2 | AL9: 3 | AM9: 65 | AN9: Yes | AO9: Standard | AP9: No | AQ9: =B9&" "&C9 -> Marie Gardner | AR9: =DATEDIF(E9,ReadMe!$C$7,"y") -> 40 | AS9: =ROUND(DATEDIF(O9,IF(Q9="Active",ReadMe!$C$7,P9),"m")/12,2) -> 6.42
A10: EMP0009 | B10: Daniel | C10: Lawrence | D10: Male | E10: 1988-02-06 | F10: Divorced | G10: D05 | H10: Human Resources | I10: JT19 | J10: HR Coordinator | K10: Entry | L10: L03 | M10: E08 | N10: EMP0581 | O10: 2023-12-07 | Q10: Active | S10: No | T10: 54100 | U10: 0 | V10: Yes | W10: Onsite | Y10: 17 | Z10: 0 | AA10: LinkedIn | AB10: 1.14 | AC10: 1.32 | AD10: 1.11 | AE10: 20 | AF10: 2 | AG10: 14 | AH10: 2 | AI10: 3 | AJ10: 3 | AK10: 3 | AL10: 3 | AM10: 72 | AN10: Yes | AO10: Standard | AP10: No | AQ10: =B10&" "&C10 -> Daniel Lawrence | AR10: =DATEDIF(E10,ReadMe!$C$7,"y") -> 38 | AS10: =ROUND(DATEDIF(O10,IF(Q10="Active",ReadMe!$C$7,P10),"m")/12,2) -> 2.67
A11: EMP0010 | B11: Robert | C11: Smith | D11: Male | E11: 1982-10-06 | F11: Divorced | G11: D09 | H11: Legal | I11: JT34 | J11: General Counsel | K11: Director | L11: L13 | M11: E31 | N11: EMP0763 | O11: 2022-02-20 | Q11: Active | S11: No | T11: 161800 | U11: 0 | V11: No | W11: Hybrid | Y11: 29 | Z11: 4 | AA11: Company Website | AB11: 1.77 | AC11: 1.62 | AD11: 2.2 | AE11: 35 | AF11: 0 | AG11: 41 | AH11: 2 | AI11: 3 | AJ11: 4 | AK11: 3 | AL11: 4 | AM11: 49 | AN11: Yes | AO11: Basic | AP11: No | AQ11: =B11&" "&C11 -> Robert Smith | AR11: =DATEDIF(E11,ReadMe!$C$7,"y") -> 43 | AS11: =ROUND(DATEDIF(O11,IF(Q11="Active",ReadMe!$C$7,P11),"m")/12,2) -> 4.5
A12: EMP0011 | B12: Robert | C12: Wolfe | D12: Male | E12: 2005-02-02 | F12: Single | G12: D03 | H12: Engineering | I12: JT10 | J12: Software Engineer I | K12: Entry | L12: L01 | M12: E01 | N12: EMP0094 | O12: 2026-01-31 | Q12: Active | S12: No | T12: 56000 | U12: 1 | V12: Yes | W12: Remote | Y12: 16 | Z12: 3 | AA12: LinkedIn | AB12: 0.24 | AC12: 0.2 | AD12: 0.36 | AE12: 27 | AF12: 2 | AG12: 9 | AH12: 3 | AI12: 4 | AJ12: 3 | AK12: 1 | AL12: 4 | AM12: 90 | AN12: Yes | AO12: Standard | AP12: No | AQ12: =B12&" "&C12 -> Robert Wolfe | AR12: =DATEDIF(E12,ReadMe!$C$7,"y") -> 21 | AS12: =ROUND(DATEDIF(O12,IF(Q12="Active",ReadMe!$C$7,P12),"m")/12,2) -> 0.5
A13: EMP0012 | B13: Gerald | C13: Moore | D13: Male | E13: 1983-01-27 | F13: Single | G13: D05 | H13: Human Resources | I13: JT22 | J13: HR Manager | K13: Manager | L13: L09 | M13: E08 | N13: EMP0480 | O13: 2020-09-23 | Q13: Active | S13: No | T13: 134600 | U13: 2 | V13: No | W13: Remote | Y13: 24 | Z13: 3 | AA13: Company Website | AB13: 1.34 | AC13: 0.86 | AD13: 0.88 | AE13: 42 | AF13: 3 | AG13: 19 | AH13: 3 | AI13: 3 | AJ13: 3 | AK13: 3 | AL13: 4 | AM13: 68 | AN13: Yes | AO13: Basic | AP13: Yes | AQ13: =B13&" "&C13 -> Gerald Moore | AR13: =DATEDIF(E13,ReadMe!$C$7,"y") -> 43 | AS13: =ROUND(DATEDIF(O13,IF(Q13="Active",ReadMe!$C$7,P13),"m")/12,2) -> 5.83
A14: EMP0013 | B14: Tyler | C14: Rogers | D14: Male | E14: 2004-11-24 | F14: Divorced | G14: D07 | H14: Operations | I14: JT28 | J14: Operations Analyst | K14: Entry | L14: L14 | M14: E10 | N14: EMP0977 | O14: 2025-05-30 | P14: 2025-12-17 | Q14: Terminated | R14: Voluntary - Better Opportunity | S14: Yes | T14: 51600 | U14: 2 | V14: Yes | W14: Hybrid | Y14: 2 | Z14: 2 | AA14: Recruitment Agency | AB14: 0.08 | AC14: 0.13 | AD14: 0.39 | AE14: 36 | AF14: 5 | AG14: 14 | AH14: 2 | AI14: 2 | AJ14: 4 | AK14: 2 | AL14: 4 | AM14: 46 | AN14: Yes | AO14: Basic | AP14: No | AQ14: =B14&" "&C14 -> Tyler Rogers | AR14: =DATEDIF(E14,ReadMe!$C$7,"y") -> 21 | AS14: =ROUND(DATEDIF(O14,IF(Q14="Active",ReadMe!$C$7,P14),"m")/12,2) -> 0.5
A15: EMP0014 | B15: Brandon | C15: Davis | D15: Male | E15: 1996-07-04 | F15: Married | G15: D08 | H15: Customer Support | I15: JT31 | J15: Senior Support Representative | K15: Senior | L15: L03 | M15: E27 | N15: EMP0520 | O15: 2018-05-25 | Q15: Active | S15: No | T15: 95300 | U15: 0 | V15: Yes | W15: Hybrid | X15: Rarely | Y15: 13 | Z15: 1 | AA15: Job Portal | AB15: 0.57 | AC15: 0.24 | AD15: 2.04 | AE15: 34 | AF15: 22 | AG15: 66 | AH15: 4 | AI15: 2 | AJ15: 3 | AK15: 4 | AL15: 2 | AM15: 79 | AN15: Yes | AO15: Premium | AP15: No | AQ15: =B15&" "&C15 -> Brandon Davis | AR15: =DATEDIF(E15,ReadMe!$C$7,"y") -> 30 | AS15: =ROUND(DATEDIF(O15,IF(Q15="Active",ReadMe!$C$7,P15),"m")/12,2) -> 8.17
A16: EMP0015 | B16: Ryan | C16: Munoz | D16: Male | E16: 2003-11-28 | F16: Divorced | G16: D07 | H16: Operations | I16: JT29 | J16: Operations Manager | K16: Manager | L16: L08 | M16: E13 | N16: EMP0115 | O16: 2024-05-06 | Q16: Active | S16: No | T16: 122000 | U16: 0 | V16: No | W16: Hybrid | Y16: 51 | Z16: 0 | AA16: LinkedIn | AB16: 1.84 | AC16: 0.01 | AD16: 1.84 | AE16: 26 | AF16: 2 | AG16: 0 | AH16: 3 | AI16: 3 | AJ16: 3 | AK16: 3 | AL16: 3 | AM16: 70 | AN16: Yes | AO16: Premium | AP16: No | AQ16: =B16&" "&C16 -> Ryan Munoz | AR16: =DATEDIF(E16,ReadMe!$C$7,"y") -> 22 | AS16: =ROUND(DATEDIF(O16,IF(Q16="Active",ReadMe!$C$7,P16),"m")/12,2) -> 2.25
A17: EMP0016 | B17: Renee | C17: Blair | D17: Female | E17: 1987-07-21 | F17: Married | G17: D06 | H17: Finance | I17: JT27 | J17: Director of Finance | K17: Director | L17: L03 | M17: E33 | N17: EMP0779 | O17: 2025-03-09 | Q17: Active | S17: No | T17: 188300 | U17: 1 | V17: No | W17: Onsite | X17: Rarely | Y17: 37 | Z17: 2 | AA17: LinkedIn | AB17: 0.57 | AC17: 0.33 | AD17: 0.17 | AE17: 32 | AF17: 2 | AG17: 31 | AH17: 4 | AI17: 3 | AJ17: 1 | AK17: 2 | AL17: 3 | AM17: 49 | AN17: Yes | AO17: Basic | AP17: Yes | AQ17: =B17&" "&C17 -> Renee Blair | AR17: =DATEDIF(E17,ReadMe!$C$7,"y") -> 39 | AS17: =ROUND(DATEDIF(O17,IF(Q17="Active",ReadMe!$C$7,P17),"m")/12,2) -> 1.42
A18: EMP0017 | B18: Joshua | C18: Dudley | D18: Male | E18: 1997-06-04 | F18: Married | G18: D01 | H18: Sales | I18: JT03 | J18: Senior Account Executive | K18: Senior | L18: L12 | M18: E50 | N18: EMP0952 | O18: 2023-08-28 | Q18: Active | S18: No | T18: 110200 | U18: 2 | V18: Yes | W18: Hybrid | Y18: 5 | Z18: 2 | AA18: Company Website | AB18: 1.54 | AC18: 1.1 | AD18: 2.07 | AE18: 24 | AF18: 1 | AG18: 18 | AH18: 3 | AI18: 2 | AJ18: 3 | AK18: 4 | AL18: 2 | AM18: 95 | AN18: Yes | AO18: Basic | AP18: Yes | AQ18: =B18&" "&C18 -> Joshua Dudley | AR18: =DATEDIF(E18,ReadMe!$C$7,"y") -> 29 | AS18: =ROUND(DATEDIF(O18,IF(Q18="Active",ReadMe!$C$7,P18),"m")/12,2) -> 2.92
A19: EMP0018 | B19: Jamie | C19: Arnold | D19: Female | E19: 1993-09-30 | F19: Divorced | G19: D05 | H19: Human Resources | I19: JT21 | J19: Senior HR Business Partner | K19: Senior | L19: L11 | M19: E31 | N19: EMP0254 | O19: 2022-07-22 | Q19: Active | S19: No | T19: 111800 | U19: 2 | V19: Yes | W19: Onsite | X19: Frequently | Y19: 8 | Z19: 2 | AA19: Employee Referral | AB19: 1.38 | AC19: 0.51 | AD19: 1.27 | AE19: 30 | AF19: 10 | AG19: 12 | AH19: 2 | AI19: 4 | AJ19: 3 | AK19: 3 | AL19: 3 | AM19: 57 | AN19: Yes | AO19: Basic | AP19: Yes | AQ19: =B19&" "&C19 -> Jamie Arnold | AR19: =DATEDIF(E19,ReadMe!$C$7,"y") -> 32 | AS19: =ROUND(DATEDIF(O19,IF(Q19="Active",ReadMe!$C$7,P19),"m")/12,2) -> 4
A20: EMP0019 | B20: Ronald | C20: Montgomery | D20: Male | E20: 1979-05-12 | F20: Divorced | G20: D06 | H20: Finance | I20: JT27 | J20: Director of Finance | K20: Director | L20: L15 | M20: E43 | N20: EMP0928 | O20: 2026-06-30 | Q20: Active | S20: No | T20: 152700 | U20: 3 | V20: No | W20: Remote | Y20: 18 | Z20: 2 | AA20: Employee Referral | AB20: 0.06 | AC20: 0.06 | AD20: 0.06 | AE20: 17 | AF20: 6 | AG20: 1 | AH20: 3 | AI20: 4 | AJ20: 2 | AK20: 4 | AL20: 3 | AM20: 78 | AN20: Yes | AO20: Basic | AP20: Yes | AQ20: =B20&" "&C20 -> Ronald Montgomery | AR20: =DATEDIF(E20,ReadMe!$C$7,"y") -> 47 | AS20: =ROUND(DATEDIF(O20,IF(Q20="Active",ReadMe!$C$7,P20),"m")/12,2) -> 0.08
A21: EMP0020 | B21: Scott | C21: Ray | D21: Male | E21: 1980-12-26 | F21: Widowed | G21: D06 | H21: Finance | I21: JT27 | J21: Director of Finance | K21: Director | L21: L05 | M21: E24 | N21: EMP0904 | O21: 2024-07-10 | Q21: Active | S21: No | T21: 155300 | U21: 3 | V21: No | W21: Hybrid | Y21: 1 | Z21: 0 | AA21: LinkedIn | AB21: 1.47 | AC21: 1.66 | AD21: 0.43 | AE21: 9 | AF21: 11 | AG21: 0 | AH21: 3 | AI21: 3 | AJ21: 3 | AK21: 4 | AL21: 4 | AM21: 78 | AN21: Yes | AO21: Premium | AP21: No | AQ21: =B21&" "&C21 -> Scott Ray | AR21: =DATEDIF(E21,ReadMe!$C$7,"y") -> 45 | AS21: =ROUND(DATEDIF(O21,IF(Q21="Active",ReadMe!$C$7,P21),"m")/12,2) -> 2.08
A22: EMP0021 | B22: Michael | C22: Williams | D22: Male | E22: 1988-05-24 | F22: Single | G22: D05 | H22: Human Resources | I22: JT21 | J22: Senior HR Business Partner | K22: Senior | L22: L08 | M22: E11 | N22: EMP0421 | O22: 2025-03-08 | Q22: Active | S22: No | T22: 105500 | U22: 1 | V22: Yes | W22: Hybrid | X22: Frequently | Y22: 13 | Z22: 2 | AA22: Company Website | AB22: 0.85 | AC22: 0.71 | AD22: 0.7 | AE22: 37 | AF22: 1 | AG22: 3 | AH22: 3 | AI22: 3 | AJ22: 2 | AK22: 3 | AL22: 4 | AM22: 59 | AN22: No | AO22: Basic | AP22: Yes | AQ22: =B22&" "&C22 -> Michael Williams | AR22: =DATEDIF(E22,ReadMe!$C$7,"y") -> 38 | AS22: =ROUND(DATEDIF(O22,IF(Q22="Active",ReadMe!$C$7,P22),"m")/12,2) -> 1.42
A23: EMP0022 | B23: Darren | C23: Roberts | D23: Male | E23: 1991-07-29 | F23: Married | G23: D03 | H23: Engineering | I23: JT15 | J23: Director of Engineering | K23: Director | L23: L01 | M23: E37 | N23: EMP0112 | O23: 2022-07-18 | Q23: Active | S23: No | T23: 175500 | U23: 0 | V23: No | W23: Remote | Y23: 22 | Z23: 3 | AA23: Recruitment Agency | AB23: 1.59 | AC23: 0.52 | AD23: 2.47 | AE23: 28 | AF23: 2 | AG23: 14 | AH23: 3 | AI23: 4 | AJ23: 3 | AK23: 2 | AL23: 1 | AM23: 63 | AN23: Yes | AO23: Basic | AP23: Yes | AQ23: =B23&" "&C23 -> Darren Roberts | AR23: =DATEDIF(E23,ReadMe!$C$7,"y") -> 35 | AS23: =ROUND(DATEDIF(O23,IF(Q23="Active",ReadMe!$C$7,P23),"m")/12,2) -> 4.08
A24: EMP0023 | B24: Angela | C24: Hall | D24: Female | E24: 2005-04-05 | F24: Single | G24: D02 | H24: Marketing | I24: JT06 | J24: Marketing Coordinator | K24: Entry | L24: L06 | M24: E17 | N24: EMP0883 | O24: 2026-01-27 | Q24: Active | S24: No | T24: 46400 | U24: 0 | V24: Yes | W24: Onsite | Y24: 7 | Z24: 2 | AA24: Employee Referral | AB24: 0.46 | AC24: 0.26 | AD24: 0.2 | AE24: 23 | AF24: 7 | AG24: 30 | AH24: 3 | AI24: 4 | AJ24: 3 | AK24: 3 | AL24: 2 | AM24: 88 | AN24: Yes | AO24: Premium | AP24: No | AQ24: =B24&" "&C24 -> Angela Hall | AR24: =DATEDIF(E24,ReadMe!$C$7,"y") -> 21 | AS24: =ROUND(DATEDIF(O24,IF(Q24="Active",ReadMe!$C$7,P24),"m")/12,2) -> 0.5
A25: EMP0024 | B25: Brian | C25: Ramirez | D25: Male | E25: 1998-08-20 | F25: Widowed | G25: D08 | H25: Customer Support | I25: JT30 | J25: Customer Support Representative | K25: Entry | L25: L02 | M25: E31 | N25: EMP0925 | O25: 2018-07-24 | P25: 2024-04-02 | Q25: Terminated | R25: Voluntary - Further Education | S25: Yes | T25: 48800 | U25: 0 | V25: Yes | W25: Onsite | X25: Rarely | Y25: 54 | Z25: 1 | AA25: Employee Referral | AB25: 4.92 | AC25: 4.17 | AD25: 6.58 | AE25: 49 | AF25: 8 | AG25: 37 | AH25: 3 | AI25: 2 | AJ25: 3 | AK25: 2 | AL25: 3 | AM25: 73 | AN25: Yes | AO25: Standard | AP25: Yes | AQ25: =B25&" "&C25 -> Brian Ramirez | AR25: =DATEDIF(E25,ReadMe!$C$7,"y") -> 28 | AS25: =ROUND(DATEDIF(O25,IF(Q25="Active",ReadMe!$C$7,P25),"m")/12,2) -> 5.67
A26: EMP0025 | B26: Cynthia | C26: Diaz | D26: Non-Binary | E26: 1990-01-09 | F26: Divorced | G26: D06 | H26: Finance | I26: JT24 | J26: Financial Analyst | K26: Entry | L26: L05 | M26: E31 | N26: EMP0499 | O26: 2023-04-16 | Q26: Active | S26: No | T26: 43300 | U26: 1 | V26: Yes | W26: Onsite | Y26: 12 | Z26: 2 | AA26: LinkedIn | AB26: 0.14 | AC26: 0.69 | AD26: 0.16 | AE26: 35 | AF26: 1 | AG26: 31 | AH26: 3 | AI26: 1 | AJ26: 1 | AK26: 2 | AL26: 3 | AM26: 62 | AN26: Yes | AO26: Premium | AP26: Yes | AQ26: =B26&" "&C26 -> Cynthia Diaz | AR26: =DATEDIF(E26,ReadMe!$C$7,"y") -> 36 | AS26: =ROUND(DATEDIF(O26,IF(Q26="Active",ReadMe!$C$7,P26),"m")/12,2) -> 3.33
A27: EMP0026 | B27: Mitchell | C27: Clark | D27: Non-Binary | E27: 1987-11-26 | F27: Single | G27: D07 | H27: Operations | I27: JT29 | J27: Operations Manager | K27: Manager | L27: L04 | M27: E46 | N27: EMP0162 | O27: 2025-08-25 | P27: 2026-02-05 | Q27: Terminated | R27: Voluntary - Personal Reasons | S27: Yes | T27: 124000 | U27: 0 | V27: No | W27: Remote | Y27: 1 | Z27: 1 | AA27: Career Fair | AB27: 0.49 | AC27: 0.3 | AD27: 0.19 | AE27: 28 | AF27: 0 | AG27: 0 | AH27: 3 | AI27: 3 | AJ27: 2 | AK27: 3 | AL27: 4 | AM27: 60 | AN27: No | AO27: Basic | AP27: Yes | AQ27: =B27&" "&C27 -> Mitchell Clark | AR27: =DATEDIF(E27,ReadMe!$C$7,"y") -> 38 | AS27: =ROUND(DATEDIF(O27,IF(Q27="Active",ReadMe!$C$7,P27),"m")/12,2) -> 0.42
A28: EMP0027 | B28: Debra | C28: Zuniga | D28: Female | E28: 1993-09-17 | F28: Single | G28: D06 | H28: Finance | I28: JT26 | J28: Finance Manager | K28: Manager | L28: L02 | M28: E34 | N28: EMP0912 | O28: 2018-04-26 | Q28: Active | S28: No | T28: 124800 | U28: 1 | V28: No | W28: Onsite | X28: Frequently | Y28: 1 | Z28: 4 | AA28: Recruitment Agency | AB28: 5.03 | AC28: 2.35 | AD28: 1.89 | AE28: 32 | AF28: 2 | AG28: 16 | AH28: 3 | AI28: 2 | AJ28: 2 | AK28: 3 | AL28: 3 | AM28: 100 | AN28: Yes | AO28: Standard | AP28: No | AQ28: =B28&" "&C28 -> Debra Zuniga | AR28: =DATEDIF(E28,ReadMe!$C$7,"y") -> 32 | AS28: =ROUND(DATEDIF(O28,IF(Q28="Active",ReadMe!$C$7,P28),"m")/12,2) -> 8.25
A29: EMP0028 | B29: Maria | C29: Lynch | D29: Female | E29: 1976-11-16 | F29: Married | G29: D10 | H29: Executive | I29: JT36 | J29: Chief Financial Officer | K29: Executive | L29: L10 | M29: E20 | O29: 2021-07-25 | Q29: Active | S29: No | T29: 298900 | U29: 1 | V29: No | W29: Onsite | X29: Rarely | Y29: 25 | Z29: 2 | AA29: Job Portal | AB29: 3.96 | AC29: 3.47 | AD29: 1.31 | AE29: 13 | AF29: 0 | AG29: 44 | AH29: 2 | AI29: 4 | AJ29: 1 | AK29: 3 | AL29: 1 | AM29: 77 | AN29: Yes | AO29: Basic | AP29: No | AQ29: =B29&" "&C29 -> Maria Lynch | AR29: =DATEDIF(E29,ReadMe!$C$7,"y") -> 49 | AS29: =ROUND(DATEDIF(O29,IF(Q29="Active",ReadMe!$C$7,P29),"m")/12,2) -> 5
A30: EMP0029 | B30: Carolyn | C30: Daniel | D30: Female | E30: 2003-03-26 | F30: Divorced | G30: D03 | H30: Engineering | I30: JT10 | J30: Software Engineer I | K30: Entry | L30: L10 | M30: E31 | N30: EMP0076 | O30: 2025-03-01 | P30: 2026-04-13 | Q30: Terminated | R30: Involuntary - Performance | S30: Yes | T30: 51400 | U30: 1 | V30: Yes | W30: Onsite | X30: Rarely | Y30: 14 | Z30: 2 | AA30: LinkedIn | AB30: 1.37 | AC30: 0.05 | AD30: 1.08 | AE30: 36 | AF30: 0 | AG30: 20 | AH30: 3 | AI30: 3 | AJ30: 3 | AK30: 3 | AL30: 3 | AM30: 60 | AN30: Yes | AP30: Yes | AQ30: =B30&" "&C30 -> Carolyn Daniel | AR30: =DATEDIF(E30,ReadMe!$C$7,"y") -> 23 | AS30: =ROUND(DATEDIF(O30,IF(Q30="Active",ReadMe!$C$7,P30),"m")/12,2) -> 1.08
A31: EMP0030 | B31: Christopher | C31: Gray | D31: Male | E31: 1989-04-26 | F31: Single | G31: D09 | H31: Legal | I31: JT34 | J31: General Counsel | K31: Director | L31: L02 | M31: E02 | N31: EMP0557 | O31: 2023-02-02 | Q31: Active | S31: No | T31: 188400 | U31: 2 | V31: No | W31: Onsite | X31: Frequently | Y31: 7 | Z31: 5 | AA31: Company Website | AB31: 1.92 | AC31: 2.96 | AD31: 1.65 | AE31: 17 | AF31: 1 | AG31: 53 | AH31: 1 | AI31: 4 | AJ31: 3 | AK31: 3 | AL31: 2 | AM31: 87 | AN31: No | AO31: Premium | AP31: No | AQ31: =B31&" "&C31 -> Christopher Gray | AR31: =DATEDIF(E31,ReadMe!$C$7,"y") -> 37 | AS31: =ROUND(DATEDIF(O31,IF(Q31="Active",ReadMe!$C$7,P31),"m")/12,2) -> 3.5
A32: EMP0031 | B32: William | C32: Bowman | D32: Male | E32: 1997-09-22 | F32: Married | G32: D03 | H32: Engineering | I32: JT14 | J32: Engineering Manager | K32: Manager | L32: L09 | M32: E06 | N32: EMP0912 | O32: 2025-08-15 | Q32: Active | S32: No | T32: 110000 | U32: 0 | V32: No | W32: Onsite | X32: Rarely | Y32: 17 | Z32: 3 | AA32: Job Portal | AB32: 0.77 | AC32: 0.83 | AD32: 0.51 | AE32: 51 | AF32: 7 | AG32: 2 | AH32: 1 | AI32: 3 | AJ32: 4 | AK32: 2 | AL32: 3 | AM32: 56 | AN32: Yes | AO32: Standard | AP32: Yes | AQ32: =B32&" "&C32 -> William Bowman | AR32: =DATEDIF(E32,ReadMe!$C$7,"y") -> 28 | AS32: =ROUND(DATEDIF(O32,IF(Q32="Active",ReadMe!$C$7,P32),"m")/12,2) -> 1
A33: EMP0032 | B33: Kristin | C33: Cohen | D33: Female | E33: 1990-03-07 | F33: Single | G33: D05 | H33: Human Resources | I33: JT23 | J33: Director of Human Resources | K33: Director | L33: L08 | M33: E18 | N33: EMP0258 | O33: 2024-06-09 | Q33: Active | S33: No | T33: 151600 | U33: 1 | V33: No | W33: Hybrid | X33: Rarely | Y33: 8 | Z33: 1 | AA33: Employee Referral | AB33: 0.75 | AC33: 1.75 | AD33: 0.03 | AE33: 21 | AF33: 2 | AG33: 14 | AH33: 3 | AI33: 2 | AJ33: 2 | AK33: 3 | AL33: 2 | AM33: 66 | AN33: Yes | AO33: Basic | AP33: No | AQ33: =B33&" "&C33 -> Kristin Cohen | AR33: =DATEDIF(E33,ReadMe!$C$7,"y") -> 36 | AS33: =ROUND(DATEDIF(O33,IF(Q33="Active",ReadMe!$C$7,P33),"m")/12,2) -> 2.17
A34: EMP0033 | B34: Ryan | C34: Parsons | D34: Male | E34: 1991-08-07 | F34: Widowed | G34: D03 | H34: Engineering | I34: JT15 | J34: Director of Engineering | K34: Director | L34: L09 | M34: E31 | N34: EMP0269 | O34: 2026-06-05 | Q34: Active | S34: No | T34: 185600 | U34: 1 | V34: No | W34: Hybrid | X34: Rarely | Y34: 31 | Z34: 0 | AA34: Recruitment Agency | AB34: 0.01 | AC34: 0.03 | AD34: 0.03 | AE34: 57 | AF34: 0 | AG34: 16 | AH34: 3 | AI34: 2 | AJ34: 4 | AK34: 3 | AL34: 2 | AM34: 74 | AN34: Yes | AO34: Basic | AP34: Yes | AQ34: =B34&" "&C34 -> Ryan Parsons | AR34: =DATEDIF(E34,ReadMe!$C$7,"y") -> 35 | AS34: =ROUND(DATEDIF(O34,IF(Q34="Active",ReadMe!$C$7,P34),"m")/12,2) -> 0.17
A35: EMP0034 | B35: Daryl | C35: Johnson | D35: Male | E35: 1985-07-04 | F35: Married | G35: D01 | H35: Sales | I35: JT05 | J35: Director of Sales | K35: Director | L35: L05 | M35: E35 | N35: EMP0855 | O35: 2025-09-30 | Q35: Active | S35: No | T35: 170800 | U35: 2 | V35: No | W35: Onsite | Y35: 6 | Z35: 1 | AA35: Campus Hiring | AB35: 0.35 | AC35: 0.51 | AD35: 0.68 | AE35: 38 | AF35: 2 | AG35: 17 | AH35: 3 | AI35: 4 | AJ35: 2 | AK35: 2 | AL35: 4 | AM35: 87 | AN35: Yes | AO35: Premium | AP35: Yes | AQ35: =B35&" "&C35 -> Daryl Johnson | AR35: =DATEDIF(E35,ReadMe!$C$7,"y") -> 41 | AS35: =ROUND(DATEDIF(O35,IF(Q35="Active",ReadMe!$C$7,P35),"m")/12,2) -> 0.83
A36: EMP0035 | B36: Emily | C36: Adams | D36: Female | E36: 1988-08-09 | F36: Divorced | G36: D10 | H36: Executive | I36: JT36 | J36: Chief Financial Officer | K36: Executive | L36: L13 | M36: E29 | O36: 2018-04-05 | Q36: Active | S36: No | T36: 257000 | U36: 0 | V36: No | W36: Onsite | Y36: 16 | Z36: 3 | AA36: Career Fair | AB36: 7.14 | AC36: 5.56 | AD36: 3.37 | AE36: 20 | AF36: 1 | AG36: 7 | AH36: 2 | AI36: 4 | AJ36: 2 | AK36: 3 | AL36: 2 | AM36: 87 | AN36: Yes | AO36: Basic | AP36: No | AQ36: =B36&" "&C36 -> Emily Adams | AR36: =DATEDIF(E36,ReadMe!$C$7,"y") -> 38 | AS36: =ROUND(DATEDIF(O36,IF(Q36="Active",ReadMe!$C$7,P36),"m")/12,2) -> 8.33
A37: EMP0036 | B37: Daniel | C37: Hahn | D37: Male | E37: 1991-10-16 | F37: Married | G37: D03 | H37: Engineering | I37: JT14 | J37: Engineering Manager | K37: Manager | L37: L04 | M37: E26 | N37: EMP1000 | O37: 2019-07-24 | Q37: Active | S37: No | T37: 138700 | U37: 0 | V37: No | W37: Onsite | Y37: 26 | Z37: 4 | AA37: Campus Hiring | AB37: 3.96 | AC37: 4.33 | AD37: 1.07 | AE37: 37 | AF37: 0 | AG37: 39 | AH37: 4 | AI37: 4 | AJ37: 3 | AK37: 2 | AL37: 3 | AM37: 73 | AN37: Yes | AO37: Premium | AP37: No | AQ37: =B37&" "&C37 -> Daniel Hahn | AR37: =DATEDIF(E37,ReadMe!$C$7,"y") -> 34 | AS37: =ROUND(DATEDIF(O37,IF(Q37="Active",ReadMe!$C$7,P37),"m")/12,2) -> 7
A38: EMP0037 | B38: Sherri | C38: Edwards | D38: Female | E38: 1996-03-10 | F38: Married | G38: D08 | H38: Customer Support | I38: JT31 | J38: Senior Support Representative | K38: Senior | L38: L02 | M38: E28 | N38: EMP0885 | O38: 2019-01-10 | Q38: Active | S38: No | T38: 103000 | U38: 1 | V38: Yes | W38: Remote | Y38: 5 | Z38: 2 | AA38: Job Portal | AB38: 4.42 | AC38: 4.52 | AD38: 3.35 | AE38: 39 | AF38: 0 | AG38: 15 | AH38: 4 | AI38: 1 | AJ38: 2 | AK38: 3 | AL38: 3 | AM38: 47 | AN38: Yes | AO38: Standard | AP38: No | AQ38: =B38&" "&C38 -> Sherri Edwards | AR38: =DATEDIF(E38,ReadMe!$C$7,"y") -> 30 | AS38: =ROUND(DATEDIF(O38,IF(Q38="Active",ReadMe!$C$7,P38),"m")/12,2) -> 7.58
A39: EMP0038 | B39: Mary | C39: Foster | D39: Female | E39: 2002-02-12 | F39: Married | G39: D07 | H39: Operations | I39: JT28 | J39: Operations Analyst | K39: Entry | L39: L15 | M39: E06 | N39: EMP0229 | O39: 2022-06-29 | P39: 2025-04-26 | Q39: Terminated | R39: Voluntary - Relocation | S39: Yes | T39: 52000 | U39: 0 | V39: Yes | W39: Onsite | X39: Rarely | Y39: 1 | Z39: 3 | AA39: Campus Hiring | AB39: 0.03 | AC39: 0.56 | AD39: 0.74 | AE39: 10 | AF39: 11 | AG39: 1 | AH39: 2 | AI39: 1 | AJ39: 2 | AK39: 4 | AL39: 4 | AM39: 78 | AN39: Yes | AO39: Basic | AP39: Yes | AQ39: =B39&" "&C39 -> Mary Foster | AR39: =DATEDIF(E39,ReadMe!$C$7,"y") -> 24 | AS39: =ROUND(DATEDIF(O39,IF(Q39="Active",ReadMe!$C$7,P39),"m")/12,2) -> 2.75
A40: EMP0039 | B40: Suzanne | C40: Ellis | D40: Female | E40: 1987-04-10 | F40: Divorced | G40: D10 | H40: Executive | I40: JT35 | J40: Chief Executive Officer | K40: Executive | L40: L11 | M40: E10 | O40: 2022-10-07 | Q40: Active | S40: No | T40: 323700 | U40: 0 | V40: No | W40: Hybrid | Y40: 1 | Z40: 1 | AA40: Employee Referral | AB40: 2.84 | AC40: 2.58 | AD40: 2.05 | AE40: 14 | AF40: 0 | AG40: 37 | AH40: 3 | AI40: 2 | AJ40: 3 | AK40: 3 | AL40: 2 | AM40: 73 | AN40: Yes | AO40: Basic | AP40: No | AQ40: =B40&" "&C40 -> Suzanne Ellis | AR40: =DATEDIF(E40,ReadMe!$C$7,"y") -> 39 | AS40: =ROUND(DATEDIF(O40,IF(Q40="Active",ReadMe!$C$7,P40),"m")/12,2) -> 3.83
A41: EMP0040 | B41: Deborah | C41: Wright | D41: Female | E41: 1988-05-30 | F41: Single | G41: D09 | H41: Legal | I41: JT34 | J41: General Counsel | K41: Director | L41: L13 | M41: E25 | N41: EMP0447 | O41: 2021-01-15 | P41: 2024-08-18 | Q41: Terminated | R41: Voluntary - Career Change | S41: Yes | T41: 193400 | U41: 1 | V41: No | W41: Onsite | X41: Frequently | Y41: 7 | Z41: 1 | AA41: Campus Hiring | AB41: 1.39 | AC41: 1.83 | AD41: 4.45 | AE41: 42 | AF41: 18 | AG41: 6 | AH41: 3 | AI41: 3 | AJ41: 2 | AK41: 2 | AL41: 2 | AM41: 76 | AN41: No | AO41: Basic | AP41: No | AQ41: =B41&" "&C41 -> Deborah Wright | AR41: =DATEDIF(E41,ReadMe!$C$7,"y") -> 38 | AS41: =ROUND(DATEDIF(O41,IF(Q41="Active",ReadMe!$C$7,P41),"m")/12,2) -> 3.58
A42: EMP0041 | B42: Justin | C42: Baker | D42: Male | E42: 2002-08-04 | F42: Married | G42: D08 | H42: Customer Support | I42: JT30 | J42: Customer Support Representative | K42: Entry | L42: L11 | M42: E16 | N42: EMP0826 | O42: 2023-10-19 | Q42: Active | S42: No | T42: 41800 | U42: 0 | V42: Yes | W42: Onsite | X42: Rarely | Y42: 1 | Z42: 0 | AA42: Job Portal | AB42: 0.08 | AC42: 1.54 | AD42: 0.64 | AE42: 23 | AF42: 6 | AG42: 4 | AH42: 4 | AI42: 3 | AJ42: 1 | AK42: 3 | AL42: 4 | AM42: 81 | AN42: No | AO42: Standard | AP42: Yes | AQ42: =B42&" "&C42 -> Justin Baker | AR42: =DATEDIF(E42,ReadMe!$C$7,"y") -> 24 | AS42: =ROUND(DATEDIF(O42,IF(Q42="Active",ReadMe!$C$7,P42),"m")/12,2) -> 2.83
A43: EMP0042 | B43: Lauren | C43: Hurst | D43: Female | E43: 2002-03-10 | F43: Widowed | G43: D02 | H43: Marketing | I43: JT07 | J43: Marketing Specialist | K43: Mid | L43: L14 | M43: E40 | N43: EMP0308 | O43: 2023-12-23 | Q43: Active | S43: No | T43: 78700 | U43: 1 | V43: Yes | W43: Onsite | X43: Rarely | Y43: 5 | Z43: 3 | AA43: Job Portal | AB43: 2.37 | AC43: 0.65 | AD43: 2.19 | AE43: 53 | AF43: 6 | AG43: 2 | AH43: 2 | AI43: 4 | AJ43: 3 | AK43: 4 | AL43: 3 | AM43: 54 | AN43: Yes | AO43: Standard | AP43: Yes | AQ43: =B43&" "&C43 -> Lauren Hurst | AR43: =DATEDIF(E43,ReadMe!$C$7,"y") -> 24 | AS43: =ROUND(DATEDIF(O43,IF(Q43="Active",ReadMe!$C$7,P43),"m")/12,2) -> 2.58
A44: EMP0043 | B44: Jennifer | C44: Robinson | D44: Female | E44: 1984-06-26 | F44: Divorced | G44: D06 | H44: Finance | I44: JT26 | J44: Finance Manager | K44: Manager | L44: L05 | M44: E03 | N44: EMP0925 | O44: 2024-05-17 | Q44: Active | S44: No | T44: 109800 | U44: 2 | V44: No | W44: Onsite | Y44: 2 | Z44: 2 | AA44: Campus Hiring | AB44: 0.54 | AC44: 1.67 | AD44: 1 | AE44: 33 | AF44: 5 | AG44: 11 | AH44: 3 | AI44: 3 | AJ44: 2 | AK44: 2 | AL44: 4 | AM44: 51 | AN44: Yes | AO44: Standard | AP44: Yes | AQ44: =B44&" "&C44 -> Jennifer Robinson | AR44: =DATEDIF(E44,ReadMe!$C$7,"y") -> 42 | AS44: =ROUND(DATEDIF(O44,IF(Q44="Active",ReadMe!$C$7,P44),"m")/12,2) -> 2.25
A45: EMP0044 | B45: Zachary | C45: Hicks | D45: Male | E45: 1997-04-03 | F45: Widowed | G45: D05 | H45: Human Resources | I45: JT21 | J45: Senior HR Business Partner | K45: Senior | L45: L06 | M45: E45 | N45: EMP0330 | O45: 2023-12-09 | Q45: Active | S45: No | T45: 78000 | U45: 1 | V45: Yes | W45: Onsite | Y45: 1 | Z45: 1 | AA45: Company Website | AB45: 1.4 | AC45: 0.23 | AD45: 1.89 | AE45: 33 | AF45: 4 | AG45: 5 | AH45: 2 | AI45: 2 | AJ45: 3 | AK45: 3 | AL45: 4 | AM45: 57 | AN45: Yes | AO45: Standard | AP45: Yes | AQ45: =B45&" "&C45 -> Zachary Hicks | AR45: =DATEDIF(E45,ReadMe!$C$7,"y") -> 29 | AS45: =ROUND(DATEDIF(O45,IF(Q45="Active",ReadMe!$C$7,P45),"m")/12,2) -> 2.67
A46: EMP0045 | B46: Ann | C46: Williams | D46: Female | E46: 1995-06-03 | F46: Single | G46: D07 | H46: Operations | I46: JT29 | J46: Operations Manager | K46: Manager | L46: L07 | M46: E46 | N46: EMP0649 | O46: 2020-04-24 | Q46: Active | S46: No | T46: 118700 | U46: 0 | V46: No | W46: Remote | Y46: 12 | Z46: 2 | AA46: Career Fair | AB46: 0.77 | AC46: 3.49 | AD46: 4.18 | AE46: 42 | AF46: 2 | AG46: 20 | AH46: 2 | AI46: 3 | AJ46: 3 | AK46: 3 | AL46: 3 | AM46: 71 | AN46: Yes | AO46: Premium | AP46: No | AQ46: =B46&" "&C46 -> Ann Williams | AR46: =DATEDIF(E46,ReadMe!$C$7,"y") -> 31 | AS46: =ROUND(DATEDIF(O46,IF(Q46="Active",ReadMe!$C$7,P46),"m")/12,2) -> 6.25
A47: EMP0046 | B47: Brian | C47: Burton | D47: Male | E47: 1996-03-22 | F47: Single | G47: D04 | H47: Information Technology | I47: JT17 | J47: Systems Administrator | K47: Mid | L47: L09 | M47: E12 | N47: EMP0626 | O47: 2024-05-04 | P47: 2024-09-18 | Q47: Terminated | R47: Voluntary - Further Education | S47: Yes | T47: 60900 | U47: 2 | V47: Yes | W47: Onsite | Y47: 11 | Z47: 1 | AA47: Campus Hiring | AB47: 1.48 | AC47: 0.46 | AD47: 0.09 | AE47: 28 | AF47: 1 | AG47: 3 | AH47: 2 | AI47: 2 | AJ47: 2 | AK47: 2 | AL47: 5 | AM47: 67 | AN47: Yes | AO47: Basic | AP47: No | AQ47: =B47&" "&C47 -> Brian Burton | AR47: =DATEDIF(E47,ReadMe!$C$7,"y") -> 30 | AS47: =ROUND(DATEDIF(O47,IF(Q47="Active",ReadMe!$C$7,P47),"m")/12,2) -> 0.33
A48: EMP0047 | B48: Rebecca | C48: Henderson | D48: Female | E48: 1977-05-25 | F48: Single | G48: D10 | H48: Executive | I48: JT38 | J48: Chief People Officer | K48: Executive | L48: L04 | M48: E44 | O48: 2019-08-20 | Q48: Active | S48: No | T48: 295600 | U48: 3 | V48: No | W48: Onsite | Y48: 7 | Z48: 0 | AA48: Career Fair | AB48: 0.05 | AC48: 0.17 | AD48: 3.64 | AE48: 23 | AF48: 8 | AG48: 5 | AH48: 3 | AI48: 2 | AJ48: 3 | AK48: 2 | AL48: 2 | AM48: 78 | AN48: Yes | AP48: Yes | AQ48: =B48&" "&C48 -> Rebecca Henderson | AR48: =DATEDIF(E48,ReadMe!$C$7,"y") -> 49 | AS48: =ROUND(DATEDIF(O48,IF(Q48="Active",ReadMe!$C$7,P48),"m")/12,2) -> 7
A49: EMP0048 | B49: Arthur | C49: James | D49: Male | E49: 1983-01-26 | F49: Single | G49: D03 | H49: Engineering | I49: JT13 | J49: Lead Software Engineer | K49: Lead | L49: L13 | M49: E43 | N49: EMP0571 | O49: 2023-12-10 | Q49: Active | S49: No | T49: 131600 | U49: 0 | V49: Yes | W49: Remote | Y49: 3 | Z49: 2 | AA49: Campus Hiring | AB49: 1.36 | AC49: 0.41 | AD49: 0.65 | AE49: 12 | AF49: 5 | AG49: 21 | AH49: 1 | AI49: 4 | AJ49: 2 | AK49: 3 | AL49: 3 | AM49: 79 | AN49: Yes | AO49: Basic | AP49: Yes | AQ49: =B49&" "&C49 -> Arthur James | AR49: =DATEDIF(E49,ReadMe!$C$7,"y") -> 43 | AS49: =ROUND(DATEDIF(O49,IF(Q49="Active",ReadMe!$C$7,P49),"m")/12,2) -> 2.67
A50: EMP0049 | B50: Whitney | C50: Rice | D50: Female | E50: 1988-12-01 | F50: Widowed | G50: D01 | H50: Sales | I50: JT04 | J50: Sales Manager | K50: Manager | L50: L06 | M50: E41 | N50: EMP0913 | O50: 2017-04-23 | Q50: Active | S50: No | T50: 118200 | U50: 0 | V50: No | W50: Hybrid | X50: Frequently | Y50: 17 | Z50: 2 | AA50: Career Fair | AB50: 6.83 | AC50: 2.81 | AD50: 3.69 | AE50: 34 | AF50: 0 | AG50: 35 | AH50: 2 | AI50: 3 | AJ50: 3 | AK50: 3 | AL50: 4 | AM50: 78 | AN50: Yes | AP50: Yes | AQ50: =B50&" "&C50 -> Whitney Rice | AR50: =DATEDIF(E50,ReadMe!$C$7,"y") -> 37 | AS50: =ROUND(DATEDIF(O50,IF(Q50="Active",ReadMe!$C$7,P50),"m")/12,2) -> 9.25
A51: EMP0050 | B51: Wesley | C51: Valencia | D51: Male | E51: 1982-06-11 | F51: Divorced | G51: D10 | H51: Executive | I51: JT37 | J51: Chief Technology Officer | K51: Executive | L51: L10 | M51: E43 | O51: 2019-04-15 | Q51: Active | S51: No | T51: 273500 | U51: 1 | V51: No | W51: Onsite | Y51: 14 | Z51: 3 | AA51: Career Fair | AB51: 6.26 | AC51: 0.96 | AD51: 2.07 | AE51: 37 | AF51: 6 | AG51: 71 | AH51: 1 | AI51: 3 | AJ51: 2 | AK51: 4 | AL51: 5 | AM51: 79 | AN51: Yes | AO51: Standard | AP51: No | AQ51: =B51&" "&C51 -> Wesley Valencia | AR51: =DATEDIF(E51,ReadMe!$C$7,"y") -> 44 | AS51: =ROUND(DATEDIF(O51,IF(Q51="Active",ReadMe!$C$7,P51),"m")/12,2) -> 7.33
A52: EMP0051 | B52: Adam | C52: Le | D52: Male | E52: 2005-04-25 | F52: Divorced | G52: D03 | H52: Engineering | I52: JT10 | J52: Software Engineer I | K52: Entry | L52: L07 | M52: E10 | N52: EMP0241 | O52: 2026-04-05 | Q52: Active | S52: No | T52: 47700 | U52: 2 | V52: Yes | W52: Hybrid | X52: Frequently | Y52: 9 | Z52: 1 | AA52: Recruitment Agency | AB52: 0.01 | AC52: 0.27 | AD52: 0.12 | AE52: 43 | AF52: 8 | AG52: 26 | AH52: 3 | AI52: 2 | AJ52: 3 | AK52: 2 | AL52: 3 | AM52: 83 | AN52: Yes | AO52: Standard | AP52: Yes | AQ52: =B52&" "&C52 -> Adam Le | AR52: =DATEDIF(E52,ReadMe!$C$7,"y") -> 21 | AS52: =ROUND(DATEDIF(O52,IF(Q52="Active",ReadMe!$C$7,P52),"m")/12,2) -> 0.33
A53: EMP0052 | B53: Melanie | C53: Herrera | D53: Female | E53: 1995-02-13 | F53: Widowed | G53: D09 | H53: Legal | I53: JT33 | J53: Legal Counsel | K53: Senior | L53: L10 | M53: E08 | N53: EMP0426 | O53: 2020-02-03 | P53: 2024-11-27 | Q53: Terminated | R53: Voluntary - Further Education | S53: Yes | T53: 83100 | U53: 2 | V53: Yes | W53: Onsite | Y53: 1 | Z53: 0 | AA53: Campus Hiring | AB53: 5.96 | AC53: 5.83 | AD53: 5.64 | AE53: 30 | AF53: 1 | AG53: 17 | AH53: 2 | AI53: 2 | AJ53: 2 | AK53: 3 | AL53: 2 | AM53: 66 | AN53: Yes | AO53: Premium | AP53: Yes | AQ53: =B53&" "&C53 -> Melanie Herrera | AR53: =DATEDIF(E53,ReadMe!$C$7,"y") -> 31 | AS53: =ROUND(DATEDIF(O53,IF(Q53="Active",ReadMe!$C$7,P53),"m")/12,2) -> 4.75
A54: EMP0053 | B54: Derek | C54: Davidson | D54: Male | E54: 1988-09-07 | F54: Divorced | G54: D10 | H54: Executive | I54: JT36 | J54: Chief Financial Officer | K54: Executive | L54: L04 | M54: E49 | O54: 2025-08-26 | Q54: Active | S54: No | T54: 290100 | U54: 0 | V54: No | W54: Onsite | X54: Rarely | Y54: 9 | Z54: 4 | AA54: Job Portal | AB54: 0.01 | AC54: 0.18 | AD54: 0.12 | AE54: 3 | AF54: 5 | AG54: 28 | AH54: 2 | AI54: 3 | AJ54: 3 | AK54: 3 | AL54: 3 | AM54: 65 | AN54: Yes | AO54: Basic | AP54: Yes | AQ54: =B54&" "&C54 -> Derek Davidson | AR54: =DATEDIF(E54,ReadMe!$C$7,"y") -> 37 | AS54: =ROUND(DATEDIF(O54,IF(Q54="Active",ReadMe!$C$7,P54),"m")/12,2) -> 0.92
A55: EMP0054 | B55: Brian | C55: Graham | D55: Male | E55: 2003-01-24 | F55: Married | G55: D05 | H55: Human Resources | I55: JT19 | J55: HR Coordinator | K55: Entry | L55: L11 | M55: E01 | N55: EMP0920 | O55: 2024-04-06 | Q55: Active | S55: No | T55: 55100 | U55: 0 | V55: Yes | W55: Onsite | Y55: 1 | Z55: 2 | AA55: Job Portal | AB55: 1.23 | AC55: 0.31 | AD55: 0.56 | AE55: 27 | AF55: 4 | AG55: 22 | AH55: 2 | AI55: 2 | AJ55: 3 | AK55: 3 | AL55: 3 | AM55: 72 | AN55: Yes | AO55: Basic | AP55: Yes | AQ55: =B55&" "&C55 -> Brian Graham | AR55: =DATEDIF(E55,ReadMe!$C$7,"y") -> 23 | AS55: =ROUND(DATEDIF(O55,IF(Q55="Active",ReadMe!$C$7,P55),"m")/12,2) -> 2.33
A56: EMP0055 | B56: Jody | C56: Mckay | D56: Female | E56: 1986-03-11 | F56: Married | G56: D01 | H56: Sales | I56: JT05 | J56: Director of Sales | K56: Director | L56: L07 | M56: E24 | N56: EMP0861 | O56: 2020-01-20 | Q56: Active | S56: No | T56: 141600 | U56: 0 | V56: No | W56: Hybrid | Y56: 4 | Z56: 0 | AA56: Recruitment Agency | AB56: 1.35 | AC56: 3.15 | AD56: 0.63 | AE56: 25 | AF56: 3 | AG56: 3 | AH56: 2 | AI56: 4 | AJ56: 2 | AK56: 2 | AL56: 4 | AM56: 56 | AN56: Yes | AP56: Yes | AQ56: =B56&" "&C56 -> Jody Mckay | AR56: =DATEDIF(E56,ReadMe!$C$7,"y") -> 40 | AS56: =ROUND(DATEDIF(O56,IF(Q56="Active",ReadMe!$C$7,P56),"m")/12,2) -> 6.58
A57: EMP0056 | B57: Shawn | C57: Baker | D57: Male | E57: 2003-10-27 | F57: Widowed | G57: D05 | H57: Human Resources | I57: JT21 | J57: Senior HR Business Partner | K57: Senior | L57: L02 | M57: E20 | N57: EMP0187 | O57: 2025-06-21 | P57: 2026-04-26 | Q57: Terminated | R57: Voluntary - Further Education | S57: Yes | T57: 108800 | U57: 0 | V57: Yes | W57: Hybrid | Y57: 5 | Z57: 1 | AA57: Job Portal | AB57: 0.82 | AC57: 0.15 | AD57: 1.13 | AE57: 27 | AF57: 1 | AG57: 46 | AH57: 2 | AI57: 3 | AJ57: 3 | AK57: 2 | AL57: 2 | AM57: 100 | AN57: No | AO57: Standard | AP57: Yes | AQ57: =B57&" "&C57 -> Shawn Baker | AR57: =DATEDIF(E57,ReadMe!$C$7,"y") -> 22 | AS57: =ROUND(DATEDIF(O57,IF(Q57="Active",ReadMe!$C$7,P57),"m")/12,2) -> 0.83
A58: EMP0057 | B58: Kathryn | C58: White | D58: Female | E58: 1986-02-17 | F58: Single | G58: D01 | H58: Sales | I58: JT05 | J58: Director of Sales | K58: Director | L58: L02 | M58: E42 | N58: EMP0084 | O58: 2023-07-20 | Q58: Active | S58: No | T58: 158000 | U58: 1 | V58: No | W58: Remote | Y58: 38 | Z58: 2 | AA58: Job Portal | AB58: 0.37 | AC58: 1.51 | AD58: 0.73 | AE58: 38 | AF58: 10 | AG58: 58 | AH58: 2 | AI58: 4 | AJ58: 3 | AK58: 3 | AL58: 1 | AM58: 48 | AN58: Yes | AO58: Standard | AP58: Yes | AQ58: =B58&" "&C58 -> Kathryn White | AR58: =DATEDIF(E58,ReadMe!$C$7,"y") -> 40 | AS58: =ROUND(DATEDIF(O58,IF(Q58="Active",ReadMe!$C$7,P58),"m")/12,2) -> 3.08
A59: EMP0058 | B59: Susan | C59: Harrell | D59: Female | E59: 1997-09-28 | F59: Married | G59: D02 | H59: Marketing | I59: JT08 | J59: Senior Marketing Specialist | K59: Senior | L59: L02 | M59: E08 | N59: EMP0205 | O59: 2026-04-11 | Q59: Active | S59: No | T59: 80300 | U59: 0 | V59: Yes | W59: Onsite | X59: Rarely | Y59: 27 | Z59: 1 | AA59: LinkedIn | AB59: 0.32 | AC59: 0.19 | AD59: 0.13 | AE59: 23 | AF59: 13 | AG59: 57 | AH59: 3 | AI59: 4 | AJ59: 3 | AK59: 2 | AL59: 3 | AM59: 60 | AN59: Yes | AO59: Premium | AP59: No | AQ59: =B59&" "&C59 -> Susan Harrell | AR59: =DATEDIF(E59,ReadMe!$C$7,"y") -> 28 | AS59: =ROUND(DATEDIF(O59,IF(Q59="Active",ReadMe!$C$7,P59),"m")/12,2) -> 0.33
A60: EMP0059 | B60: Elizabeth | C60: Fowler | D60: Female | E60: 2002-11-11 | F60: Single | G60: D03 | H60: Engineering | I60: JT11 | J60: Software Engineer II | K60: Mid | L60: L09 | M60: E38 | N60: EMP0786 | O60: 2023-02-23 | Q60: Active | S60: No | T60: 71700 | U60: 0 | V60: Yes | W60: Onsite | Y60: 13 | Z60: 2 | AA60: Career Fair | AB60: 1.79 | AC60: 2.69 | AD60: 0.46 | AE60: 19 | AF60: 2 | AG60: 23 | AH60: 3 | AI60: 2 | AJ60: 3 | AK60: 3 | AL60: 2 | AM60: 47 | AN60: Yes | AO60: Standard | AP60: Yes | AQ60: =B60&" "&C60 -> Elizabeth Fowler | AR60: =DATEDIF(E60,ReadMe!$C$7,"y") -> 23 | AS60: =ROUND(DATEDIF(O60,IF(Q60="Active",ReadMe!$C$7,P60),"m")/12,2) -> 3.42
A61: EMP0060 | B61: Lee | C61: Hernandez | D61: Male | E61: 1988-07-05 | F61: Widowed | G61: D08 | H61: Customer Support | I61: JT32 | J61: Customer Support Manager | K61: Manager | L61: L03 | M61: E19 | N61: EMP0930 | O61: 2020-12-29 | Q61: Active | S61: No | T61: 143200 | U61: 1 | V61: No | W61: Hybrid | X61: Frequently | Y61: 1 | Z61: 2 | AA61: Company Website | AB61: 0.34 | AC61: 3.15 | AD61: 4.38 | AE61: 42 | AF61: 1 | AG61: 26 | AH61: 3 | AI61: 2 | AJ61: 3 | AK61: 2 | AL61: 1 | AM61: 65 | AN61: Yes | AO61: Standard | AP61: No | AQ61: =B61&" "&C61 -> Lee Hernandez | AR61: =DATEDIF(E61,ReadMe!$C$7,"y") -> 38 | AS61: =ROUND(DATEDIF(O61,IF(Q61="Active",ReadMe!$C$7,P61),"m")/12,2) -> 5.58
A62: EMP0061 | B62: Pamela | C62: Ryan | D62: Female | E62: 1999-10-10 | F62: Single | G62: D06 | H62: Finance | I62: JT24 | J62: Financial Analyst | K62: Entry | L62: L13 | M62: E33 | N62: EMP0615 | O62: 2024-10-03 | Q62: Active | S62: No | T62: 49800 | U62: 0 | V62: Yes | W62: Onsite | Y62: 4 | Z62: 1 | AA62: Job Portal | AB62: 1.46 | AC62: 0.05 | AD62: 0.9 | AE62: 35 | AF62: 5 | AG62: 34 | AH62: 3 | AI62: 4 | AJ62: 4 | AK62: 3 | AL62: 4 | AM62: 76 | AN62: Yes | AO62: Premium | AP62: No | AQ62: =B62&" "&C62 -> Pamela Ryan | AR62: =DATEDIF(E62,ReadMe!$C$7,"y") -> 26 | AS62: =ROUND(DATEDIF(O62,IF(Q62="Active",ReadMe!$C$7,P62),"m")/12,2) -> 1.83
A63: EMP0062 | B63: Richard | C63: Moreno | D63: Male | E63: 1991-07-25 | F63: Widowed | G63: D03 | H63: Engineering | I63: JT14 | J63: Engineering Manager | K63: Manager | L63: L08 | M63: E43 | N63: EMP0444 | O63: 2021-08-12 | P63: 2024-03-19 | Q63: Terminated | R63: Involuntary - Performance | S63: Yes | T63: 128100 | U63: 0 | V63: No | W63: Hybrid | X63: Rarely | Y63: 24 | Z63: 1 | AA63: Company Website | AB63: 3.43 | AC63: 1.18 | AD63: 0.31 | AE63: 0 | AF63: 5 | AG63: 49 | AH63: 1 | AI63: 3 | AJ63: 4 | AK63: 2 | AL63: 3 | AM63: 73 | AN63: Yes | AP63: No | AQ63: =B63&" "&C63 -> Richard Moreno | AR63: =DATEDIF(E63,ReadMe!$C$7,"y") -> 35 | AS63: =ROUND(DATEDIF(O63,IF(Q63="Active",ReadMe!$C$7,P63),"m")/12,2) -> 2.58
A64: EMP0063 | B64: April | C64: Nguyen | D64: Female | E64: 1987-12-06 | F64: Widowed | G64: D05 | H64: Human Resources | I64: JT23 | J64: Director of Human Resources | K64: Director | L64: L07 | M64: E08 | N64: EMP0942 | O64: 2017-07-29 | Q64: Active | S64: No | T64: 149700 | U64: 0 | V64: No | W64: Onsite | X64: Rarely | Y64: 1 | Z64: 3 | AA64: Campus Hiring | AB64: 0.18 | AC64: 5.16 | AD64: 4 | AE64: 0 | AF64: 12 | AG64: 34 | AH64: 3 | AI64: 3 | AJ64: 3 | AK64: 2 | AL64: 3 | AM64: 67 | AN64: Yes | AO64: Basic | AP64: Yes | AQ64: =B64&" "&C64 -> April Nguyen | AR64: =DATEDIF(E64,ReadMe!$C$7,"y") -> 38 | AS64: =ROUND(DATEDIF(O64,IF(Q64="Active",ReadMe!$C$7,P64),"m")/12,2) -> 9
A65: EMP0064 | B65: Alicia | C65: Hickman | D65: Female | E65: 1997-04-12 | F65: Widowed | G65: D05 | H65: Human Resources | I65: JT20 | J65: HR Business Partner | K65: Mid | L65: L15 | M65: E34 | N65: EMP0089 | O65: 2023-05-25 | Q65: Active | S65: No | T65: 73300 | U65: 1 | V65: Yes | W65: Onsite | X65: Rarely | Y65: 1 | Z65: 5 | AA65: LinkedIn | AB65: 0.36 | AC65: 1.9 | AD65: 2.7 | AE65: 24 | AF65: 1 | AG65: 5 | AH65: 2 | AI65: 3 | AJ65: 2 | AK65: 3 | AL65: 3 | AM65: 78 | AN65: Yes | AO65: Basic | AP65: Yes | AQ65: =B65&" "&C65 -> Alicia Hickman | AR65: =DATEDIF(E65,ReadMe!$C$7,"y") -> 29 | AS65: =ROUND(DATEDIF(O65,IF(Q65="Active",ReadMe!$C$7,P65),"m")/12,2) -> 3.17
A66: EMP0065 | B66: Shawn | C66: Decker | D66: Male | E66: 1984-09-22 | F66: Married | G66: D01 | H66: Sales | I66: JT04 | J66: Sales Manager | K66: Manager | L66: L08 | M66: E06 | N66: EMP0333 | O66: 2023-03-11 | Q66: Active | S66: No | T66: 123500 | U66: 0 | V66: No | W66: Onsite | X66: Rarely | Y66: 8 | Z66: 2 | AA66: Job Portal | AB66: 2.86 | AC66: 3.29 | AD66: 1.8 | AE66: 42 | AF66: 2 | AG66: 3 | AH66: 3 | AI66: 2 | AJ66: 3 | AK66: 2 | AL66: 2 | AM66: 81 | AN66: No | AO66: Standard | AP66: Yes | AQ66: =B66&" "&C66 -> Shawn Decker | AR66: =DATEDIF(E66,ReadMe!$C$7,"y") -> 41 | AS66: =ROUND(DATEDIF(O66,IF(Q66="Active",ReadMe!$C$7,P66),"m")/12,2) -> 3.42
A67: EMP0066 | B67: Eric | C67: Brown | D67: Male | E67: 1990-10-28 | F67: Married | G67: D10 | H67: Executive | I67: JT35 | J67: Chief Executive Officer | K67: Executive | L67: L03 | M67: E16 | O67: 2019-12-11 | Q67: Active | S67: No | T67: 260800 | U67: 0 | V67: No | W67: Onsite | Y67: 8 | Z67: 1 | AA67: Employee Referral | AB67: 3.12 | AC67: 4.01 | AD67: 6.07 | AE67: 47 | AF67: 0 | AG67: 37 | AH67: 2 | AI67: 2 | AJ67: 3 | AK67: 3 | AL67: 3 | AM67: 69 | AN67: Yes | AO67: Standard | AP67: Yes | AQ67: =B67&" "&C67 -> Eric Brown | AR67: =DATEDIF(E67,ReadMe!$C$7,"y") -> 35 | AS67: =ROUND(DATEDIF(O67,IF(Q67="Active",ReadMe!$C$7,P67),"m")/12,2) -> 6.67
A68: EMP0067 | B68: Sherry | C68: Arroyo | D68: Female | E68: 2000-11-15 | F68: Single | G68: D02 | H68: Marketing | I68: JT07 | J68: Marketing Specialist | K68: Mid | L68: L15 | M68: E33 | N68: EMP0503 | O68: 2022-03-08 | Q68: Active | S68: No | T68: 65200 | U68: 0 | V68: Yes | W68: Hybrid | Y68: 9 | Z68: 4 | AA68: Employee Referral | AB68: 2.88 | AC68: 2.94 | AD68: 2.36 | AE68: 30 | AF68: 7 | AG68: 18 | AH68: 1 | AI68: 4 | AJ68: 3 | AK68: 3 | AL68: 3 | AM68: 64 | AN68: Yes | AO68: Premium | AP68: Yes | AQ68: =B68&" "&C68 -> Sherry Arroyo | AR68: =DATEDIF(E68,ReadMe!$C$7,"y") -> 25 | AS68: =ROUND(DATEDIF(O68,IF(Q68="Active",ReadMe!$C$7,P68),"m")/12,2) -> 4.42
A69: EMP0068 | B69: Angelica | C69: Tucker | D69: Female | E69: 2000-04-24 | F69: Widowed | G69: D09 | H69: Legal | I69: JT33 | J69: Legal Counsel | K69: Senior | L69: L02 | M69: E27 | N69: EMP0567 | O69: 2023-12-26 | Q69: Active | S69: No | T69: 91700 | U69: 1 | V69: Yes | W69: Remote | X69: Rarely | Y69: 3 | Z69: 3 | AA69: Company Website | AB69: 0.82 | AC69: 0.18 | AD69: 0.24 | AE69: 0 | AF69: 1 | AG69: 20 | AH69: 1 | AI69: 4 | AJ69: 2 | AK69: 3 | AL69: 4 | AM69: 88 | AN69: Yes | AO69: Premium | AP69: Yes | AQ69: =B69&" "&C69 -> Angelica Tucker | AR69: =DATEDIF(E69,ReadMe!$C$7,"y") -> 26 | AS69: =ROUND(DATEDIF(O69,IF(Q69="Active",ReadMe!$C$7,P69),"m")/12,2) -> 2.58
A70: EMP0069 | B70: Benjamin | C70: Hodges | D70: Male | E70: 1990-01-09 | F70: Single | G70: D05 | H70: Human Resources | I70: JT21 | J70: Senior HR Business Partner | K70: Senior | L70: L02 | M70: E41 | N70: EMP0739 | O70: 2023-11-06 | Q70: Active | S70: No | T70: 90000 | U70: 0 | V70: Yes | W70: Hybrid | Y70: 1 | Z70: 1 | AA70: Company Website | AB70: 1.85 | AC70: 0.98 | AD70: 1.99 | AE70: 37 | AF70: 8 | AG70: 2 | AH70: 3 | AI70: 2 | AJ70: 3 | AK70: 3 | AL70: 3 | AM70: 66 | AN70: Yes | AO70: Basic | AP70: Yes | AQ70: =B70&" "&C70 -> Benjamin Hodges | AR70: =DATEDIF(E70,ReadMe!$C$7,"y") -> 36 | AS70: =ROUND(DATEDIF(O70,IF(Q70="Active",ReadMe!$C$7,P70),"m")/12,2) -> 2.75
A71: EMP0070 | B71: Ralph | C71: Anderson | D71: Male | E71: 1988-05-27 | F71: Divorced | G71: D05 | H71: Human Resources | I71: JT21 | J71: Senior HR Business Partner | K71: Senior | L71: L11 | M71: E22 | N71: EMP0604 | O71: 2024-03-29 | Q71: Active | S71: No | T71: 103900 | U71: 2 | V71: Yes | W71: Hybrid | X71: Rarely | Y71: 1 | Z71: 0 | AA71: Employee Referral | AB71: 1.56 | AC71: 1.15 | AD71: 1.36 | AE71: 9 | AF71: 0 | AG71: 37 | AH71: 2 | AI71: 2 | AJ71: 3 | AK71: 1 | AL71: 3 | AM71: 73 | AN71: Yes | AO71: Standard | AP71: No | AQ71: =B71&" "&C71 -> Ralph Anderson | AR71: =DATEDIF(E71,ReadMe!$C$7,"y") -> 38 | AS71: =ROUND(DATEDIF(O71,IF(Q71="Active",ReadMe!$C$7,P71),"m")/12,2) -> 2.33
A72: EMP0071 | B72: John | C72: Pierce | D72: Male | E72: 1991-02-26 | F72: Single | G72: D08 | H72: Customer Support | I72: JT32 | J72: Customer Support Manager | K72: Manager | L72: L08 | M72: E33 | N72: EMP0130 | O72: 2025-01-03 | Q72: Active | S72: No | T72: 109800 | U72: 0 | V72: No | W72: Remote | Y72: 28 | Z72: 2 | AA72: Recruitment Agency | AB72: 0.05 | AC72: 1.32 | AD72: 1.54 | AE72: 16 | AF72: 0 | AG72: 21 | AH72: 2 | AI72: 3 | AJ72: 4 | AK72: 2 | AL72: 3 | AM72: 31 | AN72: Yes | AO72: Standard | AP72: Yes | AQ72: =B72&" "&C72 -> John Pierce | AR72: =DATEDIF(E72,ReadMe!$C$7,"y") -> 35 | AS72: =ROUND(DATEDIF(O72,IF(Q72="Active",ReadMe!$C$7,P72),"m")/12,2) -> 1.58
A73: EMP0072 | B73: Deborah | C73: Brennan | D73: Female | E73: 1996-10-05 | F73: Widowed | G73: D08 | H73: Customer Support | I73: JT32 | J73: Customer Support Manager | K73: Manager | L73: L13 | M73: E40 | N73: EMP0013 | O73: 2018-02-18 | Q73: Active | S73: No | T73: 142200 | U73: 0 | V73: No | W73: Onsite | Y73: 4 | Z73: 3 | AA73: Campus Hiring | AB73: 3.82 | AC73: 5.7 | AD73: 2.84 | AE73: 38 | AF73: 4 | AG73: 4 | AH73: 1 | AI73: 3 | AJ73: 3 | AK73: 2 | AL73: 4 | AM73: 76 | AN73: Yes | AO73: Standard | AP73: No | AQ73: =B73&" "&C73 -> Deborah Brennan | AR73: =DATEDIF(E73,ReadMe!$C$7,"y") -> 29 | AS73: =ROUND(DATEDIF(O73,IF(Q73="Active",ReadMe!$C$7,P73),"m")/12,2) -> 8.5
A74: EMP0073 | B74: Jenny | C74: Lewis | D74: Female | E74: 1986-08-04 | F74: Widowed | G74: D10 | H74: Executive | I74: JT37 | J74: Chief Technology Officer | K74: Executive | L74: L14 | M74: E11 | O74: 2023-09-13 | Q74: Active | S74: No | T74: 242100 | U74: 3 | V74: No | W74: Onsite | Y74: 6 | Z74: 2 | AA74: Employee Referral | AB74: 0.75 | AC74: 1.11 | AD74: 0.68 | AE74: 33 | AF74: 6 | AG74: 34 | AH74: 3 | AI74: 1 | AJ74: 1 | AK74: 3 | AL74: 3 | AM74: 68 | AN74: No | AO74: Standard | AP74: Yes | AQ74: =B74&" "&C74 -> Jenny Lewis | AR74: =DATEDIF(E74,ReadMe!$C$7,"y") -> 40 | AS74: =ROUND(DATEDIF(O74,IF(Q74="Active",ReadMe!$C$7,P74),"m")/12,2) -> 2.92
A75: EMP0074 | B75: Joshua | C75: Blair | D75: Male | E75: 1987-06-14 | F75: Married | G75: D10 | H75: Executive | I75: JT35 | J75: Chief Executive Officer | K75: Executive | L75: L09 | M75: E25 | O75: 2024-07-04 | Q75: Active | S75: No | T75: 302400 | U75: 2 | V75: No | W75: Hybrid | Y75: 22 | Z75: 0 | AA75: Employee Referral | AB75: 0.7 | AC75: 0.95 | AD75: 0.74 | AE75: 16 | AF75: 0 | AG75: 49 | AH75: 3 | AI75: 3 | AJ75: 4 | AK75: 3 | AL75: 1 | AM75: 53 | AN75: Yes | AO75: Premium | AP75: Yes | AQ75: =B75&" "&C75 -> Joshua Blair | AR75: =DATEDIF(E75,ReadMe!$C$7,"y") -> 39 | AS75: =ROUND(DATEDIF(O75,IF(Q75="Active",ReadMe!$C$7,P75),"m")/12,2) -> 2.08
A76: EMP0075 | B76: Curtis | C76: Collins | D76: Male | E76: 2004-10-24 | F76: Widowed | G76: D01 | H76: Sales | I76: JT02 | J76: Account Executive | K76: Mid | L76: L03 | M76: E35 | N76: EMP0390 | O76: 2025-07-13 | Q76: Active | S76: No | T76: 65400 | U76: 1 | V76: Yes | W76: Onsite | Y76: 5 | Z76: 0 | AA76: Job Portal | AB76: 0.31 | AC76: 0.12 | AD76: 0.6 | AE76: 17 | AF76: 7 | AG76: 6 | AH76: 3 | AI76: 2 | AJ76: 2 | AK76: 3 | AL76: 3 | AM76: 96 | AN76: Yes | AO76: Premium | AP76: Yes | AQ76: =B76&" "&C76 -> Curtis Collins | AR76: =DATEDIF(E76,ReadMe!$C$7,"y") -> 21 | AS76: =ROUND(DATEDIF(O76,IF(Q76="Active",ReadMe!$C$7,P76),"m")/12,2) -> 1.08
A77: EMP0076 | B77: Zachary | C77: Santos | D77: Male | E77: 2001-03-23 | F77: Married | G77: D01 | H77: Sales | I77: JT02 | J77: Account Executive | K77: Mid | L77: L06 | M77: E07 | N77: EMP0758 | O77: 2023-09-19 | Q77: Active | S77: No | T77: 79800 | U77: 1 | V77: Yes | W77: Onsite | X77: Rarely | Y77: 2 | Z77: 0 | AA77: Company Website | AB77: 1.07 | AC77: 1.27 | AD77: 1.83 | AE77: 32 | AF77: 0 | AG77: 12 | AH77: 2 | AI77: 2 | AJ77: 4 | AK77: 3 | AL77: 2 | AM77: 77 | AN77: Yes | AO77: Standard | AP77: Yes | AQ77: =B77&" "&C77 -> Zachary Santos | AR77: =DATEDIF(E77,ReadMe!$C$7,"y") -> 25 | AS77: =ROUND(DATEDIF(O77,IF(Q77="Active",ReadMe!$C$7,P77),"m")/12,2) -> 2.92
A78: EMP0077 | B78: Jessica | C78: Holmes | D78: Female | E78: 1992-06-09 | F78: Married | G78: D02 | H78: Marketing | I78: JT08 | J78: Senior Marketing Specialist | K78: Senior | L78: L08 | M78: E19 | N78: EMP0482 | O78: 2023-09-15 | P78: 2023-12-16 | Q78: Terminated | R78: Voluntary - Personal Reasons | S78: Yes | T78: 100500 | U78: 1 | V78: Yes | W78: Hybrid | Y78: 23 | Z78: 0 | AA78: Job Portal | AB78: 1.13 | AC78: 0.99 | AD78: 1.38 | AE78: 29 | AF78: 1 | AG78: 24 | AH78: 1 | AI78: 2 | AJ78: 3 | AK78: 4 | AL78: 2 | AM78: 60 | AN78: Yes | AO78: Basic | AP78: Yes | AQ78: =B78&" "&C78 -> Jessica Holmes | AR78: =DATEDIF(E78,ReadMe!$C$7,"y") -> 34 | AS78: =ROUND(DATEDIF(O78,IF(Q78="Active",ReadMe!$C$7,P78),"m")/12,2) -> 0.25
A79: EMP0078 | B79: Bryan | C79: Walker | D79: Male | E79: 2001-01-06 | F79: Married | G79: D03 | H79: Engineering | I79: JT11 | J79: Software Engineer II | K79: Mid | L79: L01 | M79: E21 | N79: EMP0807 | O79: 2025-12-13 | Q79: Active | S79: No | T79: 72600 | U79: 2 | V79: Yes | W79: Hybrid | Y79: 1 | Z79: 2 | AA79: Campus Hiring | AB79: 0.02 | AC79: 0.33 | AD79: 0.2 | AE79: 22 | AF79: 9 | AG79: 5 | AH79: 3 | AI79: 2 | AJ79: 3 | AK79: 3 | AL79: 3 | AM79: 73 | AN79: Yes | AO79: Basic | AP79: No | AQ79: =B79&" "&C79 -> Bryan Walker | AR79: =DATEDIF(E79,ReadMe!$C$7,"y") -> 25 | AS79: =ROUND(DATEDIF(O79,IF(Q79="Active",ReadMe!$C$7,P79),"m")/12,2) -> 0.67
A80: EMP0079 | B80: Gina | C80: Chapman | D80: Female | E80: 1998-06-12 | F80: Divorced | G80: D09 | H80: Legal | I80: JT33 | J80: Legal Counsel | K80: Senior | L80: L09 | M80: E08 | N80: EMP0767 | O80: 2019-03-05 | P80: 2021-04-12 | Q80: Terminated | R80: Involuntary - Policy Violation | S80: Yes | T80: 85600 | U80: 0 | V80: Yes | W80: Hybrid | Y80: 13 | Z80: 0 | AA80: Campus Hiring | AB80: 1.3 | AC80: 5.28 | AD80: 5.2 | AE80: 38 | AF80: 0 | AG80: 75 | AH80: 4 | AI80: 2 | AJ80: 3 | AK80: 3 | AL80: 4 | AM80: 76 | AN80: Yes | AO80: Standard | AP80: No | AQ80: =B80&" "&C80 -> Gina Chapman | AR80: =DATEDIF(E80,ReadMe!$C$7,"y") -> 28 | AS80: =ROUND(DATEDIF(O80,IF(Q80="Active",ReadMe!$C$7,P80),"m")/12,2) -> 2.08
A81: EMP0080 | B81: Crystal | C81: Robinson | D81: Female | E81: 1996-09-03 | F81: Single | G81: D01 | H81: Sales | I81: JT04 | J81: Sales Manager | K81: Manager | L81: L15 | M81: E14 | N81: EMP0506 | O81: 2022-08-21 | Q81: Active | S81: No | T81: 129400 | U81: 0 | V81: No | W81: Remote | X81: Frequently | Y81: 12 | Z81: 2 | AA81: Campus Hiring | AB81: 0.43 | AC81: 2 | AD81: 1.63 | AE81: 30 | AF81: 4 | AG81: 7 | AH81: 2 | AI81: 2 | AJ81: 2 | AK81: 2 | AL81: 3 | AM81: 62 | AN81: Yes | AO81: Standard | AP81: Yes | AQ81: =B81&" "&C81 -> Crystal Robinson | AR81: =DATEDIF(E81,ReadMe!$C$7,"y") -> 29 | AS81: =ROUND(DATEDIF(O81,IF(Q81="Active",ReadMe!$C$7,P81),"m")/12,2) -> 3.92
A82: EMP0081 | B82: Benjamin | C82: Welch | D82: Male | E82: 2005-08-12 | F82: Divorced | G82: D03 | H82: Engineering | I82: JT11 | J82: Software Engineer II | K82: Mid | L82: L10 | M82: E37 | N82: EMP0022 | O82: 2025-09-28 | Q82: Active | S82: No | T82: 70100 | U82: 0 | V82: Yes | W82: Onsite | X82: Rarely | Y82: 2 | Z82: 0 | AA82: Recruitment Agency | AB82: 0.09 | AC82: 0.09 | AD82: 0.06 | AE82: 22 | AF82: 2 | AG82: 12 | AH82: 3 | AI82: 2 | AJ82: 1 | AK82: 2 | AL82: 3 | AM82: 82 | AN82: No | AO82: Premium | AP82: No | AQ82: =B82&" "&C82 -> Benjamin Welch | AR82: =DATEDIF(E82,ReadMe!$C$7,"y") -> 21 | AS82: =ROUND(DATEDIF(O82,IF(Q82="Active",ReadMe!$C$7,P82),"m")/12,2) -> 0.83
A83: EMP0082 | B83: Crystal | C83: Whitehead | D83: Female | E83: 1992-01-01 | F83: Widowed | G83: D04 | H83: Information Technology | I83: JT16 | J83: IT Support Specialist | K83: Entry | L83: L02 | M83: E17 | N83: EMP0186 | O83: 2021-05-08 | Q83: Active | S83: No | T83: 53100 | U83: 2 | V83: Yes | W83: Onsite | Y83: 49 | Z83: 1 | AA83: Company Website | AB83: 3.18 | AC83: 0.21 | AD83: 1.56 | AE83: 41 | AF83: 5 | AG83: 12 | AH83: 2 | AI83: 2 | AJ83: 4 | AK83: 3 | AL83: 3 | AM83: 78 | AN83: Yes | AO83: Basic | AP83: No | AQ83: =B83&" "&C83 -> Crystal Whitehead | AR83: =DATEDIF(E83,ReadMe!$C$7,"y") -> 34 | AS83: =ROUND(DATEDIF(O83,IF(Q83="Active",ReadMe!$C$7,P83),"m")/12,2) -> 5.25
A84: EMP0083 | B84: Scott | C84: Jones | D84: Male | E84: 2001-12-29 | F84: Divorced | G84: D05 | H84: Human Resources | I84: JT19 | J84: HR Coordinator | K84: Entry | L84: L06 | M84: E22 | N84: EMP0108 | O84: 2024-10-12 | Q84: Active | S84: No | T84: 57400 | U84: 3 | V84: Yes | W84: Hybrid | Y84: 16 | Z84: 0 | AA84: Campus Hiring | AB84: 1.35 | AC84: 0.21 | AD84: 0.14 | AE84: 38 | AF84: 3 | AG84: 48 | AH84: 2 | AI84: 2 | AJ84: 2 | AK84: 3 | AL84: 3 | AM84: 53 | AN84: Yes | AP84: No | AQ84: =B84&" "&C84 -> Scott Jones | AR84: =DATEDIF(E84,ReadMe!$C$7,"y") -> 24 | AS84: =ROUND(DATEDIF(O84,IF(Q84="Active",ReadMe!$C$7,P84),"m")/12,2) -> 1.83
A85: EMP0084 | B85: David | C85: Caldwell | D85: Male | E85: 2003-02-02 | F85: Widowed | G85: D07 | H85: Operations | I85: JT28 | J85: Operations Analyst | K85: Entry | L85: L08 | M85: E42 | N85: EMP0119 | O85: 2023-06-06 | P85: 2023-12-03 | Q85: Terminated | R85: Voluntary - Career Change | S85: Yes | T85: 43800 | U85: 0 | V85: Yes | W85: Hybrid | X85: Rarely | Y85: 10 | Z85: 2 | AA85: Career Fair | AB85: 1.59 | AC85: 1.66 | AD85: 0.18 | AE85: 28 | AF85: 2 | AG85: 17 | AH85: 3 | AI85: 2 | AJ85: 2 | AK85: 2 | AL85: 3 | AM85: 99 | AN85: Yes | AP85: No | AQ85: =B85&" "&C85 -> David Caldwell | AR85: =DATEDIF(E85,ReadMe!$C$7,"y") -> 23 | AS85: =ROUND(DATEDIF(O85,IF(Q85="Active",ReadMe!$C$7,P85),"m")/12,2) -> 0.42
A86: EMP0085 | B86: Daniel | C86: Anderson | D86: Male | E86: 1993-09-26 | F86: Widowed | G86: D07 | H86: Operations | I86: JT29 | J86: Operations Manager | K86: Manager | L86: L13 | M86: E48 | N86: EMP0193 | O86: 2018-03-05 | Q86: Active | S86: No | T86: 144400 | U86: 0 | V86: No | W86: Hybrid | Y86: 19 | Z86: 0 | AA86: Company Website | AB86: 5.3 | AC86: 5.8 | AD86: 3.42 | AE86: 27 | AF86: 1 | AG86: 29 | AH86: 2 | AI86: 2 | AJ86: 3 | AK86: 3 | AL86: 2 | AM86: 48 | AN86: Yes | AO86: Standard | AP86: Yes | AQ86: =B86&" "&C86 -> Daniel Anderson | AR86: =DATEDIF(E86,ReadMe!$C$7,"y") -> 32 | AS86: =ROUND(DATEDIF(O86,IF(Q86="Active",ReadMe!$C$7,P86),"m")/12,2) -> 8.42
A87: EMP0086 | B87: Taylor | C87: Duncan | D87: Female | E87: 2000-04-12 | F87: Single | G87: D03 | H87: Engineering | I87: JT11 | J87: Software Engineer II | K87: Mid | L87: L14 | M87: E34 | N87: EMP0716 | O87: 2022-12-08 | Q87: Active | S87: No | T87: 56300 | U87: 3 | V87: Yes | W87: Remote | Y87: 4 | Z87: 2 | AA87: Company Website | AB87: 1.17 | AC87: 3.3 | AD87: 0.35 | AE87: 56 | AF87: 3 | AG87: 5 | AH87: 3 | AI87: 3 | AJ87: 3 | AK87: 3 | AL87: 3 | AM87: 59 | AN87: Yes | AO87: Basic | AP87: Yes | AQ87: =B87&" "&C87 -> Taylor Duncan | AR87: =DATEDIF(E87,ReadMe!$C$7,"y") -> 26 | AS87: =ROUND(DATEDIF(O87,IF(Q87="Active",ReadMe!$C$7,P87),"m")/12,2) -> 3.67
A88: EMP0087 | B88: John | C88: Mueller | D88: Male | E88: 1999-06-07 | F88: Single | G88: D01 | H88: Sales | I88: JT01 | J88: Sales Development Representative | K88: Entry | L88: L14 | M88: E34 | N88: EMP0096 | O88: 2024-06-09 | Q88: Active | S88: No | T88: 42800 | U88: 0 | V88: Yes | W88: Remote | Y88: 3 | Z88: 1 | AA88: Campus Hiring | AB88: 0.85 | AC88: 0.53 | AD88: 1.28 | AE88: 32 | AF88: 3 | AG88: 9 | AH88: 3 | AI88: 4 | AJ88: 4 | AK88: 2 | AL88: 3 | AM88: 75 | AN88: Yes | AO88: Standard | AP88: Yes | AQ88: =B88&" "&C88 -> John Mueller | AR88: =DATEDIF(E88,ReadMe!$C$7,"y") -> 27 | AS88: =ROUND(DATEDIF(O88,IF(Q88="Active",ReadMe!$C$7,P88),"m")/12,2) -> 2.17
A89: EMP0088 | B89: Robert | C89: Lee | D89: Male | E89: 1985-06-13 | F89: Widowed | G89: D01 | H89: Sales | I89: JT05 | J89: Director of Sales | K89: Director | L89: L14 | M89: E31 | N89: EMP0280 | O89: 2021-09-28 | Q89: Active | S89: No | T89: 175600 | U89: 0 | V89: No | W89: Hybrid | Y89: 3 | Z89: 0 | AA89: Campus Hiring | AB89: 1.61 | AC89: 3.48 | AD89: 2.67 | AE89: 11 | AF89: 0 | AG89: 21 | AH89: 2 | AI89: 3 | AJ89: 1 | AK89: 3 | AL89: 3 | AM89: 66 | AN89: Yes | AO89: Standard | AP89: Yes | AQ89: =B89&" "&C89 -> Robert Lee | AR89: =DATEDIF(E89,ReadMe!$C$7,"y") -> 41 | AS89: =ROUND(DATEDIF(O89,IF(Q89="Active",ReadMe!$C$7,P89),"m")/12,2) -> 4.83
A90: EMP0089 | B90: Anne | C90: Jordan | D90: Female | E90: 1980-02-17 | F90: Divorced | G90: D01 | H90: Sales | I90: JT04 | J90: Sales Manager | K90: Manager | L90: L10 | M90: E32 | N90: EMP0140 | O90: 2024-03-16 | Q90: Active | S90: No | T90: 122600 | U90: 2 | V90: No | W90: Hybrid | Y90: 18 | Z90: 3 | AA90: Career Fair | AB90: 0.17 | AC90: 0.95 | AD90: 1.52 | AE90: 36 | AF90: 0 | AG90: 42 | AH90: 3 | AI90: 3 | AJ90: 2 | AK90: 3 | AL90: 3 | AM90: 57 | AN90: Yes | AP90: No | AQ90: =B90&" "&C90 -> Anne Jordan | AR90: =DATEDIF(E90,ReadMe!$C$7,"y") -> 46 | AS90: =ROUND(DATEDIF(O90,IF(Q90="Active",ReadMe!$C$7,P90),"m")/12,2) -> 2.42
A91: EMP0090 | B91: Jeff | C91: Owens | D91: Male | E91: 1990-12-13 | F91: Widowed | G91: D06 | H91: Finance | I91: JT25 | J91: Senior Financial Analyst | K91: Senior | L91: L07 | M91: E27 | N91: EMP0306 | O91: 2024-03-26 | Q91: Active | S91: No | T91: 92100 | U91: 0 | V91: Yes | W91: Hybrid | Y91: 23 | Z91: 5 | AA91: Career Fair | AB91: 2.39 | AC91: 1.25 | AD91: 2.33 | AE91: 4 | AF91: 3 | AG91: 1 | AH91: 3 | AI91: 3 | AJ91: 3 | AK91: 3 | AL91: 3 | AM91: 65 | AN91: Yes | AO91: Standard | AP91: No | AQ91: =B91&" "&C91 -> Jeff Owens | AR91: =DATEDIF(E91,ReadMe!$C$7,"y") -> 35 | AS91: =ROUND(DATEDIF(O91,IF(Q91="Active",ReadMe!$C$7,P91),"m")/12,2) -> 2.33
A92: EMP0091 | B92: Monica | C92: Nunez | D92: Female | E92: 1991-03-06 | F92: Married | G92: D08 | H92: Customer Support | I92: JT31 | J92: Senior Support Representative | K92: Senior | L92: L14 | M92: E26 | N92: EMP0956 | O92: 2022-11-20 | Q92: Active | S92: No | T92: 96300 | U92: 0 | V92: Yes | W92: Hybrid | X92: Frequently | Y92: 4 | Z92: 4 | AA92: Company Website | AB92: 1.32 | AC92: 0.43 | AD92: 0.07 | AE92: 20 | AF92: 10 | AG92: 1 | AH92: 3 | AI92: 2 | AJ92: 3 | AK92: 3 | AL92: 5 | AM92: 69 | AN92: No | AO92: Standard | AP92: Yes | AQ92: =B92&" "&C92 -> Monica Nunez | AR92: =DATEDIF(E92,ReadMe!$C$7,"y") -> 35 | AS92: =ROUND(DATEDIF(O92,IF(Q92="Active",ReadMe!$C$7,P92),"m")/12,2) -> 3.75
A93: EMP0092 | B93: Victoria | C93: Garcia | D93: Female | E93: 1984-02-02 | F93: Married | G93: D02 | H93: Marketing | I93: JT09 | J93: Marketing Manager | K93: Manager | L93: L06 | M93: E22 | N93: EMP0831 | O93: 2025-08-01 | Q93: Active | S93: No | T93: 114100 | U93: 2 | V93: No | W93: Hybrid | Y93: 13 | Z93: 3 | AA93: Campus Hiring | AB93: 0.39 | AC93: 0 | AD93: 0.2 | AE93: 17 | AF93: 1 | AG93: 11 | AH93: 3 | AI93: 3 | AJ93: 2 | AK93: 3 | AL93: 3 | AM93: 58 | AN93: No | AO93: Premium | AP93: Yes | AQ93: =B93&" "&C93 -> Victoria Garcia | AR93: =DATEDIF(E93,ReadMe!$C$7,"y") -> 42 | AS93: =ROUND(DATEDIF(O93,IF(Q93="Active",ReadMe!$C$7,P93),"m")/12,2) -> 1
A94: EMP0093 | B94: Richard | C94: Morgan | D94: Non-Binary | E94: 1995-10-30 | F94: Widowed | G94: D03 | H94: Engineering | I94: JT11 | J94: Software Engineer II | K94: Mid | L94: L15 | M94: E36 | N94: EMP0451 | O94: 2023-07-05 | Q94: Active | S94: No | T94: 58200 | U94: 1 | V94: Yes | W94: Onsite | Y94: 12 | Z94: 6 | AA94: Employee Referral | AB94: 0.96 | AC94: 1.87 | AD94: 1.62 | AE94: 9 | AF94: 0 | AG94: 9 | AH94: 2 | AI94: 1 | AJ94: 2 | AK94: 3 | AL94: 3 | AM94: 72 | AN94: Yes | AO94: Premium | AP94: Yes | AQ94: =B94&" "&C94 -> Richard Morgan | AR94: =DATEDIF(E94,ReadMe!$C$7,"y") -> 30 | AS94: =ROUND(DATEDIF(O94,IF(Q94="Active",ReadMe!$C$7,P94),"m")/12,2) -> 3.08
A95: EMP0094 | B95: Scott | C95: Wright | D95: Male | E95: 2004-09-24 | F95: Widowed | G95: D06 | H95: Finance | I95: JT24 | J95: Financial Analyst | K95: Entry | L95: L14 | M95: E37 | N95: EMP0993 | O95: 2025-07-24 | Q95: Active | S95: No | T95: 46200 | U95: 1 | V95: Yes | W95: Onsite | Y95: 3 | Z95: 0 | AA95: Company Website | AB95: 0.83 | AC95: 0.38 | AD95: 0.87 | AE95: 27 | AF95: 4 | AG95: 7 | AH95: 2 | AI95: 2 | AJ95: 3 | AK95: 1 | AL95: 3 | AM95: 79 | AN95: Yes | AO95: Basic | AP95: Yes | AQ95: =B95&" "&C95 -> Scott Wright | AR95: =DATEDIF(E95,ReadMe!$C$7,"y") -> 21 | AS95: =ROUND(DATEDIF(O95,IF(Q95="Active",ReadMe!$C$7,P95),"m")/12,2) -> 1
A96: EMP0095 | B96: Cheryl | C96: West | D96: Female | E96: 1983-09-20 | F96: Widowed | G96: D03 | H96: Engineering | I96: JT14 | J96: Engineering Manager | K96: Manager | L96: L06 | M96: E01 | N96: EMP0642 | O96: 2018-05-19 | Q96: Active | S96: No | T96: 111400 | U96: 0 | V96: No | W96: Remote | Y96: 18 | Z96: 1 | AA96: Career Fair | AB96: 7.16 | AC96: 1.33 | AD96: 6.4 | AE96: 40 | AF96: 0 | AG96: 44 | AH96: 4 | AI96: 3 | AJ96: 4 | AK96: 2 | AL96: 2 | AM96: 65 | AN96: No | AP96: No | AQ96: =B96&" "&C96 -> Cheryl West | AR96: =DATEDIF(E96,ReadMe!$C$7,"y") -> 42 | AS96: =ROUND(DATEDIF(O96,IF(Q96="Active",ReadMe!$C$7,P96),"m")/12,2) -> 8.25
A97: EMP0096 | B97: Javier | C97: Ramirez | D97: Male | E97: 1984-05-02 | F97: Single | G97: D05 | H97: Human Resources | I97: JT22 | J97: HR Manager | K97: Manager | L97: L08 | M97: E11 | N97: EMP0765 | O97: 2020-07-22 | Q97: Active | S97: No | T97: 125900 | U97: 0 | V97: No | W97: Hybrid | Y97: 15 | Z97: 1 | AA97: Career Fair | AB97: 3.72 | AC97: 1.92 | AD97: 4.36 | AE97: 14 | AF97: 0 | AG97: 10 | AH97: 3 | AI97: 3 | AJ97: 2 | AK97: 3 | AL97: 3 | AM97: 93 | AN97: Yes | AO97: Standard | AP97: Yes | AQ97: =B97&" "&C97 -> Javier Ramirez | AR97: =DATEDIF(E97,ReadMe!$C$7,"y") -> 42 | AS97: =ROUND(DATEDIF(O97,IF(Q97="Active",ReadMe!$C$7,P97),"m")/12,2) -> 6
A98: EMP0097 | B98: David | C98: Leblanc | D98: Male | E98: 1984-01-16 | F98: Single | G98: D06 | H98: Finance | I98: JT27 | J98: Director of Finance | K98: Director | L98: L14 | M98: E36 | N98: EMP0048 | O98: 2024-09-19 | Q98: Active | S98: No | T98: 188000 | U98: 2 | V98: No | W98: Hybrid | Y98: 7 | Z98: 1 | AA98: Job Portal | AB98: 0.41 | AC98: 0.81 | AD98: 0.05 | AE98: 19 | AF98: 7 | AG98: 26 | AH98: 2 | AI98: 3 | AJ98: 2 | AK98: 3 | AL98: 3 | AM98: 80 | AN98: Yes | AO98: Premium | AP98: Yes | AQ98: =B98&" "&C98 -> David Leblanc | AR98: =DATEDIF(E98,ReadMe!$C$7,"y") -> 42 | AS98: =ROUND(DATEDIF(O98,IF(Q98="Active",ReadMe!$C$7,P98),"m")/12,2) -> 1.92
A99: EMP0098 | B99: Jessica | C99: Callahan | D99: Female | E99: 1983-04-28 | F99: Married | G99: D10 | H99: Executive | I99: JT37 | J99: Chief Technology Officer | K99: Executive | L99: L05 | M99: E18 | O99: 2021-01-25 | Q99: Active | S99: No | T99: 271700 | U99: 1 | V99: No | W99: Remote | Y99: 28 | Z99: 3 | AA99: Employee Referral | AB99: 3.11 | AC99: 3.75 | AD99: 1.8 | AE99: 27 | AF99: 0 | AG99: 2 | AH99: 2 | AI99: 1 | AJ99: 4 | AK99: 4 | AL99: 3 | AM99: 49 | AN99: No | AO99: Premium | AP99: Yes | AQ99: =B99&" "&C99 -> Jessica Callahan | AR99: =DATEDIF(E99,ReadMe!$C$7,"y") -> 43 | AS99: =ROUND(DATEDIF(O99,IF(Q99="Active",ReadMe!$C$7,P99),"m")/12,2) -> 5.5
A100: EMP0099 | B100: Joshua | C100: Williams | D100: Male | E100: 1990-09-14 | F100: Widowed | G100: D05 | H100: Human Resources | I100: JT21 | J100: Senior HR Business Partner | K100: Senior | L100: L01 | M100: E28 | N100: EMP0262 | O100: 2023-08-26 | P100: 2025-03-10 | Q100: Terminated | R100: Involuntary - Restructuring | S100: Yes | T100: 91000 | U100: 1 | V100: Yes | W100: Onsite | Y100: 4 | Z100: 1 | AA100: Job Portal | AB100: 0.1 | AC100: 1.44 | AD100: 0.56 | AE100: 42 | AF100: 9 | AG100: 12 | AH100: 3 | AI100: 3 | AJ100: 4 | AK100: 2 | AL100: 3 | AM100: 99 | AN100: Yes | AO100: Premium | AP100: No | AQ100: =B100&" "&C100 -> Joshua Williams | AR100: =DATEDIF(E100,ReadMe!$C$7,"y") -> 35 | AS100: =ROUND(DATEDIF(O100,IF(Q100="Active",ReadMe!$C$7,P100),"m")/12,2) -> 1.5
...

Sheet Dim_Department
A1: DepartmentID | B1: DepartmentName | C1: Division | D1: BusinessUnit | E1: DepartmentHeadName | F1: DepartmentBudgetUSD
A2: D01 | B2: Sales | C2: Commercial | D2: Revenue Generation | E2: Adaeze Okafor | F2: 4200000
A3: D02 | B3: Marketing | C3: Commercial | D3: Revenue Generation | E3: Michael Chen | F3: 2100000
A4: D03 | B4: Engineering | C4: Technology | D4: Product & Technology | E4: Sarah Whitfield | F4: 6800000
A5: D04 | B5: Information Technology | C5: Technology | D5: Product & Technology | E5: David Okonkwo | F5: 3100000
A6: D05 | B6: Human Resources | C6: Corporate | D6: People & Culture | E6: Funmilayo Adeyemi | F6: 1200000
A7: D06 | B7: Finance | C7: Corporate | D7: Finance & Legal | E7: James Whitmore | F7: 1600000
A8: D07 | B8: Operations | C8: Operations | D8: Operations & Supply | E8: Grace Muthoni | F8: 2600000
A9: D08 | B9: Customer Support | C9: Operations | D9: Operations & Supply | E9: Daniel Ibrahim | F9: 1400000
A10: D09 | B10: Legal | C10: Corporate | D10: Finance & Legal | E10: Patricia Nwosu | F10: 900000
A11: D10 | B11: Executive | C11: Corporate | D11: Leadership | E11: Chukwuemeka Eze | F11: 1100000

Sheet Dim_JobTitle
A1: JobTitleID | B1: JobTitle | C1: JobLevel | D1: JobFamily | E1: DepartmentID
A2: JT01 | B2: Sales Development Representative | C2: Entry | D2: Sales | E2: D01
A3: JT02 | B3: Account Executive | C3: Mid | D3: Sales | E3: D01
A4: JT03 | B4: Senior Account Executive | C4: Senior | D4: Sales | E4: D01
A5: JT04 | B5: Sales Manager | C5: Manager | D5: Sales | E5: D01
A6: JT05 | B6: Director of Sales | C6: Director | D6: Sales | E6: D01
A7: JT06 | B7: Marketing Coordinator | C7: Entry | D7: Marketing | E7: D02
A8: JT07 | B8: Marketing Specialist | C8: Mid | D8: Marketing | E8: D02
A9: JT08 | B9: Senior Marketing Specialist | C9: Senior | D9: Marketing | E9: D02
A10: JT09 | B10: Marketing Manager | C10: Manager | D10: Marketing | E10: D02
A11: JT10 | B11: Software Engineer I | C11: Entry | D11: Engineering | E11: D03
A12: JT11 | B12: Software Engineer II | C12: Mid | D12: Engineering | E12: D03
... A39: JT38 | B39: Chief People Officer | C39: Executive | D39: Executive | E39: D10

Sheet Dim_Location
A1: LocationID | B1: City | C1: StateProvince | D1: Country | E1: Region | F1: OfficeType
A2: L01 | B2: Lagos | C2: Lagos State | D2: Nigeria | E2: Africa | F2: HQ
A3: L02 | B3: Abuja | C3: FCT | D3: Nigeria | E3: Africa | F3: Regional Office
A4: L03 | B4: Nairobi | C4: Nairobi County | D4: Kenya | E4: Africa | F4: Regional Office
A5: L04 | B5: Accra | C5: Greater Accra | D5: Ghana | E5: Africa | F5: Regional Office
A6: L05 | B6: Johannesburg | C6: Gauteng | D6: South Africa | E6: Africa | F6: Regional Office
A7: L06 | B7: London | C7: England | D7: United Kingdom | E7: EMEA | F7: Regional Office
A8: L07 | B8: Dublin | C8: Leinster | D8: Ireland | E8: EMEA | F8: Regional Office
A9: L08 | B9: New York | C9: New York | D9: United States | E9: North America | F9: Regional Office
A10: L09 | B10: Austin | C10: Texas | D10: United States | E10: North America | F10: Regional Office
A11: L10 | B11: Toronto | C11: Ontario | D11: Canada | E11: North America | F11: Regional Office
A12: L11 | B12: Dubai | C12: Dubai | D12: United Arab Emirates | E12: Middle East | F12: Regional Office
... A14: L13 | B14: Mumbai | C14: Maharashtra | D14: India | E14: APAC | F14: Regional Office
A15: L14 | B15: Remote - Africa | E15: Africa | F15: Remote Hub
A16: L15 | B16: Remote - Global | E16: Global | F16: Remote Hub

Sheet Dim_Education
A1: EducationID | B1: EducationLevel | C1: EducationField
A2: E01 | B2: High School | C2: Business Administration
A3: E02 | B3: High School | C3: Computer Science
A4: E03 | B4: High School | C4: Engineering
A5: E04 | B5: High School | C5: Human Resources
A6: E05 | B6: High School | C6: Marketing
A7: E06 | B7: High School | C7: Finance & Accounting
A8: E07 | B8: High School | C8: Economics
A9: E08 | B9: High School | C9: Law
A10: E09 | B10: High School | C10: Communications
A11: E10 | B11: High School | C11: Other
A12: E11 | B12: Associate Degree | C12: Business Administration
... A51: E50 | B51: PhD / Doctorate | C51: Other

Sheet Dim_Date
A1: DateKey | B1: Date | C1: Year | D1: FiscalYear | E1: QuarterNumber | F1: Quarter | G1: MonthNumber | H1: MonthName | I1: MonthShort | J1: Day | K1: DayName | L1: WeekOfYear | M1: IsWeekend | N1: YearMonth
A2: 20180101 | B2: 2018-01-01 | C2: 2018 | D2: 2018 | E2: 1 | F2: Q1 | G2: 1 | H2: January | I2: Jan | J2: 1 | K2: Monday | L2: 1 | M2: =FALSE() -> FALSE | N2: 2018-01
A3: 20180102 | B3: 2018-01-02 | C3: 2018 | D3: 2018 | E3: 1 | F3: Q1 | G3: 1 | H3: January | I3: Jan | J3: 2 | K3: Tuesday | L3: 1 | M3: =FALSE() -> FALSE | N3: 2018-01
A4: 20180103 | B4: 2018-01-03 | C4: 2018 | D4: 2018 | E4: 1 | F4: Q1 | G4: 1 | H4: January | I4: Jan | J4: 3 | K4: Wednesday | L4: 1 | M4: =FALSE() -> FALSE | N4: 2018-01
A5: 20180104 | B5: 2018-01-04 | C5: 2018 | D5: 2018 | E5: 1 | F5: Q1 | G5: 1 | H5: January | I5: Jan | J5: 4 | K5: Thursday | L5: 1 | M5: =FALSE() -> FALSE | N5: 2018-01
A6: 20180105 | B6: 2018-01-05 | C6: 2018 | D6: 2018 | E6: 1 | F6: Q1 | G6: 1 | H6: January | I6: Jan | J6: 5 | K6: Friday | L6: 1 | M6: =FALSE() -> FALSE | N6: 2018-01
A7: 20180106 | B7: 2018-01-06 | C7: 2018 | D7: 2018 | E7: 1 | F7: Q1 | G7: 1 | H7: January | I7: Jan | J7: 6 | K7: Saturday | L7: 1 | M7: =TRUE() -> TRUE | N7: 2018-01
A8: 20180107 | B8: 2018-01-07 | C8: 2018 | D8: 2018 | E8: 1 | F8: Q1 | G8: 1 | H8: January | I8: Jan | J8: 7 | K8: Sunday | L8: 1 | M8: =TRUE() -> TRUE | N8: 2018-01
A9: 20180108 | B9: 2018-01-08 | C9: 2018 | D9: 2018 | E9: 1 | F9: Q1 | G9: 1 | H9: January | I9: Jan | J9: 8 | K9: Monday | L9: 2 | M9: =FALSE() -> FALSE | N9: 2018-01
A10: 20180109 | B10: 2018-01-09 | C10: 2018 | D10: 2018 | E10: 1 | F10: Q1 | G10: 1 | H10: January | I10: Jan | J10: 9 | K10: Tuesday | L10: 2 | M10: =FALSE() -> FALSE | N10: 2018-01
A11: 20180110 | B11: 2018-01-10 | C11: 2018 | D11: 2018 | E11: 1 | F11: Q1 | G11: 1 | H11: January | I11: Jan | J11: 10 | K11: Wednesday | L11: 2 | M11: =FALSE() -> FALSE | N11: 2018-01
A12: 20180111 | B12: 2018-01-11 | C12: 2018 | D12: 2018 | E12: 1 | F12: Q1 | G12: 1 | H12: January | I12: Jan | J12: 11 | K12: Thursday | L12: 2 | M12: =FALSE() -> FALSE | N12: 2018-01
A13: 20180112 | B13: 2018-01-12 | C13: 2018 | D13: 2018 | E13: 1 | F13: Q1 | G13: 1 | H13: January | I13: Jan | J13: 12 | K13: Friday | L13: 2 | M13: =FALSE() -> FALSE | N13: 2018-01
A14: 20180113 | B14: 2018-01-13 | C14: 2018 | D14: 2018 | E14: 1 | F14: Q1 | G14: 1 | H14: January | I14: Jan | J14: 13 | K14: Saturday | L14: 2 | M14: =TRUE() -> TRUE | N14: 2018-01
A15: 20180114 | B15: 2018-01-14 | C15: 2018 | D15: 2018 | E15: 1 | F15: Q1 | G15: 1 | H15: January | I15: Jan | J15: 14 | K15: Sunday | L15: 2 | M15: =TRUE() -> TRUE | N15: 2018-01
A16: 20180115 | B16: 2018-01-15 | C16: 2018 | D16: 2018 | E16: 1 | F16: Q1 | G16: 1 | H16: January | I16: Jan | J16: 15 | K16: Monday | L16: 3 | M16: =FALSE() -> FALSE | N16: 2018-01
A17: 20180116 | B17: 2018-01-16 | C17: 2018 | D17: 2018 | E17: 1 | F17: Q1 | G17: 1 | H17: January | I17: Jan | J17: 16 | K17: Tuesday | L17: 3 | M17: =FALSE() -> FALSE | N17: 2018-01
A18: 20180117 | B18: 2018-01-17 | C18: 2018 | D18: 2018 | E18: 1 | F18: Q1 | G18: 1 | H18: January | I18: Jan | J18: 17 | K18: Wednesday | L18: 3 | M18: =FALSE() -> FALSE | N18: 2018-01
A19: 20180118 | B19: 2018-01-18 | C19: 2018 | D19: 2018 | E19: 1 | F19: Q1 | G19: 1 | H19: January | I19: Jan | J19: 18 | K19: Thursday | L19: 3 | M19: =FALSE() -> FALSE | N19: 2018-01
A20: 20180119 | B20: 2018-01-19 | C20: 2018 | D20: 2018 | E20: 1 | F20: Q1 | G20: 1 | H20: January | I20: Jan | J20: 19 | K20: Friday | L20: 3 | M20: =FALSE() -> FALSE | N20: 2018-01
A21: 20180120 | B21: 2018-01-20 | C21: 2018 | D21: 2018 | E21: 1 | F21: Q1 | G21: 1 | H21: January | I21: Jan | J21: 20 | K21: Saturday | L21: 3 | M21: =TRUE() -> TRUE | N21: 2018-01
A22: 20180121 | B22: 2018-01-21 | C22: 2018 | D22: 2018 | E22: 1 | F22: Q1 | G22: 1 | H22: January | I22: Jan | J22: 21 | K22: Sunday | L22: 3 | M22: =TRUE() -> TRUE | N22: 2018-01
A23: 20180122 | B23: 2018-01-22 | C23: 2018 | D23: 2018 | E23: 1 | F23: Q1 | G23: 1 | H23: January | I23: Jan | J23: 22 | K23: Monday | L23: 4 | M23: =FALSE() -> FALSE | N23: 2018-01
A24: 20180123 | B24: 2018-01-23 | C24: 2018 | D24: 2018 | E24: 1 | F24: Q1 | G24: 1 | H24: January | I24: Jan | J24: 23 | K24: Tuesday | L24: 4 | M24: =FALSE() -> FALSE | N24: 2018-01
A25: 20180124 | B25: 2018-01-24 | C25: 2018 | D25: 2018 | E25: 1 | F25: Q1 | G25: 1 | H25: January | I25: Jan | J25: 24 | K25: Wednesday | L25: 4 | M25: =FALSE() -> FALSE | N25: 2018-01
A26: 20180125 | B26: 2018-01-25 | C26: 2018 | D26: 2018 | E26: 1 | F26: Q1 | G26: 1 | H26: January | I26: Jan | J26: 25 | K26: Thursday | L26: 4 | M26: =FALSE() -> FALSE | N26: 2018-01
A27: 20180126 | B27: 2018-01-26 | C27: 2018 | D27: 2018 | E27: 1 | F27: Q1 | G27: 1 | H27: January | I27: Jan | J27: 26 | K27: Friday | L27: 4 | M27: =FALSE() -> FALSE | N27: 2018-01
A28: 20180127 | B28: 2018-01-27 | C28: 2018 | D28: 2018 | E28: 1 | F28: Q1 | G28: 1 | H28: January | I28: Jan | J28: 27 | K28: Saturday | L28: 4 | M28: =TRUE() -> TRUE | N28: 2018-01
A29: 20180128 | B29: 2018-01-28 | C29: 2018 | D29: 2018 | E29: 1 | F29: Q1 | G29: 1 | H29: January | I29: Jan | J29: 28 | K29: Sunday | L29: 4 | M29: =TRUE() -> TRUE | N29: 2018-01
A30: 20180129 | B30: 2018-01-29 | C30: 2018 | D30: 2018 | E30: 1 | F30: Q1 | G30: 1 | H30: January | I30: Jan | J30: 29 | K30: Monday | L30: 5 | M30: =FALSE() -> FALSE | N30: 2018-01
A31: 20180130 | B31: 2018-01-30 | C31: 2018 | D31: 2018 | E31: 1 | F31: Q1 | G31: 1 | H31: January | I31: Jan | J31: 30 | K31: Tuesday | L31: 5 | M31: =FALSE() -> FALSE | N31: 2018-01
A32: 20180131 | B32: 2018-01-31 | C32: 2018 | D32: 2018 | E32: 1 | F32: Q1 | G32: 1 | H32: January | I32: Jan | J32: 31 | K32: Wednesday | L32: 5 | M32: =FALSE() -> FALSE | N32: 2018-01
A33: 20180201 | B33: 2018-02-01 | C33: 2018 | D33: 2018 | E33: 1 | F33: Q1 | G33: 2 | H33: February | I33: Feb | J33: 1 | K33: Thursday | L33: 5 | M33: =FALSE() -> FALSE | N33: 2018-02
A34: 20180202 | B34: 2018-02-02 | C34: 2018 | D34: 2018 | E34: 1 | F34: Q1 | G34: 2 | H34: February | I34: Feb | J34: 2 | K34: Friday | L34: 5 | M34: =FALSE() -> FALSE | N34: 2018-02
A35: 20180203 | B35: 2018-02-03 | C35: 2018 | D35: 2018 | E35: 1 | F35: Q1 | G35: 2 | H35: February | I35: Feb | J35: 3 | K35: Saturday | L35: 5 | M35: =TRUE() -> TRUE | N35: 2018-02
A36: 20180204 | B36: 2018-02-04 | C36: 2018 | D36: 2018 | E36: 1 | F36: Q1 | G36: 2 | H36: February | I36: Feb | J36: 4 | K36: Sunday | L36: 5 | M36: =TRUE() -> TRUE | N36: 2018-02
A37: 20180205 | B37: 2018-02-05 | C37: 2018 | D37: 2018 | E37: 1 | F37: Q1 | G37: 2 | H37: February | I37: Feb | J37: 5 | K37: Monday | L37: 6 | M37: =FALSE() -> FALSE | N37: 2018-02
A38: 20180206 | B38: 2018-02-06 | C38: 2018 | D38: 2018 | E38: 1 | F38: Q1 | G38: 2 | H38: February | I38: Feb | J38: 6 | K38: Tuesday | L38: 6 | M38: =FALSE() -> FALSE | N38: 2018-02
A39: 20180207 | B39: 2018-02-07 | C39: 2018 | D39: 2018 | E39: 1 | F39: Q1 | G39: 2 | H39: February | I39: Feb | J39: 7 | K39: Wednesday | L39: 6 | M39: =FALSE() -> FALSE | N39: 2018-02
A40: 20180208 | B40: 2018-02-08 | C40: 2018 | D40: 2018 | E40: 1 | F40: Q1 | G40: 2 | H40: February | I40: Feb | J40: 8 | K40: Thursday | L40: 6 | M40: =FALSE() -> FALSE | N40: 2018-02
A41: 20180209 | B41: 2018-02-09 | C41: 2018 | D41: 2018 | E41: 1 | F41: Q1 | G41: 2 | H41: February | I41: Feb | J41: 9 | K41: Friday | L41: 6 | M41: =FALSE() -> FALSE | N41: 2018-02
A42: 20180210 | B42: 2018-02-10 | C42: 2018 | D42: 2018 | E42: 1 | F42: Q1 | G42: 2 | H42: February | I42: Feb | J42: 10 | K42: Saturday | L42: 6 | M42: =TRUE() -> TRUE | N42: 2018-02
A43: 20180211 | B43: 2018-02-11 | C43: 2018 | D43: 2018 | E43: 1 | F43: Q1 | G43: 2 | H43: February | I43: Feb | J43: 11 | K43: Sunday | L43: 6 | M43: =TRUE() -> TRUE | N43: 2018-02
A44: 20180212 | B44: 2018-02-12 | C44: 2018 | D44: 2018 | E44: 1 | F44: Q1 | G44: 2 | H44: February | I44: Feb | J44: 12 | K44: Monday | L44: 7 | M44: =FALSE() -> FALSE | N44: 2018-02
A45: 20180213 | B45: 2018-02-13 | C45: 2018 | D45: 2018 | E45: 1 | F45: Q1 | G45: 2 | H45: February | I45: Feb | J45: 13 | K45: Tuesday | L45: 7 | M45: =FALSE() -> FALSE | N45: 2018-02
A46: 20180214 | B46: 2018-02-14 | C46: 2018 | D46: 2018 | E46: 1 | F46: Q1 | G46: 2 | H46: February | I46: Feb | J46: 14 | K46: Wednesday | L46: 7 | M46: =FALSE() -> FALSE | N46: 2018-02
A47: 20180215 | B47: 2018-02-15 | C47: 2018 | D47: 2018 | E47: 1 | F47: Q1 | G47: 2 | H47: February | I47: Feb | J47: 15 | K47: Thursday | L47: 7 | M47: =FALSE() -> FALSE | N47: 2018-02
A48: 20180216 | B48: 2018-02-16 | C48: 2018 | D48: 2018 | E48: 1 | F48: Q1 | G48: 2 | H48: February | I48: Feb | J48: 16 | K48: Friday | L48: 7 | M48: =FALSE() -> FALSE | N48: 2018-02
A49: 20180217 | B49: 2018-02-17 | C49: 2018 | D49: 2018 | E49: 1 | F49: Q1 | G49: 2 | H49: February | I49: Feb | J49: 17 | K49: Saturday | L49: 7 | M49: =TRUE() -> TRUE | N49: 2018-02
A50: 20180218 | B50: 2018-02-18 | C50: 2018 | D50: 2018 | E50: 1 | F50: Q1 | G50: 2 | H50: February | I50: Feb | J50: 18 | K50: Sunday | L50: 7 | M50: =TRUE() -> TRUE | N50: 2018-02
A51: 20180219 | B51: 2018-02-19 | C51: 2018 | D51: 2018 | E51: 1 | F51: Q1 | G51: 2 | H51: February | I51: Feb | J51: 19 | K51: Monday | L51: 8 | M51: =FALSE() -> FALSE | N51: 2018-02
A52: 20180220 | B52: 2018-02-20 | C52: 2018 | D52: 2018 | E52: 1 | F52: Q1 | G52: 2 | H52: February | I52: Feb | J52: 20 | K52: Tuesday | L52: 8 | M52: =FALSE() -> FALSE | N52: 2018-02
A53: 20180221 | B53: 2018-02-21 | C53: 2018 | D53: 2018 | E53: 1 | F53: Q1 | G53: 2 | H53: February | I53: Feb | J53: 21 | K53: Wednesday | L53: 8 | M53: =FALSE() -> FALSE | N53: 2018-02
A54: 20180222 | B54: 2018-02-22 | C54: 2018 | D54: 2018 | E54: 1 | F54: Q1 | G54: 2 | H54: February | I54: Feb | J54: 22 | K54: Thursday | L54: 8 | M54: =FALSE() -> FALSE | N54: 2018-02
A55: 20180223 | B55: 2018-02-23 | C55: 2018 | D55: 2018 | E55: 1 | F55: Q1 | G55: 2 | H55: February | I55: Feb | J55: 23 | K55: Friday | L55: 8 | M55: =FALSE() -> FALSE | N55: 2018-02
A56: 20180224 | B56: 2018-02-24 | C56: 2018 | D56: 2018 | E56: 1 | F56: Q1 | G56: 2 | H56: February | I56: Feb | J56: 24 | K56: Saturday | L56: 8 | M56: =TRUE() -> TRUE | N56: 2018-02
A57: 20180225 | B57: 2018-02-25 | C57: 2018 | D57: 2018 | E57: 1 | F57: Q1 | G57: 2 | H57: February | I57: Feb | J57: 25 | K57: Sunday | L57: 8 | M57: =TRUE() -> TRUE | N57: 2018-02
A58: 20180226 | B58: 2018-02-26 | C58: 2018 | D58: 2018 | E58: 1 | F58: Q1 | G58: 2 | H58: February | I58: Feb | J58: 26 | K58: Monday | L58: 9 | M58: =FALSE() -> FALSE | N58: 2018-02
A59: 20180227 | B59: 2018-02-27 | C59: 2018 | D59: 2018 | E59: 1 | F59: Q1 | G59: 2 | H59: February | I59: Feb | J59: 27 | K59: Tuesday | L59: 9 | M59: =FALSE() -> FALSE | N59: 2018-02
A60: 20180228 | B60: 2018-02-28 | C60: 2018 | D60: 2018 | E60: 1 | F60: Q1 | G60: 2 | H60: February | I60: Feb | J60: 28 | K60: Wednesday | L60: 9 | M60: =FALSE() -> FALSE | N60: 2018-02
A61: 20180301 | B61: 2018-03-01 | C61: 2018 | D61: 2018 | E61: 1 | F61: Q1 | G61: 3 | H61: March | I61: Mar | J61: 1 | K61: Thursday | L61: 9 | M61: =FALSE() -> FALSE | N61: 2018-03
A62: 20180302 | B62: 2018-03-02 | C62: 2018 | D62: 2018 | E62: 1 | F62: Q1 | G62: 3 | H62: March | I62: Mar | J62: 2 | K62: Friday | L62: 9 | M62: =FALSE() -> FALSE | N62: 2018-03
A63: 20180303 | B63: 2018-03-03 | C63: 2018 | D63: 2018 | E63: 1 | F63: Q1 | G63: 3 | H63: March | I63: Mar | J63: 3 | K63: Saturday | L63: 9 | M63: =TRUE() -> TRUE | N63: 2018-03
A64: 20180304 | B64: 2018-03-04 | C64: 2018 | D64: 2018 | E64: 1 | F64: Q1 | G64: 3 | H64: March | I64: Mar | J64: 4 | K64: Sunday | L64: 9 | M64: =TRUE() -> TRUE | N64: 2018-03
A65: 20180305 | B65: 2018-03-05 | C65: 2018 | D65: 2018 | E65: 1 | F65: Q1 | G65: 3 | H65: March | I65: Mar | J65: 5 | K65: Monday | L65: 10 | M65: =FALSE() -> FALSE | N65: 2018-03
A66: 20180306 | B66: 2018-03-06 | C66: 2018 | D66: 2018 | E66: 1 | F66: Q1 | G66: 3 | H66: March | I66: Mar | J66: 6 | K66: Tuesday | L66: 10 | M66: =FALSE() -> FALSE | N66: 2018-03
A67: 20180307 | B67: 2018-03-07 | C67: 2018 | D67: 2018 | E67: 1 | F67: Q1 | G67: 3 | H67: March | I67: Mar | J67: 7 | K67: Wednesday | L67: 10 | M67: =FALSE() -> FALSE | N67: 2018-03
A68: 20180308 | B68: 2018-03-08 | C68: 2018 | D68: 2018 | E68: 1 | F68: Q1 | G68: 3 | H68: March | I68: Mar | J68: 8 | K68: Thursday | L68: 10 | M68: =FALSE() -> FALSE | N68: 2018-03
A69: 20180309 | B69: 2018-03-09 | C69: 2018 | D69: 2018 | E69: 1 | F69: Q1 | G69: 3 | H69: March | I69: Mar | J69: 9 | K69: Friday | L69: 10 | M69: =FALSE() -> FALSE | N69: 2018-03
A70: 20180310 | B70: 2018-03-10 | C70: 2018 | D70: 2018 | E70: 1 | F70: Q1 | G70: 3 | H70: March | I70: Mar | J70: 10 | K70: Saturday | L70: 10 | M70: =TRUE() -> TRUE | N70: 2018-03
A71: 20180311 | B71: 2018-03-11 | C71: 2018 | D71: 2018 | E71: 1 | F71: Q1 | G71: 3 | H71: March | I71: Mar | J71: 11 | K71: Sunday | L71: 10 | M71: =TRUE() -> TRUE | N71: 2018-03
A72: 20180312 | B72: 2018-03-12 | C72: 2018 | D72: 2018 | E72: 1 | F72: Q1 | G72: 3 | H72: March | I72: Mar | J72: 12 | K72: Monday | L72: 11 | M72: =FALSE() -> FALSE | N72: 2018-03
A73: 20180313 | B73: 2018-03-13 | C73: 2018 | D73: 2018 | E73: 1 | F73: Q1 | G73: 3 | H73: March | I73: Mar | J73: 13 | K73: Tuesday | L73: 11 | M73: =FALSE() -> FALSE | N73: 2018-03
A74: 20180314 | B74: 2018-03-14 | C74: 2018 | D74: 2018 | E74: 1 | F74: Q1 | G74: 3 | H74: March | I74: Mar | J74: 14 | K74: Wednesday | L74: 11 | M74: =FALSE() -> FALSE | N74: 2018-03
A75: 20180315 | B75: 2018-03-15 | C75: 2018 | D75: 2018 | E75: 1 | F75: Q1 | G75: 3 | H75: March | I75: Mar | J75: 15 | K75: Thursday | L75: 11 | M75: =FALSE() -> FALSE | N75: 2018-03
A76: 20180316 | B76: 2018-03-16 | C76: 2018 | D76: 2018 | E76: 1 | F76: Q1 | G76: 3 | H76: March | I76: Mar | J76: 16 | K76: Friday | L76: 11 | M76: =FALSE() -> FALSE | N76: 2018-03
A77: 20180317 | B77: 2018-03-17 | C77: 2018 | D77: 2018 | E77: 1 | F77: Q1 | G77: 3 | H77: March | I77: Mar | J77: 17 | K77: Saturday | L77: 11 | M77: =TRUE() -> TRUE | N77: 2018-03
A78: 20180318 | B78: 2018-03-18 | C78: 2018 | D78: 2018 | E78: 1 | F78: Q1 | G78: 3 | H78: March | I78: Mar | J78: 18 | K78: Sunday | L78: 11 | M78: =TRUE() -> TRUE | N78: 2018-03
A79: 20180319 | B79: 2018-03-19 | C79: 2018 | D79: 2018 | E79: 1 | F79: Q1 | G79: 3 | H79: March | I79: Mar | J79: 19 | K79: Monday | L79: 12 | M79: =FALSE() -> FALSE | N79: 2018-03
A80: 20180320 | B80: 2018-03-20 | C80: 2018 | D80: 2018 | E80: 1 | F80: Q1 | G80: 3 | H80: March | I80: Mar | J80: 20 | K80: Tuesday | L80: 12 | M80: =FALSE() -> FALSE | N80: 2018-03
A81: 20180321 | B81: 2018-03-21 | C81: 2018 | D81: 2018 | E81: 1 | F81: Q1 | G81: 3 | H81: March | I81: Mar | J81: 21 | K81: Wednesday | L81: 12 | M81: =FALSE() -> FALSE | N81: 2018-03
A82: 20180322 | B82: 2018-03-22 | C82: 2018 | D82: 2018 | E82: 1 | F82: Q1 | G82: 3 | H82: March | I82: Mar | J82: 22 | K82: Thursday | L82: 12 | M82: =FALSE() -> FALSE | N82: 2018-03
A83: 20180323 | B83: 2018-03-23 | C83: 2018 | D83: 2018 | E83: 1 | F83: Q1 | G83: 3 | H83: March | I83: Mar | J83: 23 | K83: Friday | L83: 12 | M83: =FALSE() -> FALSE | N83: 2018-03
A84: 20180324 | B84: 2018-03-24 | C84: 2018 | D84: 2018 | E84: 1 | F84: Q1 | G84: 3 | H84: March | I84: Mar | J84: 24 | K84: Saturday | L84: 12 | M84: =TRUE() -> TRUE | N84: 2018-03
A85: 20180325 | B85: 2018-03-25 | C85: 2018 | D85: 2018 | E85: 1 | F85: Q1 | G85: 3 | H85: March | I85: Mar | J85: 25 | K85: Sunday | L85: 12 | M85: =TRUE() -> TRUE | N85: 2018-03
A86: 20180326 | B86: 2018-03-26 | C86: 2018 | D86: 2018 | E86: 1 | F86: Q1 | G86: 3 | H86: March | I86: Mar | J86: 26 | K86: Monday | L86: 13 | M86: =FALSE() -> FALSE | N86: 2018-03
A87: 20180327 | B87: 2018-03-27 | C87: 2018 | D87: 2018 | E87: 1 | F87: Q1 | G87: 3 | H87: March | I87: Mar | J87: 27 | K87: Tuesday | L87: 13 | M87: =FALSE() -> FALSE | N87: 2018-03
A88: 20180328 | B88: 2018-03-28 | C88: 2018 | D88: 2018 | E88: 1 | F88: Q1 | G88: 3 | H88: March | I88: Mar | J88: 28 | K88: Wednesday | L88: 13 | M88: =FALSE() -> FALSE | N88: 2018-03
A89: 20180329 | B89: 2018-03-29 | C89: 2018 | D89: 2018 | E89: 1 | F89: Q1 | G89: 3 | H89: March | I89: Mar | J89: 29 | K89: Thursday | L89: 13 | M89: =FALSE() -> FALSE | N89: 2018-03
A90: 20180330 | B90: 2018-03-30 | C90: 2018 | D90: 2018 | E90: 1 | F90: Q1 | G90: 3 | H90: March | I90: Mar | J90: 30 | K90: Friday | L90: 13 | M90: =FALSE() -> FALSE | N90: 2018-03
A91: 20180331 | B91: 2018-03-31 | C91: 2018 | D91: 2018 | E91: 1 | F91: Q1 | G91: 3 | H91: March | I91: Mar | J91: 31 | K91: Saturday | L91: 13 | M91: =TRUE() -> TRUE | N91: 2018-03
A92: 20180401 | B92: 2018-04-01 | C92: 2018 | D92: 2018 | E92: 2 | F92: Q2 | G92: 4 | H92: April | I92: Apr | J92: 1 | K92: Sunday | L92: 13 | M92: =TRUE() -> TRUE | N92: 2018-04
A93: 20180402 | B93: 2018-04-02 | C93: 2018 | D93: 2018 | E93: 2 | F93: Q2 | G93: 4 | H93: April | I93: Apr | J93: 2 | K93: Monday | L93: 14 | M93: =FALSE() -> FALSE | N93: 2018-04
A94: 20180403 | B94: 2018-04-03 | C94: 2018 | D94: 2018 | E94: 2 | F94: Q2 | G94: 4 | H94: April | I94: Apr | J94: 3 | K94: Tuesday | L94: 14 | M94: =FALSE() -> FALSE | N94: 2018-04
A95: 20180404 | B95: 2018-04-04 | C95: 2018 | D95: 2018 | E95: 2 | F95: Q2 | G95: 4 | H95: April | I95: Apr | J95: 4 | K95: Wednesday | L95: 14 | M95: =FALSE() -> FALSE | N95: 2018-04
A96: 20180405 | B96: 2018-04-05 | C96: 2018 | D96: 2018 | E96: 2 | F96: Q2 | G96: 4 | H96: April | I96: Apr | J96: 5 | K96: Thursday | L96: 14 | M96: =FALSE() -> FALSE | N96: 2018-04
A97: 20180406 | B97: 2018-04-06 | C97: 2018 | D97: 2018 | E97: 2 | F97: Q2 | G97: 4 | H97: April | I97: Apr | J97: 6 | K97: Friday | L97: 14 | M97: =FALSE() -> FALSE | N97: 2018-04
A98: 20180407 | B98: 2018-04-07 | C98: 2018 | D98: 2018 | E98: 2 | F98: Q2 | G98: 4 | H98: April | I98: Apr | J98: 7 | K98: Saturday | L98: 14 | M98: =TRUE() -> TRUE | N98: 2018-04
A99: 20180408 | B99: 2018-04-08 | C99: 2018 | D99: 2018 | E99: 2 | F99: Q2 | G99: 4 | H99: April | I99: Apr | J99: 8 | K99: Sunday | L99: 14 | M99: =TRUE() -> TRUE | N99: 2018-04
A100: 20180409 | B100: 2018-04-09 | C100: 2018 | D100: 2018 | E100: 2 | F100: Q2 | G100: 4 | H100: April | I100: Apr | J100: 9 | K100: Monday | L100: 15 | M100: =FALSE() -> FALSE | N100: 2018-04
...

Sheet Fact_PerformanceReviews
A1: ReviewID | B1: EmployeeID | C1: ReviewDate | D1: ReviewYear | E1: PerformanceRating | F1: EngagementScorePercent | G1: JobSatisfactionScore | H1: ManagerFeedbackScore | I1: GoalsAchievedPercent | J1: TrainingHoursCompleted | K1: PromotionRecommended
A2: REV00001 | B2: EMP0001 | C2: 2025-02-17 | D2: 2025 | E2: 4 | F2: 62 | G2: 3 | H2: 4 | I2: 58 | J2: 36 | K2: No
A3: REV00002 | B3: EMP0001 | C3: 2026-03-24 | D3: 2026 | E3: 1 | F3: 39 | G3: 4 | H3: 3 | I3: 73 | J3: 30 | K3: No
A4: REV00003 | B4: EMP0002 | C4: 2025-04-13 | D4: 2025 | E4: 2 | F4: 68 | G4: 3 | H4: 5 | I4: 79 | J4: 41 | K4: No
A5: REV00004 | B5: EMP0003 | C5: 2021-04-13 | D5: 2021 | E5: 2 | F5: 86 | G5: 3 | H5: 3 | I5: 74 | J5: 10 | K5: No
A6: REV00005 | B6: EMP0003 | C6: 2022-03-27 | D6: 2022 | E6: 2 | F6: 75 | G6: 2 | H6: 3 | I6: 53 | J6: 11 | K6: No
A7: REV00006 | B7: EMP0003 | C7: 2023-12-18 | D7: 2023 | E7: 3 | F7: 81 | G7: 4 | H7: 3 | I7: 94 | J7: 21 | K7: No
A8: REV00007 | B8: EMP0003 | C8: 2024-10-27 | D8: 2024 | E8: 4 | F8: 58 | G8: 3 | H8: 2 | I8: 91 | J8: 34 | K8: Yes
A9: REV00008 | B9: EMP0003 | C9: 2025-12-15 | D9: 2025 | E9: 4 | F9: 92 | G9: 3 | H9: 2 | I9: 109 | J9: 35 | K9: No
A10: REV00009 | B10: EMP0004 | C10: 2024-07-27 | D10: 2024 | E10: 3 | F10: 63 | G10: 2 | H10: 3 | I10: 88 | J10: 40 | K10: No
A11: REV00010 | B11: EMP0004 | C11: 2025-07-06 | D11: 2025 | E11: 4 | F11: 75 | G11: 2 | H11: 5 | I11: 78 | J11: 5 | K11: Yes
A12: REV00011 | B12: EMP0004 | C12: 2026-06-21 | D12: 2026 | E12: 2 | F12: 53 | G12: 3 | H12: 5 | I12: 94 | J12: 37 | K12: No
A13: REV00012 | B13: EMP0005 | C13: 2022-07-07 | D13: 2022 | E13: 3 | F13: 97 | G13: 4 | H13: 4 | I13: 74 | J13: 1 | K13: No
... A3174: REV03173 | B3174: EMP1000 | C3174: 2025-02-16 | D3174: 2025 | E3174: 1 | F3174: 45 | G3174: 2 | H3174: 3 | I3174: 98 | J3174: 37 | K3174: No
