Workbook

Sheet README
B2: GEREGU POWER ENERGY PLC — TABLEAU DASHBOARD TRAINING DATASET
B3: Simulated multi-department dataset for Tableau training purposes
B5: Prepared by: Kajola Gbenga
B6: Data Scientist & AI Engineer
B9: Sheet Name | C9: Purpose | D9: Key Columns Linking to Other Sheets
B10: Dim_Date | C10: Central date dimension - connect to every transactional sheet's Date field for time intelligence. | D10: Date
B11: Dim_Department | C11: Department master list with mandate and head of department. | D11: Department_ID, Department_Name, Head_Employee_ID
B12: Dim_Employee | C12: Employee master (HR) - connects to every other sheet through Employee_ID. | D12: Employee_ID, Department
B13: Operations | C13: Daily plant/unit generation performance. | D13: Employee_ID, Date
B14: Legal | C14: Contracts, litigation and regulatory case tracking. | D14: Employee_ID, Date_Opened, Department_Linked
B15: Supply_Chain | C15: Procurement and vendor purchase orders. | D15: Employee_ID, Date
B16: Admin | C16: Facilities, assets, travel and fleet requests. | D16: Employee_ID, Date
B17: Customer_Service | C17: DisCo/off-taker ticket and complaints log. | D17: Employee_ID, Date
B18: IT | C18: Systems and SCADA support ticket log. | D18: Employee_ID, Date
B19: Accounts_Finance | C19: Revenue, opex and capex transactions vs budget. | D19: Employee_ID, Date, Department_Linked
B20: Human_Resources | C20: Leave, training, appraisal and disciplinary records. | D20: Employee_ID, Date, Department
... B22: Risk_Mgmt_Compliance | C22: Enterprise risk register with likelihood x impact scoring. | D22: Employee_ID, Date_Identified, Department_Linked
B25: Color legend:
B26: Blue text = linking/key column (e.g. Employee_ID)
B27: Green text = formula pulling data from another sheet (e.g. Employee_Name via INDEX/MATCH)
B28: Black text = raw / hardcoded source data entered for the simulation
B30: How to use this workbook in Tableau:
B31: 1. Connect Tableau to this Excel file (Data > Connect to Data > Microsoft Excel).
B32: 2. Drag Dim_Employee and Dim_Department onto the canvas, then add each transactional sheet.
B33: 3. Build relationships (not physical joins) using Employee_ID as the linking field, and Date to Dim_Date's Date field.
B34: 4. This keeps each department's grain intact while allowing cross-department analysis in one data source.

Sheet Dim_Date
A1: Date | B1: Year | C1: Quarter | D1: Month_No | E1: Month_Name | F1: Week_No | G1: Day_Name | H1: Is_Weekend
A2: 45658 | B2: 2025 | C2: Q1 | D2: 1 | E2: January | F2: 1 | G2: Wednesday | H2: No
A3: 45659 | B3: 2025 | C3: Q1 | D3: 1 | E3: January | F3: 1 | G3: Thursday | H3: No
A4: 45660 | B4: 2025 | C4: Q1 | D4: 1 | E4: January | F4: 1 | G4: Friday | H4: No
A5: 45661 | B5: 2025 | C5: Q1 | D5: 1 | E5: January | F5: 1 | G5: Saturday | H5: Yes
A6: 45662 | B6: 2025 | C6: Q1 | D6: 1 | E6: January | F6: 1 | G6: Sunday | H6: Yes
A7: 45663 | B7: 2025 | C7: Q1 | D7: 1 | E7: January | F7: 2 | G7: Monday | H7: No
A8: 45664 | B8: 2025 | C8: Q1 | D8: 1 | E8: January | F8: 2 | G8: Tuesday | H8: No
A9: 45665 | B9: 2025 | C9: Q1 | D9: 1 | E9: January | F9: 2 | G9: Wednesday | H9: No
A10: 45666 | B10: 2025 | C10: Q1 | D10: 1 | E10: January | F10: 2 | G10: Thursday | H10: No
A11: 45667 | B11: 2025 | C11: Q1 | D11: 1 | E11: January | F11: 2 | G11: Friday | H11: No
A12: 45668 | B12: 2025 | C12: Q1 | D12: 1 | E12: January | F12: 2 | G12: Saturday | H12: Yes
A13: 45669 | B13: 2025 | C13: Q1 | D13: 1 | E13: January | F13: 2 | G13: Sunday | H13: Yes
... A366: 46022 | B366: 2025 | C366: Q4 | D366: 12 | E366: December | F366: 1 | G366: Wednesday | H366: No

Sheet Dim_Department
A1: Department_ID | B1: Department_Name | C1: Location | D1: Department_Mandate | E1: Head_Employee_ID
A2: DPT01 | B2: Operations | C2: Kogi Plant Site | D2: Power generation and plant performance | E2: EMP0001
A3: DPT02 | B3: Legal | C3: Head Office - Abuja | D3: Contracts, litigation and regulatory affairs | E3: EMP0017
A4: DPT03 | B4: Supply Chain | C4: Head Office - Abuja | D4: Procurement, vendor and inventory management | E4: EMP0022
A5: DPT04 | B5: Admin | C5: Kogi Plant Site | D5: Facilities, assets and general administration | E5: EMP0030
A6: DPT05 | B6: Customer Service | C6: Head Office - Abuja | D6: DisCo and off-taker relationship management | E6: EMP0036
A7: DPT06 | B7: IT | C7: Head Office - Abuja | D7: Systems, SCADA support and infrastructure | E7: EMP0043
A8: DPT07 | B8: Accounts and Finance | C8: Head Office - Abuja | D8: Revenue, expenditure and financial reporting | E8: EMP0050
A9: DPT08 | B9: Human Resources | C9: Head Office - Abuja | D9: Recruitment, welfare, training and payroll | E9: EMP0058
A10: DPT09 | B10: Internal Control | C10: Head Office - Abuja | D10: Internal audit and process assurance | E10: EMP0065
A11: DPT10 | B11: Risk Management and Compliance | C11: Head Office - Abuja | D11: Enterprise risk and regulatory compliance | E11: EMP0070

Sheet Dim_Employee
A1: Employee_ID | B1: Employee_Name | C1: Department | D1: Job_Title | E1: Gender | F1: Date_Hired | G1: Employment_Status | H1: Work_Email | I1: Phone_Number
A2: EMP0001 | B2: Ngozi Okafor | C2: Operations | D2: Plant Manager | E2: Female | F2: 44625 | G2: Active | H2: ngozi.okafor@geregupower.com | I2: 08023756669
A3: EMP0002 | B3: Abdullahi Adeyemi | C3: Operations | D3: Shift Engineer | E3: Female | F3: 45498 | G3: Active | H3: abdullahi.adeyemi@geregupower.com | I3: 08039345092
A4: EMP0003 | B4: Olamide Sani | C4: Operations | D4: Turbine Technician | E4: Male | F4: 43330 | G4: Active | H4: olamide.sani@geregupower.com | I4: 08097226012
A5: EMP0004 | B5: Abdullahi Aliyu | C5: Operations | D5: Control Room Operator | E5: Male | F5: 43789 | G5: Active | H5: abdullahi.aliyu@geregupower.com | I5: 08010872248
A6: EMP0005 | B6: Kelechi Ojo | C6: Operations | D6: HSE Officer | E6: Female | F6: 44235 | G6: Active | H6: kelechi.ojo@geregupower.com | I6: 08038898923
A7: EMP0006 | B7: Halima Nwosu | C7: Operations | D7: Maintenance Engineer | E7: Male | F7: 44072 | G7: Active | H7: halima.nwosu@geregupower.com | I7: 08056164955
A8: EMP0007 | B8: Emmanuel Yakubu | C8: Operations | D8: Plant Manager | E8: Male | F8: 42640 | G8: Active | H8: emmanuel.yakubu@geregupower.com | I8: 08026753883
A9: EMP0008 | B9: Musa Adeyemi | C9: Operations | D9: Shift Engineer | E9: Female | F9: 42231 | G9: Active | H9: musa.adeyemi@geregupower.com | I9: 08058537831
A10: EMP0009 | B10: Kingsley Okonkwo | C10: Operations | D10: Turbine Technician | E10: Male | F10: 45441 | G10: Active | H10: kingsley.okonkwo@geregupower.com | I10: 08048840994
A11: EMP0010 | B11: Amaka Bakare | C11: Operations | D11: Control Room Operator | E11: Male | F11: 42079 | G11: Active | H11: amaka.bakare@geregupower.com | I11: 08047308985
A12: EMP0011 | B12: Titilayo Danjuma | C12: Operations | D12: HSE Officer | E12: Female | F12: 44962 | G12: Active | H12: titilayo.danjuma@geregupower.com | I12: 08038119557
A13: EMP0012 | B13: Uche Ojo | C13: Operations | D13: Maintenance Engineer | E13: Male | F13: 43133 | G13: Active | H13: uche.ojo@geregupower.com | I13: 08081691040
... A76: EMP0075 | B76: Halima Okafor | C76: Risk Management and Compliance | D76: Risk Analyst | E76: Male | F76: 42036 | G76: Resigned | H76: halima.okafor@geregupower.com | I76: 08033966966

Sheet Operations
A1: Record_ID | B1: Date | C1: Plant_Unit | D1: Employee_ID | E1: Employee_Name | F1: Shift | G1: Power_Generated_MWh | H1: Planned_Output_MWh | I1: Availability_Percent | J1: Downtime_Hours | K1: Downtime_Reason | L1: Fuel_Type | M1: Fuel_Consumed_MMscf | N1: Turbine_Temperature_C | O1: Maintenance_Status
A2: OPS00001 | B2: 45932 | C2: GT1 | D2: EMP0011 | E2: =IFERROR(INDEX(Dim_Employee!$B$2:$B$76,MATCH(D2,Dim_Employee!$A$2:$A$76,0)),"") -> Titilayo Danjuma | F2: Afternoon | G2: 99.3 | H2: 118.4 | I2: =ROUND(G2/H2*100,1) -> 83.9 | J2: 2.1 | K2: Scheduled Maintenance | L2: Natural Gas | M2: 22.48 | N2: 510.1 | O2: Normal
A3: OPS00002 | B3: 45688 | C3: GT1 | D3: EMP0014 | E3: =IFERROR(INDEX(Dim_Employee!$B$2:$B$76,MATCH(D3,Dim_Employee!$A$2:$A$76,0)),"") -> Peace Balogun | F3: Morning | G3: 81.2 | H3: 102.5 | I3: =ROUND(G3/H3*100,1) -> 79.2 | J3: 4.5 | K3: Gas Supply Shortage | L3: Natural Gas | M3: 17.32 | N3: 488.7 | O3: Scheduled
A4: OPS00003 | B4: 45806 | C4: ST1 | D4: EMP0002 | E4: =IFERROR(INDEX(Dim_Employee!$B$2:$B$76,MATCH(D4,Dim_Employee!$A$2:$A$76,0)),"") -> Abdullahi Adeyemi | F4: Morning | G4: 87.6 | H4: 119.3 | I4: =ROUND(G4/H4*100,1) -> 73.4 | J4: 8.6 | K4: Scheduled Maintenance | L4: Natural Gas | M4: 18.64 | N4: 558.4 | O4: Under Inspection
A5: OPS00004 | B5: 45938 | C5: GT1 | D5: EMP0004 | E5: =IFERROR(INDEX(Dim_Employee!$B$2:$B$76,MATCH(D5,Dim_Employee!$A$2:$A$76,0)),"") -> Abdullahi Aliyu | F5: Night | G5: 97.9 | H5: 107.4 | I5: =ROUND(G5/H5*100,1) -> 91.2 | J5: 1.7 | K5: None | L5: Natural Gas | M5: 19.41 | N5: 575.3 | O5: Scheduled
A6: OPS00005 | B6: 45785 | C6: GT2 | D6: EMP0011 | E6: =IFERROR(INDEX(Dim_Employee!$B$2:$B$76,MATCH(D6,Dim_Employee!$A$2:$A$76,0)),"") -> Titilayo Danjuma | F6: Night | G6: 103.7 | H6: 104 | I6: =ROUND(G6/H6*100,1) -> 99.7 | J6: 0.1 | K6: Grid Instability | L6: Natural Gas | M6: 20.04 | N6: 522 | O6: Scheduled
A7: OPS00006 | B7: 45718 | C7: ST1 | D7: EMP0011 | E7: =IFERROR(INDEX(Dim_Employee!$B$2:$B$76,MATCH(D7,Dim_Employee!$A$2:$A$76,0)),"") -> Titilayo Danjuma | F7: Morning | G7: 90.2 | H7: 111.9 | I7: =ROUND(G7/H7*100,1) -> 80.6 | J7: 6.4 | K7: Grid Instability | L7: Natural Gas | M7: 17.69 | N7: 548.5 | O7: Normal
A8: OPS00007 | B8: 45818 | C8: GT3 | D8: EMP0003 | E8: =IFERROR(INDEX(Dim_Employee!$B$2:$B$76,MATCH(D8,Dim_Employee!$A$2:$A$76,0)),"") -> Olamide Sani | F8: Night | G8: 100.7 | H8: 112.9 | I8: =ROUND(G8/H8*100,1) -> 89.2 | J8: 3.4 | K8: None | L8: Natural Gas | M8: 21.13 | N8: 591.6 | O8: Normal
A9: OPS00008 | B9: 45689 | C9: GT3 | D9: EMP0003 | E9: =IFERROR(INDEX(Dim_Employee!$B$2:$B$76,MATCH(D9,Dim_Employee!$A$2:$A$76,0)),"") -> Olamide Sani | F9: Night | G9: 102 | H9: 118.3 | I9: =ROUND(G9/H9*100,1) -> 86.2 | J9: 3.8 | K9: Scheduled Maintenance | L9: Natural Gas | M9: 22.16 | N9: 542.4 | O9: Scheduled
A10: OPS00009 | B10: 45717 | C10: ST1 | D10: EMP0012 | E10: =IFERROR(INDEX(Dim_Employee!$B$2:$B$76,MATCH(D10,Dim_Employee!$A$2:$A$76,0)),"") -> Uche Ojo | F10: Morning | G10: 77.9 | H10: 90.7 | I10: =ROUND(G10/H10*100,1) -> 85.9 | J10: 1.7 | K10: None | L10: Natural Gas | M10: 15.7 | N10: 583.4 | O10: Scheduled
A11: OPS00010 | B11: 45863 | C11: GT3 | D11: EMP0013 | E11: =IFERROR(INDEX(Dim_Employee!$B$2:$B$76,MATCH(D11,Dim_Employee!$A$2:$A$76,0)),"") -> Chukwudi Eze | F11: Morning | G11: 102.1 | H11: 117.5 | I11: =ROUND(G11/H11*100,1) -> 86.9 | J11: 2.1 | K11: Grid Instability | L11: Natural Gas | M11: 22.93 | N11: 519 | O11: Scheduled
A12: OPS00011 | B12: 45700 | C12: GT2 | D12: EMP0012 | E12: =IFERROR(INDEX(Dim_Employee!$B$2:$B$76,MATCH(D12,Dim_Employee!$A$2:$A$76,0)),"") -> Uche Ojo | F12: Morning | G12: 92.2 | H12: 110.5 | I12: =ROUND(G12/H12*100,1) -> 83.4 | J12: 2.7 | K12: None | L12: Natural Gas | M12: 18.38 | N12: 547.9 | O12: Under Inspection
A13: OPS00012 | B13: 45970 | C13: GT3 | D13: EMP0009 | E13: =IFERROR(INDEX(Dim_Employee!$B$2:$B$76,MATCH(D13,Dim_Employee!$A$2:$A$76,0)),"") -> Kingsley Okonkwo | F13: Morning | G13: 75.2 | H13: 98.5 | I13: =ROUND(G13/H13*100,1) -> 76.3 | J13: 4.8 | K13: Gas Supply Shortage | L13: Natural Gas | M13: 15.84 | N13: 566.5 | O13: Normal
... A221: OPS00220 | B221: 45855 | C221: GT3 | D221: EMP0013 | E221: =IFERROR(INDEX(Dim_Employee!$B$2:$B$76,MATCH(D221,Dim_Employee!$A$2:$A$76,0)),"") -> Chukwudi Eze | F221: Afternoon | G221: 80.6 | H221: 106.8 | I221: =ROUND(G221/H221*100,1) -> 75.5 | J221: 5.4 | K221: Gas Supply Shortage | L221: Natural Gas | M221: 18.41 | N221: 539.1 | O221: Under Repair

Sheet Legal
A1: Case_ID | B1: Date_Opened | C1: Employee_ID | D1: Employee_Name | E1: Department_Linked | F1: Case_Type | G1: Counterparty | H1: Risk_Level | I1: Case_Status | J1: Resolution_Date | K1: Cost_Incurred_NGN
A2: LEG0001 | B2: 45783 | C2: EMP0021 | D2: =IFERROR(INDEX(Dim_Employee!$B$2:$B$76,MATCH(C2,Dim_Employee!$A$2:$A$76,0)),"") -> Tunde Nnamdi | E2: Supply Chain | F2: Compliance Advisory | G2: Local Vendor Ltd | H2: Low | I2: Under Review | K2: 2206103.4
A3: LEG0002 | B3: 45998 | C3: EMP0019 | D3: =IFERROR(INDEX(Dim_Employee!$B$2:$B$76,MATCH(C3,Dim_Employee!$A$2:$A$76,0)),"") -> Yusuf Sani | E3: Admin | F3: Litigation | G3: Distribution Company - Abuja Disco | H3: Medium | I3: Open | K3: 508524.96
A4: LEG0003 | B4: 45936 | C4: EMP0019 | D4: =IFERROR(INDEX(Dim_Employee!$B$2:$B$76,MATCH(C4,Dim_Employee!$A$2:$A$76,0)),"") -> Yusuf Sani | E4: Accounts and Finance | F4: Compliance Advisory | G4: Distribution Company - Abuja Disco | H4: Low | I4: Closed | J4: 46017 | K4: 1796947.4
A5: LEG0004 | B5: 45850 | C5: EMP0020 | D5: =IFERROR(INDEX(Dim_Employee!$B$2:$B$76,MATCH(C5,Dim_Employee!$A$2:$A$76,0)),"") -> Aisha Danjuma | E5: Accounts and Finance | F5: Land/Right-of-Way | G5: Distribution Company - Abuja Disco | H5: Low | I5: Closed | J5: 45898 | K5: 2290826.2
A6: LEG0005 | B6: 46019 | C6: EMP0018 | D6: =IFERROR(INDEX(Dim_Employee!$B$2:$B$76,MATCH(C6,Dim_Employee!$A$2:$A$76,0)),"") -> Abdullahi Yakubu | E6: Human Resources | F6: Compliance Advisory | G6: NERC | H6: Medium | I6: Pending Court Date | K6: 2050545.6
A7: LEG0006 | B7: 45766 | C7: EMP0021 | D7: =IFERROR(INDEX(Dim_Employee!$B$2:$B$76,MATCH(C7,Dim_Employee!$A$2:$A$76,0)),"") -> Tunde Nnamdi | E7: Operations | F7: Land/Right-of-Way | G7: NBET | H7: Medium | I7: Closed | J7: 45872 | K7: 1388525.2
A8: LEG0007 | B8: 45672 | C8: EMP0020 | D8: =IFERROR(INDEX(Dim_Employee!$B$2:$B$76,MATCH(C8,Dim_Employee!$A$2:$A$76,0)),"") -> Aisha Danjuma | E8: Operations | F8: Compliance Advisory | G8: NBET | H8: Medium | I8: Closed | J8: 45721 | K8: 3891882.5
A9: LEG0008 | B9: 45822 | C9: EMP0018 | D9: =IFERROR(INDEX(Dim_Employee!$B$2:$B$76,MATCH(C9,Dim_Employee!$A$2:$A$76,0)),"") -> Abdullahi Yakubu | E9: Operations | F9: Contract Review | G9: Insurance Underwriter | H9: High | I9: Closed | J9: 45916 | K9: 4035642.7
A10: LEG0009 | B10: 45756 | C10: EMP0019 | D10: =IFERROR(INDEX(Dim_Employee!$B$2:$B$76,MATCH(C10,Dim_Employee!$A$2:$A$76,0)),"") -> Yusuf Sani | E10: Customer Service | F10: Regulatory Filing | G10: NBET | H10: Low | I10: Open | K10: 674356.25
A11: LEG0010 | B11: 45802 | C11: EMP0020 | D11: =IFERROR(INDEX(Dim_Employee!$B$2:$B$76,MATCH(C11,Dim_Employee!$A$2:$A$76,0)),"") -> Aisha Danjuma | E11: Accounts and Finance | F11: Compliance Advisory | G11: Distribution Company - Ikeja Disco | H11: High | I11: Pending Court Date | K11: 923147.5
A12: LEG0011 | B12: 46005 | C12: EMP0019 | D12: =IFERROR(INDEX(Dim_Employee!$B$2:$B$76,MATCH(C12,Dim_Employee!$A$2:$A$76,0)),"") -> Yusuf Sani | E12: Accounts and Finance | F12: Contract Review | G12: Community Association | H12: Low | I12: Pending Court Date | K12: 4241235.8
A13: LEG0012 | B13: 45979 | C13: EMP0019 | D13: =IFERROR(INDEX(Dim_Employee!$B$2:$B$76,MATCH(C13,Dim_Employee!$A$2:$A$76,0)),"") -> Yusuf Sani | E13: Supply Chain | F13: Regulatory Filing | G13: NBET | H13: Low | I13: Open | K13: 3064138
A14: LEG0013 | B14: 46022 | C14: EMP0018 | D14: =IFERROR(INDEX(Dim_Employee!$B$2:$B$76,MATCH(C14,Dim_Employee!$A$2:$A$76,0)),"") -> Abdullahi Yakubu | E14: Accounts and Finance | F14: Contract Review | G14: Distribution Company - Ikeja Disco | H14: Medium | I14: Open | K14: 3796950.5
A15: LEG0014 | B15: 45852 | C15: EMP0018 | D15: =IFERROR(INDEX(Dim_Employee!$B$2:$B$76,MATCH(C15,Dim_Employee!$A$2:$A$76,0)),"") -> Abdullahi Yakubu | E15: Human Resources | F15: Regulatory Filing | G15: Distribution Company - Ikeja Disco | H15: Medium | I15: Open | K15: 1176892.1
A16: LEG0015 | B16: 45924 | C16: EMP0020 | D16: =IFERROR(INDEX(Dim_Employee!$B$2:$B$76,MATCH(C16,Dim_Employee!$A$2:$A$76,0)),"") -> Aisha Danjuma | E16: Accounts and Finance | F16: Land/Right-of-Way | G16: NERC | H16: High | I16: Pending Court Date | K16: 603767
A17: LEG0016 | B17: 45679 | C17: EMP0019 | D17: =IFERROR(INDEX(Dim_Employee!$B$2:$B$76,MATCH(C17,Dim_Employee!$A$2:$A$76,0)),"") -> Yusuf Sani | E17: Supply Chain | F17: Contract Review | G17: TCN | H17: Medium | I17: Open | K17: 1090188.9
A18: LEG0017 | B18: 45702 | C18: EMP0019 | D18: =IFERROR(INDEX(Dim_Employee!$B$2:$B$76,MATCH(C18,Dim_Employee!$A$2:$A$76,0)),"") -> Yusuf Sani | E18: Customer Service | F18: Compliance Advisory | G18: Distribution Company - Abuja Disco | H18: Low | I18: Under Review | K18: 495171.24
A19: LEG0018 | B19: 45884 | C19: EMP0020 | D19: =IFERROR(INDEX(Dim_Employee!$B$2:$B$76,MATCH(C19,Dim_Employee!$A$2:$A$76,0)),"") -> Aisha Danjuma | E19: Customer Service | F19: Land/Right-of-Way | G19: Community Association | H19: Medium | I19: Pending Court Date | K19: 3399110.7
A20: LEG0019 | B20: 45877 | C20: EMP0018 | D20: =IFERROR(INDEX(Dim_Employee!$B$2:$B$76,MATCH(C20,Dim_Employee!$A$2:$A$76,0)),"") -> Abdullahi Yakubu | E20: Supply Chain | F20: Contract Review | G20: Insurance Underwriter | H20: Low | I20: Closed | J20: 45949 | K20: 2754697.2
A21: LEG0020 | B21: 45936 | C21: EMP0018 | D21: =IFERROR(INDEX(Dim_Employee!$B$2:$B$76,MATCH(C21,Dim_Employee!$A$2:$A$76,0)),"") -> Abdullahi Yakubu | E21: Supply Chain | F21: Contract Review | G21: Distribution Company - Ikeja Disco | H21: Low | I21: Pending Court Date | K21: 2087608.1
A22: LEG0021 | B22: 45983 | C22: EMP0018 | D22: =IFERROR(INDEX(Dim_Employee!$B$2:$B$76,MATCH(C22,Dim_Employee!$A$2:$A$76,0)),"") -> Abdullahi Yakubu | E22: Supply Chain | F22: Litigation | G22: Community Association | H22: Medium | I22: Pending Court Date | K22: 1227469.6
A23: LEG0022 | B23: 45661 | C23: EMP0018 | D23: =IFERROR(INDEX(Dim_Employee!$B$2:$B$76,MATCH(C23,Dim_Employee!$A$2:$A$76,0)),"") -> Abdullahi Yakubu | E23: Supply Chain | F23: Regulatory Filing | G23: Local Vendor Ltd | H23: Low | I23: Under Review | K23: 3553190.9
A24: LEG0023 | B24: 45946 | C24: EMP0021 | D24: =IFERROR(INDEX(Dim_Employee!$B$2:$B$76,MATCH(C24,Dim_Employee!$A$2:$A$76,0)),"") -> Tunde Nnamdi | E24: Customer Service | F24: Contract Review | G24: Insurance Underwriter | H24: Medium | I24: Closed | J24: 45998 | K24: 4709023.5
A25: LEG0024 | B25: 45964 | C25: EMP0018 | D25: =IFERROR(INDEX(Dim_Employee!$B$2:$B$76,MATCH(C25,Dim_Employee!$A$2:$A$76,0)),"") -> Abdullahi Yakubu | E25: Accounts and Finance | F25: Litigation | G25: NBET | H25: Medium | I25: Under Review | K25: 111237.96
A26: LEG0025 | B26: 45763 | C26: EMP0020 | D26: =IFERROR(INDEX(Dim_Employee!$B$2:$B$76,MATCH(C26,Dim_Employee!$A$2:$A$76,0)),"") -> Aisha Danjuma | E26: Operations | F26: Regulatory Filing | G26: Local Vendor Ltd | H26: Low | I26: Open | K26: 3523038
A27: LEG0026 | B27: 45715 | C27: EMP0020 | D27: =IFERROR(INDEX(Dim_Employee!$B$2:$B$76,MATCH(C27,Dim_Employee!$A$2:$A$76,0)),"") -> Aisha Danjuma | E27: Accounts and Finance | F27: Compliance Advisory | G27: NERC | H27: Low | I27: Closed | J27: 45766 | K27: 2809781.7
A28: LEG0027 | B28: 45663 | C28: EMP0017 | D28: =IFERROR(INDEX(Dim_Employee!$B$2:$B$76,MATCH(C28,Dim_Employee!$A$2:$A$76,0)),"") -> Titilayo Abubakar | E28: Accounts and Finance | F28: Contract Review | G28: NERC | H28: High | I28: Under Review | K28: 2840084.3
A29: LEG0028 | B29: 45988 | C29: EMP0017 | D29: =IFERROR(INDEX(Dim_Employee!$B$2:$B$76,MATCH(C29,Dim_Employee!$A$2:$A$76,0)),"") -> Titilayo Abubakar | E29: Accounts and Finance | F29: Compliance Advisory | G29: Distribution Company - Abuja Disco | H29: Medium | I29: Under Review | K29: 1642974.5
A30: LEG0029 | B30: 45704 | C30: EMP0019 | D30: =IFERROR(INDEX(Dim_Employee!$B$2:$B$76,MATCH(C30,Dim_Employee!$A$2:$A$76,0)),"") -> Yusuf Sani | E30: Customer Service | F30: Land/Right-of-Way | G30: Local Vendor Ltd | H30: Medium | I30: Pending Court Date | K30: 436816.78
A31: LEG0030 | B31: 45670 | C31: EMP0017 | D31: =IFERROR(INDEX(Dim_Employee!$B$2:$B$76,MATCH(C31,Dim_Employee!$A$2:$A$76,0)),"") -> Titilayo Abubakar | E31: Supply Chain | F31: Regulatory Filing | G31: NERC | H31: Low | I31: Under Review | K31: 3208599.4
A32: LEG0031 | B32: 45710 | C32: EMP0018 | D32: =IFERROR(INDEX(Dim_Employee!$B$2:$B$76,MATCH(C32,Dim_Employee!$A$2:$A$76,0)),"") -> Abdullahi Yakubu | E32: Customer Service | F32: Land/Right-of-Way | G32: NERC | H32: Low | I32: Pending Court Date | K32: 3254159.9
A33: LEG0032 | B33: 45821 | C33: EMP0019 | D33: =IFERROR(INDEX(Dim_Employee!$B$2:$B$76,MATCH(C33,Dim_Employee!$A$2:$A$76,0)),"") -> Yusuf Sani | E33: Supply Chain | F33: Land/Right-of-Way | G33: NERC | H33: High | I33: Closed | J33: 45878 | K33: 1305072.2
A34: LEG0033 | B34: 45679 | C34: EMP0017 | D34: =IFERROR(INDEX(Dim_Employee!$B$2:$B$76,MATCH(C34,Dim_Employee!$A$2:$A$76,0)),"") -> Titilayo Abubakar | E34: Human Resources | F34: Compliance Advisory | G34: TCN | H34: High | I34: Open | K34: 2497180.2
A35: LEG0034 | B35: 45738 | C35: EMP0020 | D35: =IFERROR(INDEX(Dim_Employee!$B$2:$B$76,MATCH(C35,Dim_Employee!$A$2:$A$76,0)),"") -> Aisha Danjuma | E35: Human Resources | F35: Land/Right-of-Way | G35: NBET | H35: Low | I35: Pending Court Date | K35: 1176121.4
A36: LEG0035 | B36: 45884 | C36: EMP0018 | D36: =IFERROR(INDEX(Dim_Employee!$B$2:$B$76,MATCH(C36,Dim_Employee!$A$2:$A$76,0)),"") -> Abdullahi Yakubu | E36: Operations | F36: Contract Review | G36: Community Association | H36: Medium | I36: Under Review | K36: 1130462.6
A37: LEG0036 | B37: 45659 | C37: EMP0019 | D37: =IFERROR(INDEX(Dim_Employee!$B$2:$B$76,MATCH(C37,Dim_Employee!$A$2:$A$76,0)),"") -> Yusuf Sani | E37: Human Resources | F37: Land/Right-of-Way | G37: State Government - Kogi | H37: Low | I37: Open | K37: 406371.35
A38: LEG0037 | B38: 45921 | C38: EMP0017 | D38: =IFERROR(INDEX(Dim_Employee!$B$2:$B$76,MATCH(C38,Dim_Employee!$A$2:$A$76,0)),"") -> Titilayo Abubakar | E38: Admin | F38: Contract Review | G38: Community Association | H38: Low | I38: Under Review | K38: 4782239.7
A39: LEG0038 | B39: 45742 | C39: EMP0018 | D39: =IFERROR(INDEX(Dim_Employee!$B$2:$B$76,MATCH(C39,Dim_Employee!$A$2:$A$76,0)),"") -> Abdullahi Yakubu | E39: Admin | F39: Contract Review | G39: Community Association | H39: High | I39: Under Review | K39: 3392544.3
A40: LEG0039 | B40: 45758 | C40: EMP0021 | D40: =IFERROR(INDEX(Dim_Employee!$B$2:$B$76,MATCH(C40,Dim_Employee!$A$2:$A$76,0)),"") -> Tunde Nnamdi | E40: Operations | F40: Land/Right-of-Way | G40: NERC | H40: Medium | I40: Under Review | K40: 2170456.5
A41: LEG0040 | B41: 45978 | C41: EMP0021 | D41: =IFERROR(INDEX(Dim_Employee!$B$2:$B$76,MATCH(C41,Dim_Employee!$A$2:$A$76,0)),"") -> Tunde Nnamdi | E41: Human Resources | F41: Land/Right-of-Way | G41: NBET | H41: High | I41: Closed | J41: 46039 | K41: 347041.82
A42: LEG0041 | B42: 45969 | C42: EMP0019 | D42: =IFERROR(INDEX(Dim_Employee!$B$2:$B$76,MATCH(C42,Dim_Employee!$A$2:$A$76,0)),"") -> Yusuf Sani | E42: Human Resources | F42: Land/Right-of-Way | G42: State Government - Kogi | H42: High | I42: Pending Court Date | K42: 2429624.6
A43: LEG0042 | B43: 45811 | C43: EMP0018 | D43: =IFERROR(INDEX(Dim_Employee!$B$2:$B$76,MATCH(C43,Dim_Employee!$A$2:$A$76,0)),"") -> Abdullahi Yakubu | E43: Human Resources | F43: Contract Review | G43: Distribution Company - Abuja Disco | H43: Low | I43: Pending Court Date | K43: 3711595.6
A44: LEG0043 | B44: 45733 | C44: EMP0017 | D44: =IFERROR(INDEX(Dim_Employee!$B$2:$B$76,MATCH(C44,Dim_Employee!$A$2:$A$76,0)),"") -> Titilayo Abubakar | E44: Human Resources | F44: Land/Right-of-Way | G44: State Government - Kogi | H44: Low | I44: Pending Court Date | K44: 1239179.9
A45: LEG0044 | B45: 45860 | C45: EMP0020 | D45: =IFERROR(INDEX(Dim_Employee!$B$2:$B$76,MATCH(C45,Dim_Employee!$A$2:$A$76,0)),"") -> Aisha Danjuma | E45: Operations | F45: Litigation | G45: Distribution Company - Ikeja Disco | H45: High | I45: Pending Court Date | K45: 1053960.8
A46: LEG0045 | B46: 45771 | C46: EMP0017 | D46: =IFERROR(INDEX(Dim_Employee!$B$2:$B$76,MATCH(C46,Dim_Employee!$A$2:$A$76,0)),"") -> Titilayo Abubakar | E46: Customer Service | F46: Contract Review | G46: Distribution Company - Abuja Disco | H46: Medium | I46: Pending Court Date | K46: 1295133.7
A47: LEG0046 | B47: 45774 | C47: EMP0020 | D47: =IFERROR(INDEX(Dim_Employee!$B$2:$B$76,MATCH(C47,Dim_Employee!$A$2:$A$76,0)),"") -> Aisha Danjuma | E47: Supply Chain | F47: Land/Right-of-Way | G47: NBET | H47: Medium | I47: Under Review | K47: 4550803
A48: LEG0047 | B48: 45699 | C48: EMP0021 | D48: =IFERROR(INDEX(Dim_Employee!$B$2:$B$76,MATCH(C48,Dim_Employee!$A$2:$A$76,0)),"") -> Tunde Nnamdi | E48: Customer Service | F48: Contract Review | G48: Community Association | H48: Low | I48: Under Review | K48: 2540496.4
A49: LEG0048 | B49: 45716 | C49: EMP0021 | D49: =IFERROR(INDEX(Dim_Employee!$B$2:$B$76,MATCH(C49,Dim_Employee!$A$2:$A$76,0)),"") -> Tunde Nnamdi | E49: Accounts and Finance | F49: Compliance Advisory | G49: Insurance Underwriter | H49: Low | I49: Open | K49: 4802164.8
A50: LEG0049 | B50: 45901 | C50: EMP0021 | D50: =IFERROR(INDEX(Dim_Employee!$B$2:$B$76,MATCH(C50,Dim_Employee!$A$2:$A$76,0)),"") -> Tunde Nnamdi | E50: Supply Chain | F50: Regulatory Filing | G50: TCN | H50: Medium | I50: Open | K50: 283749.37
A51: LEG0050 | B51: 45665 | C51: EMP0017 | D51: =IFERROR(INDEX(Dim_Employee!$B$2:$B$76,MATCH(C51,Dim_Employee!$A$2:$A$76,0)),"") -> Titilayo Abubakar | E51: Admin | F51: Contract Review | G51: Distribution Company - Ikeja Disco | H51: Medium | I51: Closed | J51: 45733 | K51: 4448705.8
A52: LEG0051 | B52: 45761 | C52: EMP0021 | D52: =IFERROR(INDEX(Dim_Employee!$B$2:$B$76,MATCH(C52,Dim_Employee!$A$2:$A$76,0)),"") -> Tunde Nnamdi | E52: Customer Service | F52: Regulatory Filing | G52: Distribution Company - Ikeja Disco | H52: Low | I52: Open | K52: 4215296.4
A53: LEG0052 | B53: 45788 | C53: EMP0017 | D53: =IFERROR(INDEX(Dim_Employee!$B$2:$B$76,MATCH(C53,Dim_Employee!$A$2:$A$76,0)),"") -> Titilayo Abubakar | E53: Supply Chain | F53: Regulatory Filing | G53: Insurance Underwriter | H53: Medium | I53: Open | K53: 4742747.6
A54: LEG0053 | B54: 45680 | C54: EMP0020 | D54: =IFERROR(INDEX(Dim_Employee!$B$2:$B$76,MATCH(C54,Dim_Employee!$A$2:$A$76,0)),"") -> Aisha Danjuma | E54: Operations | F54: Regulatory Filing | G54: Insurance Underwriter | H54: Low | I54: Pending Court Date | K54: 3035107.6
A55: LEG0054 | B55: 46003 | C55: EMP0017 | D55: =IFERROR(INDEX(Dim_Employee!$B$2:$B$76,MATCH(C55,Dim_Employee!$A$2:$A$76,0)),"") -> Titilayo Abubakar | E55: Admin | F55: Litigation | G55: Community Association | H55: Low | I55: Closed | J55: 46045 | K55: 4944221.7
A56: LEG0055 | B56: 45716 | C56: EMP0020 | D56: =IFERROR(INDEX(Dim_Employee!$B$2:$B$76,MATCH(C56,Dim_Employee!$A$2:$A$76,0)),"") -> Aisha Danjuma | E56: Accounts and Finance | F56: Contract Review | G56: NBET | H56: High | I56: Open | K56: 967080.55
A57: LEG0056 | B57: 45806 | C57: EMP0021 | D57: =IFERROR(INDEX(Dim_Employee!$B$2:$B$76,MATCH(C57,Dim_Employee!$A$2:$A$76,0)),"") -> Tunde Nnamdi | E57: Supply Chain | F57: Land/Right-of-Way | G57: Local Vendor Ltd | H57: Medium | I57: Under Review | K57: 3463123.2
A58: LEG0057 | B58: 45885 | C58: EMP0019 | D58: =IFERROR(INDEX(Dim_Employee!$B$2:$B$76,MATCH(C58,Dim_Employee!$A$2:$A$76,0)),"") -> Yusuf Sani | E58: Operations | F58: Regulatory Filing | G58: Distribution Company - Ikeja Disco | H58: Medium | I58: Open | K58: 2445648.8
A59: LEG0058 | B59: 45676 | C59: EMP0017 | D59: =IFERROR(INDEX(Dim_Employee!$B$2:$B$76,MATCH(C59,Dim_Employee!$A$2:$A$76,0)),"") -> Titilayo Abubakar | E59: Supply Chain | F59: Land/Right-of-Way | G59: State Government - Kogi | H59: High | I59: Open | K59: 4839270.3
A60: LEG0059 | B60: 45859 | C60: EMP0020 | D60: =IFERROR(INDEX(Dim_Employee!$B$2:$B$76,MATCH(C60,Dim_Employee!$A$2:$A$76,0)),"") -> Aisha Danjuma | E60: Human Resources | F60: Contract Review | G60: NERC | H60: Low | I60: Closed | J60: 45947 | K60: 1120756.1
A61: LEG0060 | B61: 45959 | C61: EMP0018 | D61: =IFERROR(INDEX(Dim_Employee!$B$2:$B$76,MATCH(C61,Dim_Employee!$A$2:$A$76,0)),"") -> Abdullahi Yakubu | E61: Supply Chain | F61: Litigation | G61: NERC | H61: Medium | I61: Open | K61: 1690277.5
A62: LEG0061 | B62: 45856 | C62: EMP0020 | D62: =IFERROR(INDEX(Dim_Employee!$B$2:$B$76,MATCH(C62,Dim_Employee!$A$2:$A$76,0)),"") -> Aisha Danjuma | E62: Admin | F62: Contract Review | G62: NERC | H62: Medium | I62: Pending Court Date | K62: 1702208.2
A63: LEG0062 | B63: 45785 | C63: EMP0017 | D63: =IFERROR(INDEX(Dim_Employee!$B$2:$B$76,MATCH(C63,Dim_Employee!$A$2:$A$76,0)),"") -> Titilayo Abubakar | E63: Human Resources | F63: Contract Review | G63: Distribution Company - Ikeja Disco | H63: Medium | I63: Under Review | K63: 761072.43
A64: LEG0063 | B64: 45797 | C64: EMP0020 | D64: =IFERROR(INDEX(Dim_Employee!$B$2:$B$76,MATCH(C64,Dim_Employee!$A$2:$A$76,0)),"") -> Aisha Danjuma | E64: Human Resources | F64: Regulatory Filing | G64: NERC | H64: Medium | I64: Open | K64: 2664335.1
A65: LEG0064 | B65: 46015 | C65: EMP0018 | D65: =IFERROR(INDEX(Dim_Employee!$B$2:$B$76,MATCH(C65,Dim_Employee!$A$2:$A$76,0)),"") -> Abdullahi Yakubu | E65: Human Resources | F65: Contract Review | G65: Distribution Company - Abuja Disco | H65: Medium | I65: Open | K65: 3183854
A66: LEG0065 | B66: 45843 | C66: EMP0017 | D66: =IFERROR(INDEX(Dim_Employee!$B$2:$B$76,MATCH(C66,Dim_Employee!$A$2:$A$76,0)),"") -> Titilayo Abubakar | E66: Supply Chain | F66: Litigation | G66: NBET | H66: Low | I66: Pending Court Date | K66: 3828494.1
A67: LEG0066 | B67: 45918 | C67: EMP0019 | D67: =IFERROR(INDEX(Dim_Employee!$B$2:$B$76,MATCH(C67,Dim_Employee!$A$2:$A$76,0)),"") -> Yusuf Sani | E67: Human Resources | F67: Compliance Advisory | G67: NERC | H67: Low | I67: Closed | J67: 45972 | K67: 1719220.8
A68: LEG0067 | B68: 45904 | C68: EMP0019 | D68: =IFERROR(INDEX(Dim_Employee!$B$2:$B$76,MATCH(C68,Dim_Employee!$A$2:$A$76,0)),"") -> Yusuf Sani | E68: Supply Chain | F68: Litigation | G68: NERC | H68: Low | I68: Pending Court Date | K68: 1066542.4
A69: LEG0068 | B69: 45865 | C69: EMP0020 | D69: =IFERROR(INDEX(Dim_Employee!$B$2:$B$76,MATCH(C69,Dim_Employee!$A$2:$A$76,0)),"") -> Aisha Danjuma | E69: Accounts and Finance | F69: Land/Right-of-Way | G69: Local Vendor Ltd | H69: High | I69: Under Review | K69: 2954624.7
A70: LEG0069 | B70: 45812 | C70: EMP0018 | D70: =IFERROR(INDEX(Dim_Employee!$B$2:$B$76,MATCH(C70,Dim_Employee!$A$2:$A$76,0)),"") -> Abdullahi Yakubu | E70: Admin | F70: Land/Right-of-Way | G70: Insurance Underwriter | H70: Medium | I70: Pending Court Date | K70: 4830797.5
A71: LEG0070 | B71: 45755 | C71: EMP0017 | D71: =IFERROR(INDEX(Dim_Employee!$B$2:$B$76,MATCH(C71,Dim_Employee!$A$2:$A$76,0)),"") -> Titilayo Abubakar | E71: Human Resources | F71: Litigation | G71: Local Vendor Ltd | H71: Medium | I71: Open | K71: 4937938.1
A72: LEG0071 | B72: 46011 | C72: EMP0019 | D72: =IFERROR(INDEX(Dim_Employee!$B$2:$B$76,MATCH(C72,Dim_Employee!$A$2:$A$76,0)),"") -> Yusuf Sani | E72: Customer Service | F72: Contract Review | G72: Community Association | H72: Low | I72: Under Review | K72: 917403.47
A73: LEG0072 | B73: 45937 | C73: EMP0019 | D73: =IFERROR(INDEX(Dim_Employee!$B$2:$B$76,MATCH(C73,Dim_Employee!$A$2:$A$76,0)),"") -> Yusuf Sani | E73: Supply Chain | F73: Regulatory Filing | G73: Distribution Company - Abuja Disco | H73: Medium | I73: Open | K73: 1130655.5
A74: LEG0073 | B74: 45887 | C74: EMP0020 | D74: =IFERROR(INDEX(Dim_Employee!$B$2:$B$76,MATCH(C74,Dim_Employee!$A$2:$A$76,0)),"") -> Aisha Danjuma | E74: Admin | F74: Land/Right-of-Way | G74: NBET | H74: Low | I74: Closed | J74: 45974 | K74: 3682752.3
A75: LEG0074 | B75: 45965 | C75: EMP0018 | D75: =IFERROR(INDEX(Dim_Employee!$B$2:$B$76,MATCH(C75,Dim_Employee!$A$2:$A$76,0)),"") -> Abdullahi Yakubu | E75: Operations | F75: Contract Review | G75: NERC | H75: Medium | I75: Open | K75: 74997.93
A76: LEG0075 | B76: 45932 | C76: EMP0019 | D76: =IFERROR(INDEX(Dim_Employee!$B$2:$B$76,MATCH(C76,Dim_Employee!$A$2:$A$76,0)),"") -> Yusuf Sani | E76: Customer Service | F76: Regulatory Filing | G76: TCN | H76: Low | I76: Open | K76: 1667413.2
A77: LEG0076 | B77: 45990 | C77: EMP0017 | D77: =IFERROR(INDEX(Dim_Employee!$B$2:$B$76,MATCH(C77,Dim_Employee!$A$2:$A$76,0)),"") -> Titilayo Abubakar | E77: Accounts and Finance | F77: Land/Right-of-Way | G77: NERC | H77: Low | I77: Under Review | K77: 4323359.3
A78: LEG0077 | B78: 45702 | C78: EMP0017 | D78: =IFERROR(INDEX(Dim_Employee!$B$2:$B$76,MATCH(C78,Dim_Employee!$A$2:$A$76,0)),"") -> Titilayo Abubakar | E78: Accounts and Finance | F78: Land/Right-of-Way | G78: State Government - Kogi | H78: Low | I78: Pending Court Date | K78: 2343721.6
A79: LEG0078 | B79: 45671 | C79: EMP0017 | D79: =IFERROR(INDEX(Dim_Employee!$B$2:$B$76,MATCH(C79,Dim_Employee!$A$2:$A$76,0)),"") -> Titilayo Abubakar | E79: Human Resources | F79: Regulatory Filing | G79: TCN | H79: Medium | I79: Pending Court Date | K79: 3565212.4
A80: LEG0079 | B80: 45738 | C80: EMP0019 | D80: =IFERROR(INDEX(Dim_Employee!$B$2:$B$76,MATCH(C80,Dim_Employee!$A$2:$A$76,0)),"") -> Yusuf Sani | E80: Operations | F80: Litigation | G80: Distribution Company - Abuja Disco | H80: Low | I80: Open | K80: 3847582
A81: LEG0080 | B81: 45841 | C81: EMP0017 | D81: =IFERROR(INDEX(Dim_Employee!$B$2:$B$76,MATCH(C81,Dim_Employee!$A$2:$A$76,0)),"") -> Titilayo Abubakar | E81: Accounts and Finance | F81: Regulatory Filing | G81: Insurance Underwriter | H81: Medium | I81: Pending Court Date | K81: 4336140
A82: LEG0081 | B82: 45994 | C82: EMP0018 | D82: =IFERROR(INDEX(Dim_Employee!$B$2:$B$76,MATCH(C82,Dim_Employee!$A$2:$A$76,0)),"") -> Abdullahi Yakubu | E82: Supply Chain | F82: Land/Right-of-Way | G82: Local Vendor Ltd | H82: High | I82: Pending Court Date | K82: 2413926.9
A83: LEG0082 | B83: 45989 | C83: EMP0017 | D83: =IFERROR(INDEX(Dim_Employee!$B$2:$B$76,MATCH(C83,Dim_Employee!$A$2:$A$76,0)),"") -> Titilayo Abubakar | E83: Customer Service | F83: Land/Right-of-Way | G83: Community Association | H83: Medium | I83: Pending Court Date | K83: 1838706.7
A84: LEG0083 | B84: 45798 | C84: EMP0021 | D84: =IFERROR(INDEX(Dim_Employee!$B$2:$B$76,MATCH(C84,Dim_Employee!$A$2:$A$76,0)),"") -> Tunde Nnamdi | E84: Operations | F84: Land/Right-of-Way | G84: Community Association | H84: Low | I84: Closed | J84: 45840 | K84: 4055526.2
A85: LEG0084 | B85: 45735 | C85: EMP0019 | D85: =IFERROR(INDEX(Dim_Employee!$B$2:$B$76,MATCH(C85,Dim_Employee!$A$2:$A$76,0)),"") -> Yusuf Sani | E85: Operations | F85: Contract Review | G85: Distribution Company - Ikeja Disco | H85: Low | I85: Closed | J85: 45796 | K85: 2739194.4
A86: LEG0085 | B86: 45942 | C86: EMP0018 | D86: =IFERROR(INDEX(Dim_Employee!$B$2:$B$76,MATCH(C86,Dim_Employee!$A$2:$A$76,0)),"") -> Abdullahi Yakubu | E86: Human Resources | F86: Regulatory Filing | G86: Distribution Company - Ikeja Disco | H86: High | I86: Closed | J86: 45985 | K86: 4360634.4
A87: LEG0086 | B87: 45928 | C87: EMP0018 | D87: =IFERROR(INDEX(Dim_Employee!$B$2:$B$76,MATCH(C87,Dim_Employee!$A$2:$A$76,0)),"") -> Abdullahi Yakubu | E87: Admin | F87: Litigation | G87: Community Association | H87: High | I87: Open | K87: 2519740.2
A88: LEG0087 | B88: 45857 | C88: EMP0019 | D88: =IFERROR(INDEX(Dim_Employee!$B$2:$B$76,MATCH(C88,Dim_Employee!$A$2:$A$76,0)),"") -> Yusuf Sani | E88: Supply Chain | F88: Regulatory Filing | G88: TCN | H88: Low | I88: Under Review | K88: 3680258.9
A89: LEG0088 | B89: 45988 | C89: EMP0017 | D89: =IFERROR(INDEX(Dim_Employee!$B$2:$B$76,MATCH(C89,Dim_Employee!$A$2:$A$76,0)),"") -> Titilayo Abubakar | E89: Customer Service | F89: Regulatory Filing | G89: TCN | H89: Low | I89: Under Review | K89: 1911160.1
A90: LEG0089 | B90: 45994 | C90: EMP0020 | D90: =IFERROR(INDEX(Dim_Employee!$B$2:$B$76,MATCH(C90,Dim_Employee!$A$2:$A$76,0)),"") -> Aisha Danjuma | E90: Admin | F90: Contract Review | G90: Local Vendor Ltd | H90: Medium | I90: Closed | J90: 46007 | K90: 1247054.4
A91: LEG0090 | B91: 45762 | C91: EMP0019 | D91: =IFERROR(INDEX(Dim_Employee!$B$2:$B$76,MATCH(C91,Dim_Employee!$A$2:$A$76,0)),"") -> Yusuf Sani | E91: Accounts and Finance | F91: Regulatory Filing | G91: Local Vendor Ltd | H91: High | I91: Pending Court Date | K91: 2518076.8

Sheet Supply_Chain
A1: PO_ID | B1: Date | C1: Employee_ID | D1: Employee_Name | E1: Vendor_Name | F1: Item_Category | G1: Item_Description | H1: Quantity | I1: Unit_Cost_NGN | J1: Total_Cost_NGN | K1: Lead_Time_Days | L1: Delivery_Status | M1: Approval_Status
A2: PO00001 | B2: 45727 | C2: EMP0024 | D2: =IFERROR(INDEX(Dim_Employee!$B$2:$B$76,MATCH(C2,Dim_Employee!$A$2:$A$76,0)),"") -> Titilayo Okafor | E2: Total Energies Nigeria | F2: Safety Equipment | G2: PPE Kits | H2: 197 | I2: 228283.84 | J2: =H2*I2 -> 44971916 | K2: 7 | L2: Pending Dispatch | M2: Approved
A3: PO00002 | B3: 45970 | C3: EMP0029 | D3: =IFERROR(INDEX(Dim_Employee!$B$2:$B$76,MATCH(C3,Dim_Employee!$A$2:$A$76,0)),"") -> Amaka Usman | E3: Cummins West Africa | F3: Fuel | G3: Natural Gas Supply Top-up | H3: 42 | I3: 272823.31 | J3: =H3*I3 -> 11458579 | K3: 39 | L3: Delivered | M3: Approved
A4: PO00003 | B4: 45882 | C4: EMP0027 | D4: =IFERROR(INDEX(Dim_Employee!$B$2:$B$76,MATCH(C4,Dim_Employee!$A$2:$A$76,0)),"") -> Adaeze Onyeka | E4: GE Power Services | F4: Spare Parts | G4: Control Valve | H4: 200 | I4: 658188.28 | J4: =H4*I4 -> 131637656 | K4: 57 | L4: In Transit | M4: Pending Approval
A5: PO00004 | B5: 45662 | C5: EMP0022 | D5: =IFERROR(INDEX(Dim_Employee!$B$2:$B$76,MATCH(C5,Dim_Employee!$A$2:$A$76,0)),"") -> Zainab Igwe | E5: GE Power Services | F5: Spare Parts | G5: Bearing Assembly | H5: 39 | I5: 828224.47 | J5: =H5*I5 -> 32300754 | K5: 11 | L5: Pending Dispatch | M5: Approved
A6: PO00005 | B6: 45870 | C6: EMP0024 | D6: =IFERROR(INDEX(Dim_Employee!$B$2:$B$76,MATCH(C6,Dim_Employee!$A$2:$A$76,0)),"") -> Titilayo Okafor | E6: Safety First Equipment Ltd | F6: Safety Equipment | G6: Gas Detectors | H6: 175 | I6: 338502.11 | J6: =H6*I6 -> 59237869 | K6: 60 | L6: Delayed | M6: Pending Approval
A7: PO00006 | B7: 45979 | C7: EMP0022 | D7: =IFERROR(INDEX(Dim_Employee!$B$2:$B$76,MATCH(C7,Dim_Employee!$A$2:$A$76,0)),"") -> Zainab Igwe | E7: Dantata Engineering Ltd | F7: IT Hardware | G7: Network Switch | H7: 61 | I7: 172369.21 | J7: =H7*I7 -> 10514522 | K7: 10 | L7: In Transit | M7: Rejected
A8: PO00007 | B8: 45682 | C8: EMP0028 | D8: =IFERROR(INDEX(Dim_Employee!$B$2:$B$76,MATCH(C8,Dim_Employee!$A$2:$A$76,0)),"") -> Blessing Balogun | E8: Safety First Equipment Ltd | F8: Office Supplies | G8: Stationery Bundle | H8: 27 | I8: 619635.93 | J8: =H8*I8 -> 16730170 | K8: 58 | L8: Delivered | M8: Approved
A9: PO00008 | B9: 45749 | C9: EMP0029 | D9: =IFERROR(INDEX(Dim_Employee!$B$2:$B$76,MATCH(C9,Dim_Employee!$A$2:$A$76,0)),"") -> Amaka Usman | E9: SPX Nigeria | F9: Fuel | G9: Natural Gas Supply Top-up | H9: 135 | I9: 365060.85 | J9: =H9*I9 -> 49283215 | K9: 42 | L9: Delivered | M9: Rejected
A10: PO00009 | B10: 45768 | C10: EMP0027 | D10: =IFERROR(INDEX(Dim_Employee!$B$2:$B$76,MATCH(C10,Dim_Employee!$A$2:$A$76,0)),"") -> Adaeze Onyeka | E10: SPX Nigeria | F10: Safety Equipment | G10: Gas Detectors | H10: 20 | I10: 298001.19 | J10: =H10*I10 -> 5960023.8 | K10: 6 | L10: Pending Dispatch | M10: Rejected
A11: PO00010 | B11: 45680 | C11: EMP0024 | D11: =IFERROR(INDEX(Dim_Employee!$B$2:$B$76,MATCH(C11,Dim_Employee!$A$2:$A$76,0)),"") -> Titilayo Okafor | E11: SPX Nigeria | F11: Spare Parts | G11: Turbine Blade Set | H11: 68 | I11: 229749.74 | J11: =H11*I11 -> 15622982 | K11: 28 | L11: Pending Dispatch | M11: Pending Approval
A12: PO00011 | B12: 45890 | C12: EMP0022 | D12: =IFERROR(INDEX(Dim_Employee!$B$2:$B$76,MATCH(C12,Dim_Employee!$A$2:$A$76,0)),"") -> Zainab Igwe | E12: Total Energies Nigeria | F12: Consumables | G12: Welding Consumables | H12: 177 | I12: 36634.48 | J12: =H12*I12 -> 6484303 | K12: 23 | L12: Delayed | M12: Rejected
A13: PO00012 | B13: 45872 | C13: EMP0026 | D13: =IFERROR(INDEX(Dim_Employee!$B$2:$B$76,MATCH(C13,Dim_Employee!$A$2:$A$76,0)),"") -> Ibrahim Abubakar | E13: OilServ Ltd | F13: Safety Equipment | G13: Fire Suppression Cylinder | H13: 109 | I13: 271548.08 | J13: =H13*I13 -> 29598741 | K13: 26 | L13: Delayed | M13: Pending Approval
... A151: PO00150 | B151: 45700 | C151: EMP0024 | D151: =IFERROR(INDEX(Dim_Employee!$B$2:$B$76,MATCH(C151,Dim_Employee!$A$2:$A$76,0)),"") -> Titilayo Okafor | E151: Cummins West Africa | F151: IT Hardware | G151: SCADA Workstation | H151: 81 | I151: 181708.24 | J151: =H151*I151 -> 14718367 | K151: 31 | L151: Delayed | M151: Rejected

Sheet Admin
A1: Request_ID | B1: Date | C1: Employee_ID | D1: Employee_Name | E1: Request_Type | F1: Asset_Tag | G1: Location | H1: Priority | I1: Status | J1: Cost_NGN | K1: Closure_Date
A2: ADM0001 | B2: 45944 | C2: EMP0033 | D2: =IFERROR(INDEX(Dim_Employee!$B$2:$B$76,MATCH(C2,Dim_Employee!$A$2:$A$76,0)),"") -> Ngozi Balogun | E2: Fleet/Vehicle | F2: AST-9320 | G2: Head Office - Abuja | H2: Medium | I2: Cancelled | J2: 965660.87
A3: ADM0002 | B3: 45980 | C3: EMP0033 | D3: =IFERROR(INDEX(Dim_Employee!$B$2:$B$76,MATCH(C3,Dim_Employee!$A$2:$A$76,0)),"") -> Ngozi Balogun | E3: Facility Maintenance | F3: AST-8316 | G3: Guest House - Kogi | H3: Medium | I3: In Progress | J3: 113351.29
A4: ADM0003 | B4: 45982 | C4: EMP0035 | D4: =IFERROR(INDEX(Dim_Employee!$B$2:$B$76,MATCH(C4,Dim_Employee!$A$2:$A$76,0)),"") -> Ifeoma Balogun | E4: Fleet/Vehicle | F4: AST-8421 | G4: Head Office - Abuja | H4: Low | I4: Completed | J4: 998883.44 | K4: 46002
A5: ADM0004 | B5: 45688 | C5: EMP0030 | D5: =IFERROR(INDEX(Dim_Employee!$B$2:$B$76,MATCH(C5,Dim_Employee!$A$2:$A$76,0)),"") -> Yusuf Abubakar | E5: Asset Request | F5: AST-1492 | G5: Lagos Liaison Office | H5: High | I5: Completed | J5: 531434.68 | K5: 45695
A6: ADM0005 | B6: 45923 | C6: EMP0031 | D6: =IFERROR(INDEX(Dim_Employee!$B$2:$B$76,MATCH(C6,Dim_Employee!$A$2:$A$76,0)),"") -> Emmanuel Aliyu | E6: Office Supplies | F6: AST-5819 | G6: Lagos Liaison Office | H6: Low | I6: In Progress | J6: 796627.19
A7: ADM0006 | B7: 45993 | C7: EMP0033 | D7: =IFERROR(INDEX(Dim_Employee!$B$2:$B$76,MATCH(C7,Dim_Employee!$A$2:$A$76,0)),"") -> Ngozi Balogun | E7: Fleet/Vehicle | F7: AST-2363 | G7: Guest House - Kogi | H7: High | I7: Pending | J7: 910798.11
A8: ADM0007 | B8: 45805 | C8: EMP0034 | D8: =IFERROR(INDEX(Dim_Employee!$B$2:$B$76,MATCH(C8,Dim_Employee!$A$2:$A$76,0)),"") -> Peace Balogun | E8: Utility Payment | F8: AST-2768 | G8: Lagos Liaison Office | H8: Low | I8: Completed | J8: 1016667.4 | K8: 45808
A9: ADM0008 | B9: 45692 | C9: EMP0033 | D9: =IFERROR(INDEX(Dim_Employee!$B$2:$B$76,MATCH(C9,Dim_Employee!$A$2:$A$76,0)),"") -> Ngozi Balogun | E9: Office Supplies | F9: AST-1008 | G9: Head Office - Abuja | H9: Medium | I9: Completed | J9: 1112815.4 | K9: 45720
A10: ADM0009 | B10: 45898 | C10: EMP0030 | D10: =IFERROR(INDEX(Dim_Employee!$B$2:$B$76,MATCH(C10,Dim_Employee!$A$2:$A$76,0)),"") -> Yusuf Abubakar | E10: Office Supplies | F10: AST-7511 | G10: Lagos Liaison Office | H10: Low | I10: Cancelled | J10: 681658.89
A11: ADM0010 | B11: 46003 | C11: EMP0031 | D11: =IFERROR(INDEX(Dim_Employee!$B$2:$B$76,MATCH(C11,Dim_Employee!$A$2:$A$76,0)),"") -> Emmanuel Aliyu | E11: Travel Request | F11: AST-2427 | G11: Guest House - Kogi | H11: High | I11: Pending | J11: 23103.67
A12: ADM0011 | B12: 45718 | C12: EMP0033 | D12: =IFERROR(INDEX(Dim_Employee!$B$2:$B$76,MATCH(C12,Dim_Employee!$A$2:$A$76,0)),"") -> Ngozi Balogun | E12: Asset Request | F12: AST-2655 | G12: Kogi Plant Site | H12: Low | I12: In Progress | J12: 560603.12
A13: ADM0012 | B13: 45748 | C13: EMP0033 | D13: =IFERROR(INDEX(Dim_Employee!$B$2:$B$76,MATCH(C13,Dim_Employee!$A$2:$A$76,0)),"") -> Ngozi Balogun | E13: Fleet/Vehicle | F13: AST-9337 | G13: Head Office - Abuja | H13: Medium | I13: In Progress | J13: 505980.44
A14: ADM0013 | B14: 45717 | C14: EMP0033 | D14: =IFERROR(INDEX(Dim_Employee!$B$2:$B$76,MATCH(C14,Dim_Employee!$A$2:$A$76,0)),"") -> Ngozi Balogun | E14: Fleet/Vehicle | F14: AST-4487 | G14: Kogi Plant Site | H14: High | I14: Cancelled | J14: 1037879.1
A15: ADM0014 | B15: 45813 | C15: EMP0034 | D15: =IFERROR(INDEX(Dim_Employee!$B$2:$B$76,MATCH(C15,Dim_Employee!$A$2:$A$76,0)),"") -> Peace Balogun | E15: Asset Request | F15: AST-7459 | G15: Kogi Plant Site | H15: Low | I15: Completed | J15: 1187215.5 | K15: 45820
A16: ADM0015 | B16: 45884 | C16: EMP0031 | D16: =IFERROR(INDEX(Dim_Employee!$B$2:$B$76,MATCH(C16,Dim_Employee!$A$2:$A$76,0)),"") -> Emmanuel Aliyu | E16: Facility Maintenance | F16: AST-6389 | G16: Guest House - Kogi | H16: Urgent | I16: Pending | J16: 92711.27
A17: ADM0016 | B17: 45764 | C17: EMP0030 | D17: =IFERROR(INDEX(Dim_Employee!$B$2:$B$76,MATCH(C17,Dim_Employee!$A$2:$A$76,0)),"") -> Yusuf Abubakar | E17: Facility Maintenance | F17: AST-7040 | G17: Guest House - Kogi | H17: Urgent | I17: In Progress | J17: 157029.21
A18: ADM0017 | B18: 45905 | C18: EMP0034 | D18: =IFERROR(INDEX(Dim_Employee!$B$2:$B$76,MATCH(C18,Dim_Employee!$A$2:$A$76,0)),"") -> Peace Balogun | E18: Fleet/Vehicle | F18: AST-3995 | G18: Head Office - Abuja | H18: High | I18: In Progress | J18: 1090566.4
A19: ADM0018 | B19: 45785 | C19: EMP0034 | D19: =IFERROR(INDEX(Dim_Employee!$B$2:$B$76,MATCH(C19,Dim_Employee!$A$2:$A$76,0)),"") -> Peace Balogun | E19: Asset Request | F19: AST-4220 | G19: Lagos Liaison Office | H19: Urgent | I19: In Progress | J19: 726223.39
A20: ADM0019 | B20: 45682 | C20: EMP0033 | D20: =IFERROR(INDEX(Dim_Employee!$B$2:$B$76,MATCH(C20,Dim_Employee!$A$2:$A$76,0)),"") -> Ngozi Balogun | E20: Facility Maintenance | F20: AST-9394 | G20: Guest House - Kogi | H20: Medium | I20: Completed | J20: 889095.25 | K20: 45686
A21: ADM0020 | B21: 45789 | C21: EMP0033 | D21: =IFERROR(INDEX(Dim_Employee!$B$2:$B$76,MATCH(C21,Dim_Employee!$A$2:$A$76,0)),"") -> Ngozi Balogun | E21: Utility Payment | F21: AST-9044 | G21: Guest House - Kogi | H21: Medium | I21: Cancelled | J21: 1115437.2
A22: ADM0021 | B22: 45722 | C22: EMP0030 | D22: =IFERROR(INDEX(Dim_Employee!$B$2:$B$76,MATCH(C22,Dim_Employee!$A$2:$A$76,0)),"") -> Yusuf Abubakar | E22: Fleet/Vehicle | F22: AST-2214 | G22: Guest House - Kogi | H22: Medium | I22: In Progress | J22: 1101245.4
A23: ADM0022 | B23: 45666 | C23: EMP0031 | D23: =IFERROR(INDEX(Dim_Employee!$B$2:$B$76,MATCH(C23,Dim_Employee!$A$2:$A$76,0)),"") -> Emmanuel Aliyu | E23: Fleet/Vehicle | F23: AST-8302 | G23: Head Office - Abuja | H23: Low | I23: Completed | J23: 60684.77 | K23: 45675
A24: ADM0023 | B24: 45846 | C24: EMP0032 | D24: =IFERROR(INDEX(Dim_Employee!$B$2:$B$76,MATCH(C24,Dim_Employee!$A$2:$A$76,0)),"") -> Blessing Nnamdi | E24: Facility Maintenance | F24: AST-6933 | G24: Head Office - Abuja | H24: Urgent | I24: In Progress | J24: 1176689.6
A25: ADM0024 | B25: 46011 | C25: EMP0035 | D25: =IFERROR(INDEX(Dim_Employee!$B$2:$B$76,MATCH(C25,Dim_Employee!$A$2:$A$76,0)),"") -> Ifeoma Balogun | E25: Utility Payment | F25: AST-1574 | G25: Kogi Plant Site | H25: Urgent | I25: In Progress | J25: 1092703.9
A26: ADM0025 | B26: 45817 | C26: EMP0035 | D26: =IFERROR(INDEX(Dim_Employee!$B$2:$B$76,MATCH(C26,Dim_Employee!$A$2:$A$76,0)),"") -> Ifeoma Balogun | E26: Utility Payment | F26: AST-2226 | G26: Lagos Liaison Office | H26: Low | I26: Completed | J26: 877945.09 | K26: 45818
A27: ADM0026 | B27: 45727 | C27: EMP0032 | D27: =IFERROR(INDEX(Dim_Employee!$B$2:$B$76,MATCH(C27,Dim_Employee!$A$2:$A$76,0)),"") -> Blessing Nnamdi | E27: Fleet/Vehicle | F27: AST-9947 | G27: Guest House - Kogi | H27: Low | I27: Completed | J27: 1080734.1 | K27: 45730
A28: ADM0027 | B28: 46018 | C28: EMP0035 | D28: =IFERROR(INDEX(Dim_Employee!$B$2:$B$76,MATCH(C28,Dim_Employee!$A$2:$A$76,0)),"") -> Ifeoma Balogun | E28: Travel Request | F28: AST-6764 | G28: Kogi Plant Site | H28: Urgent | I28: In Progress | J28: 1081498.9
A29: ADM0028 | B29: 45673 | C29: EMP0033 | D29: =IFERROR(INDEX(Dim_Employee!$B$2:$B$76,MATCH(C29,Dim_Employee!$A$2:$A$76,0)),"") -> Ngozi Balogun | E29: Utility Payment | F29: AST-1238 | G29: Lagos Liaison Office | H29: Urgent | I29: Cancelled | J29: 701301.28
A30: ADM0029 | B30: 45694 | C30: EMP0034 | D30: =IFERROR(INDEX(Dim_Employee!$B$2:$B$76,MATCH(C30,Dim_Employee!$A$2:$A$76,0)),"") -> Peace Balogun | E30: Office Supplies | F30: AST-2893 | G30: Guest House - Kogi | H30: Urgent | I30: Completed | J30: 875207.46 | K30: 45697
A31: ADM0030 | B31: 46013 | C31: EMP0033 | D31: =IFERROR(INDEX(Dim_Employee!$B$2:$B$76,MATCH(C31,Dim_Employee!$A$2:$A$76,0)),"") -> Ngozi Balogun | E31: Fleet/Vehicle | F31: AST-8579 | G31: Kogi Plant Site | H31: Low | I31: Cancelled | J31: 375730.81
A32: ADM0031 | B32: 45904 | C32: EMP0030 | D32: =IFERROR(INDEX(Dim_Employee!$B$2:$B$76,MATCH(C32,Dim_Employee!$A$2:$A$76,0)),"") -> Yusuf Abubakar | E32: Office Supplies | F32: AST-2849 | G32: Lagos Liaison Office | H32: Urgent | I32: Completed | J32: 310717.11 | K32: 45912
A33: ADM0032 | B33: 45846 | C33: EMP0030 | D33: =IFERROR(INDEX(Dim_Employee!$B$2:$B$76,MATCH(C33,Dim_Employee!$A$2:$A$76,0)),"") -> Yusuf Abubakar | E33: Asset Request | F33: AST-4318 | G33: Head Office - Abuja | H33: High | I33: Pending | J33: 793688.06
A34: ADM0033 | B34: 45913 | C34: EMP0033 | D34: =IFERROR(INDEX(Dim_Employee!$B$2:$B$76,MATCH(C34,Dim_Employee!$A$2:$A$76,0)),"") -> Ngozi Balogun | E34: Travel Request | F34: AST-7631 | G34: Guest House - Kogi | H34: Medium | I34: In Progress | J34: 762836.89
A35: ADM0034 | B35: 45767 | C35: EMP0031 | D35: =IFERROR(INDEX(Dim_Employee!$B$2:$B$76,MATCH(C35,Dim_Employee!$A$2:$A$76,0)),"") -> Emmanuel Aliyu | E35: Asset Request | F35: AST-6185 | G35: Head Office - Abuja | H35: Medium | I35: Cancelled | J35: 165790.52
A36: ADM0035 | B36: 45678 | C36: EMP0032 | D36: =IFERROR(INDEX(Dim_Employee!$B$2:$B$76,MATCH(C36,Dim_Employee!$A$2:$A$76,0)),"") -> Blessing Nnamdi | E36: Asset Request | F36: AST-2848 | G36: Lagos Liaison Office | H36: Urgent | I36: Completed | J36: 333819.57 | K36: 45687
A37: ADM0036 | B37: 45869 | C37: EMP0031 | D37: =IFERROR(INDEX(Dim_Employee!$B$2:$B$76,MATCH(C37,Dim_Employee!$A$2:$A$76,0)),"") -> Emmanuel Aliyu | E37: Office Supplies | F37: AST-9519 | G37: Lagos Liaison Office | H37: High | I37: Cancelled | J37: 860950.52
A38: ADM0037 | B38: 45889 | C38: EMP0034 | D38: =IFERROR(INDEX(Dim_Employee!$B$2:$B$76,MATCH(C38,Dim_Employee!$A$2:$A$76,0)),"") -> Peace Balogun | E38: Facility Maintenance | F38: AST-1515 | G38: Guest House - Kogi | H38: Low | I38: Pending | J38: 815514.38
A39: ADM0038 | B39: 45950 | C39: EMP0032 | D39: =IFERROR(INDEX(Dim_Employee!$B$2:$B$76,MATCH(C39,Dim_Employee!$A$2:$A$76,0)),"") -> Blessing Nnamdi | E39: Travel Request | F39: AST-1313 | G39: Head Office - Abuja | H39: Urgent | I39: Pending | J39: 548524.73
A40: ADM0039 | B40: 45794 | C40: EMP0030 | D40: =IFERROR(INDEX(Dim_Employee!$B$2:$B$76,MATCH(C40,Dim_Employee!$A$2:$A$76,0)),"") -> Yusuf Abubakar | E40: Asset Request | F40: AST-1769 | G40: Kogi Plant Site | H40: Urgent | I40: In Progress | J40: 135279.14
A41: ADM0040 | B41: 45993 | C41: EMP0034 | D41: =IFERROR(INDEX(Dim_Employee!$B$2:$B$76,MATCH(C41,Dim_Employee!$A$2:$A$76,0)),"") -> Peace Balogun | E41: Facility Maintenance | F41: AST-4244 | G41: Head Office - Abuja | H41: Urgent | I41: Pending | J41: 310970.45
A42: ADM0041 | B42: 45663 | C42: EMP0035 | D42: =IFERROR(INDEX(Dim_Employee!$B$2:$B$76,MATCH(C42,Dim_Employee!$A$2:$A$76,0)),"") -> Ifeoma Balogun | E42: Utility Payment | F42: AST-1592 | G42: Head Office - Abuja | H42: Medium | I42: Cancelled | J42: 330464.15
A43: ADM0042 | B43: 45934 | C43: EMP0032 | D43: =IFERROR(INDEX(Dim_Employee!$B$2:$B$76,MATCH(C43,Dim_Employee!$A$2:$A$76,0)),"") -> Blessing Nnamdi | E43: Fleet/Vehicle | F43: AST-4668 | G43: Kogi Plant Site | H43: Urgent | I43: In Progress | J43: 1119461.6
A44: ADM0043 | B44: 45856 | C44: EMP0035 | D44: =IFERROR(INDEX(Dim_Employee!$B$2:$B$76,MATCH(C44,Dim_Employee!$A$2:$A$76,0)),"") -> Ifeoma Balogun | E44: Fleet/Vehicle | F44: AST-8430 | G44: Head Office - Abuja | H44: Low | I44: In Progress | J44: 455279.31
A45: ADM0044 | B45: 45992 | C45: EMP0034 | D45: =IFERROR(INDEX(Dim_Employee!$B$2:$B$76,MATCH(C45,Dim_Employee!$A$2:$A$76,0)),"") -> Peace Balogun | E45: Fleet/Vehicle | F45: AST-6348 | G45: Head Office - Abuja | H45: Low | I45: Pending | J45: 867713.1
A46: ADM0045 | B46: 45721 | C46: EMP0035 | D46: =IFERROR(INDEX(Dim_Employee!$B$2:$B$76,MATCH(C46,Dim_Employee!$A$2:$A$76,0)),"") -> Ifeoma Balogun | E46: Asset Request | F46: AST-7393 | G46: Kogi Plant Site | H46: High | I46: In Progress | J46: 646663.14
A47: ADM0046 | B47: 45792 | C47: EMP0032 | D47: =IFERROR(INDEX(Dim_Employee!$B$2:$B$76,MATCH(C47,Dim_Employee!$A$2:$A$76,0)),"") -> Blessing Nnamdi | E47: Utility Payment | F47: AST-2356 | G47: Kogi Plant Site | H47: Urgent | I47: Completed | J47: 413754.64 | K47: 45804
A48: ADM0047 | B48: 45798 | C48: EMP0033 | D48: =IFERROR(INDEX(Dim_Employee!$B$2:$B$76,MATCH(C48,Dim_Employee!$A$2:$A$76,0)),"") -> Ngozi Balogun | E48: Facility Maintenance | F48: AST-4576 | G48: Kogi Plant Site | H48: Urgent | I48: Cancelled | J48: 960832.54
A49: ADM0048 | B49: 45930 | C49: EMP0031 | D49: =IFERROR(INDEX(Dim_Employee!$B$2:$B$76,MATCH(C49,Dim_Employee!$A$2:$A$76,0)),"") -> Emmanuel Aliyu | E49: Office Supplies | F49: AST-3301 | G49: Lagos Liaison Office | H49: Medium | I49: Pending | J49: 1199789.6
A50: ADM0049 | B50: 45923 | C50: EMP0035 | D50: =IFERROR(INDEX(Dim_Employee!$B$2:$B$76,MATCH(C50,Dim_Employee!$A$2:$A$76,0)),"") -> Ifeoma Balogun | E50: Fleet/Vehicle | F50: AST-2409 | G50: Head Office - Abuja | H50: Urgent | I50: Cancelled | J50: 634362.77
A51: ADM0050 | B51: 45945 | C51: EMP0032 | D51: =IFERROR(INDEX(Dim_Employee!$B$2:$B$76,MATCH(C51,Dim_Employee!$A$2:$A$76,0)),"") -> Blessing Nnamdi | E51: Utility Payment | F51: AST-9424 | G51: Guest House - Kogi | H51: High | I51: In Progress | J51: 807201.89
A52: ADM0051 | B52: 45764 | C52: EMP0034 | D52: =IFERROR(INDEX(Dim_Employee!$B$2:$B$76,MATCH(C52,Dim_Employee!$A$2:$A$76,0)),"") -> Peace Balogun | E52: Asset Request | F52: AST-9924 | G52: Guest House - Kogi | H52: Urgent | I52: Pending | J52: 245155.83
A53: ADM0052 | B53: 45716 | C53: EMP0034 | D53: =IFERROR(INDEX(Dim_Employee!$B$2:$B$76,MATCH(C53,Dim_Employee!$A$2:$A$76,0)),"") -> Peace Balogun | E53: Fleet/Vehicle | F53: AST-1454 | G53: Kogi Plant Site | H53: Urgent | I53: Completed | J53: 655076.12 | K53: 45736
A54: ADM0053 | B54: 45720 | C54: EMP0034 | D54: =IFERROR(INDEX(Dim_Employee!$B$2:$B$76,MATCH(C54,Dim_Employee!$A$2:$A$76,0)),"") -> Peace Balogun | E54: Facility Maintenance | F54: AST-3732 | G54: Kogi Plant Site | H54: Urgent | I54: Cancelled | J54: 499460.03
A55: ADM0054 | B55: 45795 | C55: EMP0033 | D55: =IFERROR(INDEX(Dim_Employee!$B$2:$B$76,MATCH(C55,Dim_Employee!$A$2:$A$76,0)),"") -> Ngozi Balogun | E55: Fleet/Vehicle | F55: AST-9077 | G55: Head Office - Abuja | H55: High | I55: In Progress | J55: 523244.72
A56: ADM0055 | B56: 45926 | C56: EMP0033 | D56: =IFERROR(INDEX(Dim_Employee!$B$2:$B$76,MATCH(C56,Dim_Employee!$A$2:$A$76,0)),"") -> Ngozi Balogun | E56: Facility Maintenance | F56: AST-4136 | G56: Lagos Liaison Office | H56: Low | I56: Pending | J56: 1110698.5
A57: ADM0056 | B57: 46017 | C57: EMP0031 | D57: =IFERROR(INDEX(Dim_Employee!$B$2:$B$76,MATCH(C57,Dim_Employee!$A$2:$A$76,0)),"") -> Emmanuel Aliyu | E57: Asset Request | F57: AST-3548 | G57: Head Office - Abuja | H57: Low | I57: Completed | J57: 826005.67 | K57: 46019
A58: ADM0057 | B58: 45839 | C58: EMP0032 | D58: =IFERROR(INDEX(Dim_Employee!$B$2:$B$76,MATCH(C58,Dim_Employee!$A$2:$A$76,0)),"") -> Blessing Nnamdi | E58: Utility Payment | F58: AST-9172 | G58: Kogi Plant Site | H58: Urgent | I58: In Progress | J58: 878418.03
A59: ADM0058 | B59: 45919 | C59: EMP0030 | D59: =IFERROR(INDEX(Dim_Employee!$B$2:$B$76,MATCH(C59,Dim_Employee!$A$2:$A$76,0)),"") -> Yusuf Abubakar | E59: Office Supplies | F59: AST-4239 | G59: Lagos Liaison Office | H59: Low | I59: Pending | J59: 454004.75
A60: ADM0059 | B60: 45929 | C60: EMP0033 | D60: =IFERROR(INDEX(Dim_Employee!$B$2:$B$76,MATCH(C60,Dim_Employee!$A$2:$A$76,0)),"") -> Ngozi Balogun | E60: Utility Payment | F60: AST-4346 | G60: Head Office - Abuja | H60: Medium | I60: In Progress | J60: 1022253.5
A61: ADM0060 | B61: 45958 | C61: EMP0034 | D61: =IFERROR(INDEX(Dim_Employee!$B$2:$B$76,MATCH(C61,Dim_Employee!$A$2:$A$76,0)),"") -> Peace Balogun | E61: Asset Request | F61: AST-6695 | G61: Head Office - Abuja | H61: High | I61: In Progress | J61: 725737.36
A62: ADM0061 | B62: 45769 | C62: EMP0031 | D62: =IFERROR(INDEX(Dim_Employee!$B$2:$B$76,MATCH(C62,Dim_Employee!$A$2:$A$76,0)),"") -> Emmanuel Aliyu | E62: Facility Maintenance | F62: AST-3194 | G62: Head Office - Abuja | H62: Medium | I62: In Progress | J62: 873258.93
A63: ADM0062 | B63: 45856 | C63: EMP0032 | D63: =IFERROR(INDEX(Dim_Employee!$B$2:$B$76,MATCH(C63,Dim_Employee!$A$2:$A$76,0)),"") -> Blessing Nnamdi | E63: Fleet/Vehicle | F63: AST-9901 | G63: Head Office - Abuja | H63: Medium | I63: Completed | J63: 486320.67 | K63: 45870
A64: ADM0063 | B64: 45667 | C64: EMP0035 | D64: =IFERROR(INDEX(Dim_Employee!$B$2:$B$76,MATCH(C64,Dim_Employee!$A$2:$A$76,0)),"") -> Ifeoma Balogun | E64: Utility Payment | F64: AST-6858 | G64: Guest House - Kogi | H64: Low | I64: Completed | J64: 847130.42 | K64: 45674
A65: ADM0064 | B65: 45833 | C65: EMP0035 | D65: =IFERROR(INDEX(Dim_Employee!$B$2:$B$76,MATCH(C65,Dim_Employee!$A$2:$A$76,0)),"") -> Ifeoma Balogun | E65: Facility Maintenance | F65: AST-8898 | G65: Kogi Plant Site | H65: Low | I65: In Progress | J65: 49735.87
A66: ADM0065 | B66: 45972 | C66: EMP0034 | D66: =IFERROR(INDEX(Dim_Employee!$B$2:$B$76,MATCH(C66,Dim_Employee!$A$2:$A$76,0)),"") -> Peace Balogun | E66: Asset Request | F66: AST-4105 | G66: Head Office - Abuja | H66: Low | I66: Cancelled | J66: 248677.25
A67: ADM0066 | B67: 45802 | C67: EMP0031 | D67: =IFERROR(INDEX(Dim_Employee!$B$2:$B$76,MATCH(C67,Dim_Employee!$A$2:$A$76,0)),"") -> Emmanuel Aliyu | E67: Facility Maintenance | F67: AST-3202 | G67: Lagos Liaison Office | H67: Low | I67: Completed | J67: 918840.97 | K67: 45821
A68: ADM0067 | B68: 45858 | C68: EMP0032 | D68: =IFERROR(INDEX(Dim_Employee!$B$2:$B$76,MATCH(C68,Dim_Employee!$A$2:$A$76,0)),"") -> Blessing Nnamdi | E68: Fleet/Vehicle | F68: AST-9442 | G68: Guest House - Kogi | H68: Urgent | I68: Cancelled | J68: 256051.74
A69: ADM0068 | B69: 45664 | C69: EMP0032 | D69: =IFERROR(INDEX(Dim_Employee!$B$2:$B$76,MATCH(C69,Dim_Employee!$A$2:$A$76,0)),"") -> Blessing Nnamdi | E69: Asset Request | F69: AST-3969 | G69: Lagos Liaison Office | H69: Urgent | I69: Completed | J69: 434683.9 | K69: 45692
A70: ADM0069 | B70: 45865 | C70: EMP0032 | D70: =IFERROR(INDEX(Dim_Employee!$B$2:$B$76,MATCH(C70,Dim_Employee!$A$2:$A$76,0)),"") -> Blessing Nnamdi | E70: Utility Payment | F70: AST-3704 | G70: Kogi Plant Site | H70: Low | I70: In Progress | J70: 391817.58
A71: ADM0070 | B71: 46018 | C71: EMP0030 | D71: =IFERROR(INDEX(Dim_Employee!$B$2:$B$76,MATCH(C71,Dim_Employee!$A$2:$A$76,0)),"") -> Yusuf Abubakar | E71: Utility Payment | F71: AST-4128 | G71: Guest House - Kogi | H71: High | I71: Cancelled | J71: 339021.34
A72: ADM0071 | B72: 45739 | C72: EMP0030 | D72: =IFERROR(INDEX(Dim_Employee!$B$2:$B$76,MATCH(C72,Dim_Employee!$A$2:$A$76,0)),"") -> Yusuf Abubakar | E72: Asset Request | F72: AST-6405 | G72: Guest House - Kogi | H72: Urgent | I72: Cancelled | J72: 919448.82
A73: ADM0072 | B73: 45763 | C73: EMP0033 | D73: =IFERROR(INDEX(Dim_Employee!$B$2:$B$76,MATCH(C73,Dim_Employee!$A$2:$A$76,0)),"") -> Ngozi Balogun | E73: Facility Maintenance | F73: AST-6598 | G73: Guest House - Kogi | H73: Urgent | I73: In Progress | J73: 125531.51
A74: ADM0073 | B74: 45985 | C74: EMP0032 | D74: =IFERROR(INDEX(Dim_Employee!$B$2:$B$76,MATCH(C74,Dim_Employee!$A$2:$A$76,0)),"") -> Blessing Nnamdi | E74: Travel Request | F74: AST-5896 | G74: Guest House - Kogi | H74: Medium | I74: Completed | J74: 793414.67 | K74: 45993
A75: ADM0074 | B75: 45751 | C75: EMP0034 | D75: =IFERROR(INDEX(Dim_Employee!$B$2:$B$76,MATCH(C75,Dim_Employee!$A$2:$A$76,0)),"") -> Peace Balogun | E75: Utility Payment | F75: AST-9152 | G75: Head Office - Abuja | H75: Low | I75: Completed | J75: 915278.95 | K75: 45764
A76: ADM0075 | B76: 45669 | C76: EMP0034 | D76: =IFERROR(INDEX(Dim_Employee!$B$2:$B$76,MATCH(C76,Dim_Employee!$A$2:$A$76,0)),"") -> Peace Balogun | E76: Facility Maintenance | F76: AST-4883 | G76: Guest House - Kogi | H76: Urgent | I76: Completed | J76: 484859.01 | K76: 45689
A77: ADM0076 | B77: 45758 | C77: EMP0030 | D77: =IFERROR(INDEX(Dim_Employee!$B$2:$B$76,MATCH(C77,Dim_Employee!$A$2:$A$76,0)),"") -> Yusuf Abubakar | E77: Facility Maintenance | F77: AST-2612 | G77: Guest House - Kogi | H77: High | I77: Cancelled | J77: 334451.58
A78: ADM0077 | B78: 45939 | C78: EMP0032 | D78: =IFERROR(INDEX(Dim_Employee!$B$2:$B$76,MATCH(C78,Dim_Employee!$A$2:$A$76,0)),"") -> Blessing Nnamdi | E78: Utility Payment | F78: AST-2632 | G78: Lagos Liaison Office | H78: Low | I78: Cancelled | J78: 661551.64
A79: ADM0078 | B79: 45681 | C79: EMP0035 | D79: =IFERROR(INDEX(Dim_Employee!$B$2:$B$76,MATCH(C79,Dim_Employee!$A$2:$A$76,0)),"") -> Ifeoma Balogun | E79: Asset Request | F79: AST-7322 | G79: Lagos Liaison Office | H79: Medium | I79: Cancelled | J79: 1027528.5
A80: ADM0079 | B80: 45970 | C80: EMP0034 | D80: =IFERROR(INDEX(Dim_Employee!$B$2:$B$76,MATCH(C80,Dim_Employee!$A$2:$A$76,0)),"") -> Peace Balogun | E80: Fleet/Vehicle | F80: AST-7892 | G80: Guest House - Kogi | H80: Urgent | I80: Completed | J80: 719409.25 | K80: 45984
A81: ADM0080 | B81: 45929 | C81: EMP0032 | D81: =IFERROR(INDEX(Dim_Employee!$B$2:$B$76,MATCH(C81,Dim_Employee!$A$2:$A$76,0)),"") -> Blessing Nnamdi | E81: Fleet/Vehicle | F81: AST-5419 | G81: Guest House - Kogi | H81: High | I81: Pending | J81: 37099.27
A82: ADM0081 | B82: 45957 | C82: EMP0031 | D82: =IFERROR(INDEX(Dim_Employee!$B$2:$B$76,MATCH(C82,Dim_Employee!$A$2:$A$76,0)),"") -> Emmanuel Aliyu | E82: Asset Request | F82: AST-7697 | G82: Lagos Liaison Office | H82: Low | I82: Completed | J82: 1077562.8 | K82: 45978
A83: ADM0082 | B83: 45861 | C83: EMP0035 | D83: =IFERROR(INDEX(Dim_Employee!$B$2:$B$76,MATCH(C83,Dim_Employee!$A$2:$A$76,0)),"") -> Ifeoma Balogun | E83: Office Supplies | F83: AST-6230 | G83: Kogi Plant Site | H83: Medium | I83: Completed | J83: 518271.31 | K83: 45880
A84: ADM0083 | B84: 45786 | C84: EMP0033 | D84: =IFERROR(INDEX(Dim_Employee!$B$2:$B$76,MATCH(C84,Dim_Employee!$A$2:$A$76,0)),"") -> Ngozi Balogun | E84: Facility Maintenance | F84: AST-9574 | G84: Kogi Plant Site | H84: Urgent | I84: In Progress | J84: 177515.64
A85: ADM0084 | B85: 45967 | C85: EMP0031 | D85: =IFERROR(INDEX(Dim_Employee!$B$2:$B$76,MATCH(C85,Dim_Employee!$A$2:$A$76,0)),"") -> Emmanuel Aliyu | E85: Utility Payment | F85: AST-7834 | G85: Lagos Liaison Office | H85: Low | I85: Completed | J85: 248370.04 | K85: 45969
A86: ADM0085 | B86: 45840 | C86: EMP0030 | D86: =IFERROR(INDEX(Dim_Employee!$B$2:$B$76,MATCH(C86,Dim_Employee!$A$2:$A$76,0)),"") -> Yusuf Abubakar | E86: Facility Maintenance | F86: AST-6952 | G86: Lagos Liaison Office | H86: Medium | I86: In Progress | J86: 803130.06
A87: ADM0086 | B87: 45965 | C87: EMP0033 | D87: =IFERROR(INDEX(Dim_Employee!$B$2:$B$76,MATCH(C87,Dim_Employee!$A$2:$A$76,0)),"") -> Ngozi Balogun | E87: Office Supplies | F87: AST-7873 | G87: Guest House - Kogi | H87: Medium | I87: Pending | J87: 1143398.8
A88: ADM0087 | B88: 45723 | C88: EMP0035 | D88: =IFERROR(INDEX(Dim_Employee!$B$2:$B$76,MATCH(C88,Dim_Employee!$A$2:$A$76,0)),"") -> Ifeoma Balogun | E88: Fleet/Vehicle | F88: AST-2865 | G88: Guest House - Kogi | H88: High | I88: In Progress | J88: 333332.49
A89: ADM0088 | B89: 46008 | C89: EMP0034 | D89: =IFERROR(INDEX(Dim_Employee!$B$2:$B$76,MATCH(C89,Dim_Employee!$A$2:$A$76,0)),"") -> Peace Balogun | E89: Office Supplies | F89: AST-5565 | G89: Head Office - Abuja | H89: Medium | I89: In Progress | J89: 1142515.4
A90: ADM0089 | B90: 45992 | C90: EMP0034 | D90: =IFERROR(INDEX(Dim_Employee!$B$2:$B$76,MATCH(C90,Dim_Employee!$A$2:$A$76,0)),"") -> Peace Balogun | E90: Office Supplies | F90: AST-1647 | G90: Kogi Plant Site | H90: Low | I90: In Progress | J90: 328772.64
A91: ADM0090 | B91: 45671 | C91: EMP0033 | D91: =IFERROR(INDEX(Dim_Employee!$B$2:$B$76,MATCH(C91,Dim_Employee!$A$2:$A$76,0)),"") -> Ngozi Balogun | E91: Asset Request | F91: AST-9874 | G91: Guest House - Kogi | H91: Low | I91: Completed | J91: 908166.87 | K91: 45675
A92: ADM0091 | B92: 45740 | C92: EMP0035 | D92: =IFERROR(INDEX(Dim_Employee!$B$2:$B$76,MATCH(C92,Dim_Employee!$A$2:$A$76,0)),"") -> Ifeoma Balogun | E92: Office Supplies | F92: AST-7114 | G92: Lagos Liaison Office | H92: Urgent | I92: In Progress | J92: 428148.63
A93: ADM0092 | B93: 45833 | C93: EMP0032 | D93: =IFERROR(INDEX(Dim_Employee!$B$2:$B$76,MATCH(C93,Dim_Employee!$A$2:$A$76,0)),"") -> Blessing Nnamdi | E93: Office Supplies | F93: AST-3185 | G93: Kogi Plant Site | H93: Low | I93: Cancelled | J93: 539534.92
A94: ADM0093 | B94: 45767 | C94: EMP0034 | D94: =IFERROR(INDEX(Dim_Employee!$B$2:$B$76,MATCH(C94,Dim_Employee!$A$2:$A$76,0)),"") -> Peace Balogun | E94: Fleet/Vehicle | F94: AST-5228 | G94: Lagos Liaison Office | H94: Medium | I94: Cancelled | J94: 445895.24
A95: ADM0094 | B95: 45963 | C95: EMP0035 | D95: =IFERROR(INDEX(Dim_Employee!$B$2:$B$76,MATCH(C95,Dim_Employee!$A$2:$A$76,0)),"") -> Ifeoma Balogun | E95: Travel Request | F95: AST-9988 | G95: Head Office - Abuja | H95: Urgent | I95: Pending | J95: 786298.66
A96: ADM0095 | B96: 45707 | C96: EMP0034 | D96: =IFERROR(INDEX(Dim_Employee!$B$2:$B$76,MATCH(C96,Dim_Employee!$A$2:$A$76,0)),"") -> Peace Balogun | E96: Travel Request | F96: AST-2286 | G96: Kogi Plant Site | H96: Urgent | I96: Cancelled | J96: 679238.48
A97: ADM0096 | B97: 46008 | C97: EMP0033 | D97: =IFERROR(INDEX(Dim_Employee!$B$2:$B$76,MATCH(C97,Dim_Employee!$A$2:$A$76,0)),"") -> Ngozi Balogun | E97: Travel Request | F97: AST-1152 | G97: Kogi Plant Site | H97: High | I97: Cancelled | J97: 259846.14
A98: ADM0097 | B98: 45967 | C98: EMP0035 | D98: =IFERROR(INDEX(Dim_Employee!$B$2:$B$76,MATCH(C98,Dim_Employee!$A$2:$A$76,0)),"") -> Ifeoma Balogun | E98: Travel Request | F98: AST-9106 | G98: Guest House - Kogi | H98: High | I98: Completed | J98: 1058644.4 | K98: 45990
A99: ADM0098 | B99: 45841 | C99: EMP0031 | D99: =IFERROR(INDEX(Dim_Employee!$B$2:$B$76,MATCH(C99,Dim_Employee!$A$2:$A$76,0)),"") -> Emmanuel Aliyu | E99: Travel Request | F99: AST-2923 | G99: Guest House - Kogi | H99: Urgent | I99: Pending | J99: 685283.1
A100: ADM0099 | B100: 45800 | C100: EMP0035 | D100: =IFERROR(INDEX(Dim_Employee!$B$2:$B$76,MATCH(C100,Dim_Employee!$A$2:$A$76,0)),"") -> Ifeoma Balogun | E100: Utility Payment | F100: AST-5993 | G100: Lagos Liaison Office | H100: High | I100: Cancelled | J100: 269350.02
...

Sheet Customer_Service
A1: Ticket_ID | B1: Date | C1: Employee_ID | D1: Employee_Name | E1: Customer_Name | F1: Customer_Type | G1: Issue_Category | H1: Priority | I1: Status | J1: Resolution_Time_Hours | K1: Satisfaction_Score
A2: CS00001 | B2: 45749 | C2: EMP0038 | D2: =IFERROR(INDEX(Dim_Employee!$B$2:$B$76,MATCH(C2,Dim_Employee!$A$2:$A$76,0)),"") -> Ibrahim Nwosu | E2: Ikeja Electric Disco | F2: Bulk Trader | G2: Billing Dispute | H2: Urgent | I2: In Progress
A3: CS00002 | B3: 45752 | C3: EMP0042 | D3: =IFERROR(INDEX(Dim_Employee!$B$2:$B$76,MATCH(C3,Dim_Employee!$A$2:$A$76,0)),"") -> Funmilayo Yakubu | E3: Kaduna Disco | F3: Distribution Company | G3: Service Request | H3: Medium | I3: Resolved | J3: 30.7 | K3: 2
A4: CS00003 | B4: 45962 | C4: EMP0040 | D4: =IFERROR(INDEX(Dim_Employee!$B$2:$B$76,MATCH(C4,Dim_Employee!$A$2:$A$76,0)),"") -> Emeka Bello | E4: Nigerian Bulk Electricity Trading Plc | F4: Distribution Company | G4: Contract Query | H4: Medium | I4: Pending Customer Response
A5: CS00004 | B5: 45746 | C5: EMP0038 | D5: =IFERROR(INDEX(Dim_Employee!$B$2:$B$76,MATCH(C5,Dim_Employee!$A$2:$A$76,0)),"") -> Ibrahim Nwosu | E5: Kano Disco | F5: Government Agency | G5: Service Request | H5: Urgent | I5: Pending Customer Response
A6: CS00005 | B6: 45906 | C6: EMP0042 | D6: =IFERROR(INDEX(Dim_Employee!$B$2:$B$76,MATCH(C6,Dim_Employee!$A$2:$A$76,0)),"") -> Funmilayo Yakubu | E6: Port Harcourt Disco | F6: Bulk Trader | G6: Service Request | H6: Low | I6: Escalated
A7: CS00006 | B7: 45862 | C7: EMP0039 | D7: =IFERROR(INDEX(Dim_Employee!$B$2:$B$76,MATCH(C7,Dim_Employee!$A$2:$A$76,0)),"") -> Segun Ogunleye | E7: Ikeja Electric Disco | F7: Distribution Company | G7: Power Supply Interruption | H7: Urgent | I7: In Progress
A8: CS00007 | B8: 45687 | C8: EMP0040 | D8: =IFERROR(INDEX(Dim_Employee!$B$2:$B$76,MATCH(C8,Dim_Employee!$A$2:$A$76,0)),"") -> Emeka Bello | E8: Ibadan Disco | F8: Distribution Company | G8: Contract Query | H8: High | I8: Escalated
A9: CS00008 | B9: 45873 | C9: EMP0039 | D9: =IFERROR(INDEX(Dim_Employee!$B$2:$B$76,MATCH(C9,Dim_Employee!$A$2:$A$76,0)),"") -> Segun Ogunleye | E9: Eko Disco | F9: Bulk Trader | G9: Power Supply Interruption | H9: High | I9: In Progress
A10: CS00009 | B10: 45922 | C10: EMP0037 | D10: =IFERROR(INDEX(Dim_Employee!$B$2:$B$76,MATCH(C10,Dim_Employee!$A$2:$A$76,0)),"") -> Yusuf Usman | E10: Eko Disco | F10: Government Agency | G10: Service Request | H10: High | I10: Escalated
A11: CS00010 | B11: 45658 | C11: EMP0040 | D11: =IFERROR(INDEX(Dim_Employee!$B$2:$B$76,MATCH(C11,Dim_Employee!$A$2:$A$76,0)),"") -> Emeka Bello | E11: Ibadan Disco | F11: Distribution Company | G11: Power Supply Interruption | H11: Low | I11: Resolved | J11: 15.3 | K11: 2
A12: CS00011 | B12: 45972 | C12: EMP0038 | D12: =IFERROR(INDEX(Dim_Employee!$B$2:$B$76,MATCH(C12,Dim_Employee!$A$2:$A$76,0)),"") -> Ibrahim Nwosu | E12: Nigerian Bulk Electricity Trading Plc | F12: Distribution Company | G12: Contract Query | H12: Urgent | I12: Escalated
A13: CS00012 | B13: 45667 | C13: EMP0036 | D13: =IFERROR(INDEX(Dim_Employee!$B$2:$B$76,MATCH(C13,Dim_Employee!$A$2:$A$76,0)),"") -> Damilola Balogun | E13: Ibadan Disco | F13: Bulk Trader | G13: Power Supply Interruption | H13: Low | I13: Escalated
A14: CS00013 | B14: 45764 | C14: EMP0042 | D14: =IFERROR(INDEX(Dim_Employee!$B$2:$B$76,MATCH(C14,Dim_Employee!$A$2:$A$76,0)),"") -> Funmilayo Yakubu | E14: Ikeja Electric Disco | F14: Government Agency | G14: Contract Query | H14: Urgent | I14: Pending Customer Response
A15: CS00014 | B15: 45819 | C15: EMP0037 | D15: =IFERROR(INDEX(Dim_Employee!$B$2:$B$76,MATCH(C15,Dim_Employee!$A$2:$A$76,0)),"") -> Yusuf Usman | E15: Kano Disco | F15: Bulk Trader | G15: Billing Dispute | H15: High | I15: Escalated
A16: CS00015 | B16: 45712 | C16: EMP0039 | D16: =IFERROR(INDEX(Dim_Employee!$B$2:$B$76,MATCH(C16,Dim_Employee!$A$2:$A$76,0)),"") -> Segun Ogunleye | E16: Port Harcourt Disco | F16: Government Agency | G16: Contract Query | H16: Low | I16: Resolved | J16: 35.2 | K16: 2
A17: CS00016 | B17: 45664 | C17: EMP0041 | D17: =IFERROR(INDEX(Dim_Employee!$B$2:$B$76,MATCH(C17,Dim_Employee!$A$2:$A$76,0)),"") -> Chukwudi Okonkwo | E17: Port Harcourt Disco | F17: Government Agency | G17: Contract Query | H17: Medium | I17: Pending Customer Response
A18: CS00017 | B18: 45763 | C18: EMP0038 | D18: =IFERROR(INDEX(Dim_Employee!$B$2:$B$76,MATCH(C18,Dim_Employee!$A$2:$A$76,0)),"") -> Ibrahim Nwosu | E18: Eko Disco | F18: Bulk Trader | G18: Contract Query | H18: High | I18: Resolved | J18: 44.5 | K18: 1
A19: CS00018 | B19: 45942 | C19: EMP0038 | D19: =IFERROR(INDEX(Dim_Employee!$B$2:$B$76,MATCH(C19,Dim_Employee!$A$2:$A$76,0)),"") -> Ibrahim Nwosu | E19: Abuja Disco | F19: Bulk Trader | G19: Power Supply Interruption | H19: Medium | I19: Pending Customer Response
A20: CS00019 | B20: 45946 | C20: EMP0039 | D20: =IFERROR(INDEX(Dim_Employee!$B$2:$B$76,MATCH(C20,Dim_Employee!$A$2:$A$76,0)),"") -> Segun Ogunleye | E20: Enugu Disco | F20: Government Agency | G20: Metering/Data Issue | H20: Urgent | I20: Resolved | J20: 32.3 | K20: 3
A21: CS00020 | B21: 45705 | C21: EMP0042 | D21: =IFERROR(INDEX(Dim_Employee!$B$2:$B$76,MATCH(C21,Dim_Employee!$A$2:$A$76,0)),"") -> Funmilayo Yakubu | E21: Abuja Disco | F21: Distribution Company | G21: Service Request | H21: Low | I21: Pending Customer Response
A22: CS00021 | B22: 45750 | C22: EMP0037 | D22: =IFERROR(INDEX(Dim_Employee!$B$2:$B$76,MATCH(C22,Dim_Employee!$A$2:$A$76,0)),"") -> Yusuf Usman | E22: Ibadan Disco | F22: Bulk Trader | G22: Billing Dispute | H22: Urgent | I22: In Progress
A23: CS00022 | B23: 45738 | C23: EMP0040 | D23: =IFERROR(INDEX(Dim_Employee!$B$2:$B$76,MATCH(C23,Dim_Employee!$A$2:$A$76,0)),"") -> Emeka Bello | E23: Abuja Disco | F23: Bulk Trader | G23: Contract Query | H23: Low | I23: Resolved | J23: 10.5 | K23: 1
A24: CS00023 | B24: 45919 | C24: EMP0038 | D24: =IFERROR(INDEX(Dim_Employee!$B$2:$B$76,MATCH(C24,Dim_Employee!$A$2:$A$76,0)),"") -> Ibrahim Nwosu | E24: Eko Disco | F24: Government Agency | G24: Power Supply Interruption | H24: Medium | I24: Pending Customer Response
A25: CS00024 | B25: 45905 | C25: EMP0042 | D25: =IFERROR(INDEX(Dim_Employee!$B$2:$B$76,MATCH(C25,Dim_Employee!$A$2:$A$76,0)),"") -> Funmilayo Yakubu | E25: Kaduna Disco | F25: Bulk Trader | G25: Service Request | H25: Low | I25: Pending Customer Response
A26: CS00025 | B26: 45971 | C26: EMP0041 | D26: =IFERROR(INDEX(Dim_Employee!$B$2:$B$76,MATCH(C26,Dim_Employee!$A$2:$A$76,0)),"") -> Chukwudi Okonkwo | E26: Kaduna Disco | F26: Distribution Company | G26: Service Request | H26: Low | I26: Pending Customer Response
A27: CS00026 | B27: 45754 | C27: EMP0038 | D27: =IFERROR(INDEX(Dim_Employee!$B$2:$B$76,MATCH(C27,Dim_Employee!$A$2:$A$76,0)),"") -> Ibrahim Nwosu | E27: Kaduna Disco | F27: Bulk Trader | G27: Contract Query | H27: Low | I27: Escalated
A28: CS00027 | B28: 45762 | C28: EMP0040 | D28: =IFERROR(INDEX(Dim_Employee!$B$2:$B$76,MATCH(C28,Dim_Employee!$A$2:$A$76,0)),"") -> Emeka Bello | E28: Nigerian Bulk Electricity Trading Plc | F28: Bulk Trader | G28: Metering/Data Issue | H28: Low | I28: Pending Customer Response
A29: CS00028 | B29: 45787 | C29: EMP0040 | D29: =IFERROR(INDEX(Dim_Employee!$B$2:$B$76,MATCH(C29,Dim_Employee!$A$2:$A$76,0)),"") -> Emeka Bello | E29: Nigerian Bulk Electricity Trading Plc | F29: Bulk Trader | G29: Service Request | H29: Medium | I29: In Progress
A30: CS00029 | B30: 45951 | C30: EMP0038 | D30: =IFERROR(INDEX(Dim_Employee!$B$2:$B$76,MATCH(C30,Dim_Employee!$A$2:$A$76,0)),"") -> Ibrahim Nwosu | E30: Ibadan Disco | F30: Government Agency | G30: Power Supply Interruption | H30: Low | I30: In Progress
A31: CS00030 | B31: 45700 | C31: EMP0041 | D31: =IFERROR(INDEX(Dim_Employee!$B$2:$B$76,MATCH(C31,Dim_Employee!$A$2:$A$76,0)),"") -> Chukwudi Okonkwo | E31: Eko Disco | F31: Distribution Company | G31: Contract Query | H31: Urgent | I31: In Progress
A32: CS00031 | B32: 45826 | C32: EMP0041 | D32: =IFERROR(INDEX(Dim_Employee!$B$2:$B$76,MATCH(C32,Dim_Employee!$A$2:$A$76,0)),"") -> Chukwudi Okonkwo | E32: Abuja Disco | F32: Bulk Trader | G32: Metering/Data Issue | H32: Urgent | I32: Escalated
A33: CS00032 | B33: 45727 | C33: EMP0036 | D33: =IFERROR(INDEX(Dim_Employee!$B$2:$B$76,MATCH(C33,Dim_Employee!$A$2:$A$76,0)),"") -> Damilola Balogun | E33: Ibadan Disco | F33: Government Agency | G33: Service Request | H33: Low | I33: Pending Customer Response
A34: CS00033 | B34: 45744 | C34: EMP0040 | D34: =IFERROR(INDEX(Dim_Employee!$B$2:$B$76,MATCH(C34,Dim_Employee!$A$2:$A$76,0)),"") -> Emeka Bello | E34: Kaduna Disco | F34: Government Agency | G34: Power Supply Interruption | H34: Low | I34: Escalated
A35: CS00034 | B35: 45781 | C35: EMP0042 | D35: =IFERROR(INDEX(Dim_Employee!$B$2:$B$76,MATCH(C35,Dim_Employee!$A$2:$A$76,0)),"") -> Funmilayo Yakubu | E35: Kaduna Disco | F35: Distribution Company | G35: Power Supply Interruption | H35: Low | I35: Resolved | J35: 28.4 | K35: 3
A36: CS00035 | B36: 45815 | C36: EMP0039 | D36: =IFERROR(INDEX(Dim_Employee!$B$2:$B$76,MATCH(C36,Dim_Employee!$A$2:$A$76,0)),"") -> Segun Ogunleye | E36: Port Harcourt Disco | F36: Government Agency | G36: Service Request | H36: Low | I36: Resolved | J36: 39.3 | K36: 2
A37: CS00036 | B37: 45868 | C37: EMP0037 | D37: =IFERROR(INDEX(Dim_Employee!$B$2:$B$76,MATCH(C37,Dim_Employee!$A$2:$A$76,0)),"") -> Yusuf Usman | E37: Enugu Disco | F37: Distribution Company | G37: Power Supply Interruption | H37: Urgent | I37: In Progress
A38: CS00037 | B38: 45746 | C38: EMP0036 | D38: =IFERROR(INDEX(Dim_Employee!$B$2:$B$76,MATCH(C38,Dim_Employee!$A$2:$A$76,0)),"") -> Damilola Balogun | E38: Kaduna Disco | F38: Government Agency | G38: Power Supply Interruption | H38: High | I38: Pending Customer Response
A39: CS00038 | B39: 45685 | C39: EMP0037 | D39: =IFERROR(INDEX(Dim_Employee!$B$2:$B$76,MATCH(C39,Dim_Employee!$A$2:$A$76,0)),"") -> Yusuf Usman | E39: Ikeja Electric Disco | F39: Government Agency | G39: Power Supply Interruption | H39: Urgent | I39: Escalated
A40: CS00039 | B40: 45977 | C40: EMP0039 | D40: =IFERROR(INDEX(Dim_Employee!$B$2:$B$76,MATCH(C40,Dim_Employee!$A$2:$A$76,0)),"") -> Segun Ogunleye | E40: Port Harcourt Disco | F40: Bulk Trader | G40: Contract Query | H40: Urgent | I40: Resolved | J40: 45.6 | K40: 4
A41: CS00040 | B41: 45880 | C41: EMP0042 | D41: =IFERROR(INDEX(Dim_Employee!$B$2:$B$76,MATCH(C41,Dim_Employee!$A$2:$A$76,0)),"") -> Funmilayo Yakubu | E41: Abuja Disco | F41: Government Agency | G41: Billing Dispute | H41: High | I41: Pending Customer Response
A42: CS00041 | B42: 45873 | C42: EMP0040 | D42: =IFERROR(INDEX(Dim_Employee!$B$2:$B$76,MATCH(C42,Dim_Employee!$A$2:$A$76,0)),"") -> Emeka Bello | E42: Ikeja Electric Disco | F42: Bulk Trader | G42: Billing Dispute | H42: High | I42: Pending Customer Response
A43: CS00042 | B43: 45850 | C43: EMP0041 | D43: =IFERROR(INDEX(Dim_Employee!$B$2:$B$76,MATCH(C43,Dim_Employee!$A$2:$A$76,0)),"") -> Chukwudi Okonkwo | E43: Kaduna Disco | F43: Bulk Trader | G43: Service Request | H43: Low | I43: Pending Customer Response
A44: CS00043 | B44: 45915 | C44: EMP0037 | D44: =IFERROR(INDEX(Dim_Employee!$B$2:$B$76,MATCH(C44,Dim_Employee!$A$2:$A$76,0)),"") -> Yusuf Usman | E44: Port Harcourt Disco | F44: Distribution Company | G44: Contract Query | H44: Low | I44: Resolved | J44: 81.2 | K44: 2
A45: CS00044 | B45: 45937 | C45: EMP0040 | D45: =IFERROR(INDEX(Dim_Employee!$B$2:$B$76,MATCH(C45,Dim_Employee!$A$2:$A$76,0)),"") -> Emeka Bello | E45: Kano Disco | F45: Government Agency | G45: Contract Query | H45: Medium | I45: In Progress
A46: CS00045 | B46: 45937 | C46: EMP0036 | D46: =IFERROR(INDEX(Dim_Employee!$B$2:$B$76,MATCH(C46,Dim_Employee!$A$2:$A$76,0)),"") -> Damilola Balogun | E46: Port Harcourt Disco | F46: Government Agency | G46: Power Supply Interruption | H46: Medium | I46: Escalated
A47: CS00046 | B47: 45948 | C47: EMP0041 | D47: =IFERROR(INDEX(Dim_Employee!$B$2:$B$76,MATCH(C47,Dim_Employee!$A$2:$A$76,0)),"") -> Chukwudi Okonkwo | E47: Abuja Disco | F47: Distribution Company | G47: Billing Dispute | H47: Medium | I47: Pending Customer Response
A48: CS00047 | B48: 45658 | C48: EMP0036 | D48: =IFERROR(INDEX(Dim_Employee!$B$2:$B$76,MATCH(C48,Dim_Employee!$A$2:$A$76,0)),"") -> Damilola Balogun | E48: Kano Disco | F48: Distribution Company | G48: Metering/Data Issue | H48: Low | I48: Pending Customer Response
A49: CS00048 | B49: 45690 | C49: EMP0038 | D49: =IFERROR(INDEX(Dim_Employee!$B$2:$B$76,MATCH(C49,Dim_Employee!$A$2:$A$76,0)),"") -> Ibrahim Nwosu | E49: Enugu Disco | F49: Bulk Trader | G49: Service Request | H49: Urgent | I49: In Progress
A50: CS00049 | B50: 46012 | C50: EMP0037 | D50: =IFERROR(INDEX(Dim_Employee!$B$2:$B$76,MATCH(C50,Dim_Employee!$A$2:$A$76,0)),"") -> Yusuf Usman | E50: Ibadan Disco | F50: Distribution Company | G50: Metering/Data Issue | H50: Low | I50: Escalated
A51: CS00050 | B51: 45815 | C51: EMP0039 | D51: =IFERROR(INDEX(Dim_Employee!$B$2:$B$76,MATCH(C51,Dim_Employee!$A$2:$A$76,0)),"") -> Segun Ogunleye | E51: Kaduna Disco | F51: Bulk Trader | G51: Power Supply Interruption | H51: Urgent | I51: Escalated
A52: CS00051 | B52: 45809 | C52: EMP0037 | D52: =IFERROR(INDEX(Dim_Employee!$B$2:$B$76,MATCH(C52,Dim_Employee!$A$2:$A$76,0)),"") -> Yusuf Usman | E52: Ikeja Electric Disco | F52: Distribution Company | G52: Metering/Data Issue | H52: High | I52: In Progress
A53: CS00052 | B53: 45761 | C53: EMP0039 | D53: =IFERROR(INDEX(Dim_Employee!$B$2:$B$76,MATCH(C53,Dim_Employee!$A$2:$A$76,0)),"") -> Segun Ogunleye | E53: Nigerian Bulk Electricity Trading Plc | F53: Government Agency | G53: Power Supply Interruption | H53: Medium | I53: Resolved | J53: 17.3 | K53: 5
A54: CS00053 | B54: 45798 | C54: EMP0036 | D54: =IFERROR(INDEX(Dim_Employee!$B$2:$B$76,MATCH(C54,Dim_Employee!$A$2:$A$76,0)),"") -> Damilola Balogun | E54: Port Harcourt Disco | F54: Government Agency | G54: Power Supply Interruption | H54: High | I54: Resolved | J54: 30.1 | K54: 3
A55: CS00054 | B55: 45870 | C55: EMP0041 | D55: =IFERROR(INDEX(Dim_Employee!$B$2:$B$76,MATCH(C55,Dim_Employee!$A$2:$A$76,0)),"") -> Chukwudi Okonkwo | E55: Abuja Disco | F55: Distribution Company | G55: Power Supply Interruption | H55: High | I55: Pending Customer Response
A56: CS00055 | B56: 45795 | C56: EMP0036 | D56: =IFERROR(INDEX(Dim_Employee!$B$2:$B$76,MATCH(C56,Dim_Employee!$A$2:$A$76,0)),"") -> Damilola Balogun | E56: Eko Disco | F56: Government Agency | G56: Power Supply Interruption | H56: High | I56: In Progress
A57: CS00056 | B57: 45848 | C57: EMP0042 | D57: =IFERROR(INDEX(Dim_Employee!$B$2:$B$76,MATCH(C57,Dim_Employee!$A$2:$A$76,0)),"") -> Funmilayo Yakubu | E57: Nigerian Bulk Electricity Trading Plc | F57: Distribution Company | G57: Service Request | H57: Medium | I57: Escalated
A58: CS00057 | B58: 45999 | C58: EMP0038 | D58: =IFERROR(INDEX(Dim_Employee!$B$2:$B$76,MATCH(C58,Dim_Employee!$A$2:$A$76,0)),"") -> Ibrahim Nwosu | E58: Ibadan Disco | F58: Bulk Trader | G58: Power Supply Interruption | H58: Low | I58: In Progress
A59: CS00058 | B59: 45695 | C59: EMP0039 | D59: =IFERROR(INDEX(Dim_Employee!$B$2:$B$76,MATCH(C59,Dim_Employee!$A$2:$A$76,0)),"") -> Segun Ogunleye | E59: Nigerian Bulk Electricity Trading Plc | F59: Distribution Company | G59: Billing Dispute | H59: High | I59: Resolved | J59: 42.8 | K59: 5
A60: CS00059 | B60: 45874 | C60: EMP0040 | D60: =IFERROR(INDEX(Dim_Employee!$B$2:$B$76,MATCH(C60,Dim_Employee!$A$2:$A$76,0)),"") -> Emeka Bello | E60: Abuja Disco | F60: Distribution Company | G60: Metering/Data Issue | H60: Medium | I60: Escalated
A61: CS00060 | B61: 45800 | C61: EMP0037 | D61: =IFERROR(INDEX(Dim_Employee!$B$2:$B$76,MATCH(C61,Dim_Employee!$A$2:$A$76,0)),"") -> Yusuf Usman | E61: Nigerian Bulk Electricity Trading Plc | F61: Distribution Company | G61: Power Supply Interruption | H61: Medium | I61: In Progress
A62: CS00061 | B62: 45957 | C62: EMP0036 | D62: =IFERROR(INDEX(Dim_Employee!$B$2:$B$76,MATCH(C62,Dim_Employee!$A$2:$A$76,0)),"") -> Damilola Balogun | E62: Port Harcourt Disco | F62: Distribution Company | G62: Contract Query | H62: Low | I62: Pending Customer Response
A63: CS00062 | B63: 45822 | C63: EMP0037 | D63: =IFERROR(INDEX(Dim_Employee!$B$2:$B$76,MATCH(C63,Dim_Employee!$A$2:$A$76,0)),"") -> Yusuf Usman | E63: Enugu Disco | F63: Distribution Company | G63: Service Request | H63: High | I63: Resolved | J63: 53.8 | K63: 3
A64: CS00063 | B64: 45962 | C64: EMP0040 | D64: =IFERROR(INDEX(Dim_Employee!$B$2:$B$76,MATCH(C64,Dim_Employee!$A$2:$A$76,0)),"") -> Emeka Bello | E64: Eko Disco | F64: Distribution Company | G64: Service Request | H64: Urgent | I64: In Progress
A65: CS00064 | B65: 45938 | C65: EMP0037 | D65: =IFERROR(INDEX(Dim_Employee!$B$2:$B$76,MATCH(C65,Dim_Employee!$A$2:$A$76,0)),"") -> Yusuf Usman | E65: Kano Disco | F65: Government Agency | G65: Power Supply Interruption | H65: High | I65: Pending Customer Response
A66: CS00065 | B66: 45955 | C66: EMP0039 | D66: =IFERROR(INDEX(Dim_Employee!$B$2:$B$76,MATCH(C66,Dim_Employee!$A$2:$A$76,0)),"") -> Segun Ogunleye | E66: Enugu Disco | F66: Bulk Trader | G66: Billing Dispute | H66: Medium | I66: In Progress
A67: CS00066 | B67: 45824 | C67: EMP0040 | D67: =IFERROR(INDEX(Dim_Employee!$B$2:$B$76,MATCH(C67,Dim_Employee!$A$2:$A$76,0)),"") -> Emeka Bello | E67: Eko Disco | F67: Government Agency | G67: Billing Dispute | H67: Urgent | I67: Resolved | J67: 55.4 | K67: 2
A68: CS00067 | B68: 45915 | C68: EMP0042 | D68: =IFERROR(INDEX(Dim_Employee!$B$2:$B$76,MATCH(C68,Dim_Employee!$A$2:$A$76,0)),"") -> Funmilayo Yakubu | E68: Enugu Disco | F68: Government Agency | G68: Metering/Data Issue | H68: Low | I68: Pending Customer Response
A69: CS00068 | B69: 45985 | C69: EMP0036 | D69: =IFERROR(INDEX(Dim_Employee!$B$2:$B$76,MATCH(C69,Dim_Employee!$A$2:$A$76,0)),"") -> Damilola Balogun | E69: Nigerian Bulk Electricity Trading Plc | F69: Government Agency | G69: Power Supply Interruption | H69: Medium | I69: Resolved | J69: 87.2 | K69: 5
A70: CS00069 | B70: 45875 | C70: EMP0036 | D70: =IFERROR(INDEX(Dim_Employee!$B$2:$B$76,MATCH(C70,Dim_Employee!$A$2:$A$76,0)),"") -> Damilola Balogun | E70: Ikeja Electric Disco | F70: Government Agency | G70: Metering/Data Issue | H70: High | I70: Escalated
A71: CS00070 | B71: 45703 | C71: EMP0042 | D71: =IFERROR(INDEX(Dim_Employee!$B$2:$B$76,MATCH(C71,Dim_Employee!$A$2:$A$76,0)),"") -> Funmilayo Yakubu | E71: Nigerian Bulk Electricity Trading Plc | F71: Distribution Company | G71: Contract Query | H71: High | I71: Pending Customer Response
A72: CS00071 | B72: 45912 | C72: EMP0037 | D72: =IFERROR(INDEX(Dim_Employee!$B$2:$B$76,MATCH(C72,Dim_Employee!$A$2:$A$76,0)),"") -> Yusuf Usman | E72: Enugu Disco | F72: Distribution Company | G72: Metering/Data Issue | H72: Urgent | I72: In Progress
A73: CS00072 | B73: 46015 | C73: EMP0039 | D73: =IFERROR(INDEX(Dim_Employee!$B$2:$B$76,MATCH(C73,Dim_Employee!$A$2:$A$76,0)),"") -> Segun Ogunleye | E73: Ibadan Disco | F73: Government Agency | G73: Billing Dispute | H73: Medium | I73: Escalated
A74: CS00073 | B74: 45732 | C74: EMP0039 | D74: =IFERROR(INDEX(Dim_Employee!$B$2:$B$76,MATCH(C74,Dim_Employee!$A$2:$A$76,0)),"") -> Segun Ogunleye | E74: Enugu Disco | F74: Government Agency | G74: Billing Dispute | H74: Low | I74: In Progress
A75: CS00074 | B75: 45927 | C75: EMP0037 | D75: =IFERROR(INDEX(Dim_Employee!$B$2:$B$76,MATCH(C75,Dim_Employee!$A$2:$A$76,0)),"") -> Yusuf Usman | E75: Eko Disco | F75: Distribution Company | G75: Contract Query | H75: High | I75: Pending Customer Response
A76: CS00075 | B76: 45697 | C76: EMP0039 | D76: =IFERROR(INDEX(Dim_Employee!$B$2:$B$76,MATCH(C76,Dim_Employee!$A$2:$A$76,0)),"") -> Segun Ogunleye | E76: Ikeja Electric Disco | F76: Government Agency | G76: Service Request | H76: Medium | I76: Pending Customer Response
A77: CS00076 | B77: 45718 | C77: EMP0038 | D77: =IFERROR(INDEX(Dim_Employee!$B$2:$B$76,MATCH(C77,Dim_Employee!$A$2:$A$76,0)),"") -> Ibrahim Nwosu | E77: Nigerian Bulk Electricity Trading Plc | F77: Distribution Company | G77: Contract Query | H77: Urgent | I77: Escalated
A78: CS00077 | B78: 45844 | C78: EMP0036 | D78: =IFERROR(INDEX(Dim_Employee!$B$2:$B$76,MATCH(C78,Dim_Employee!$A$2:$A$76,0)),"") -> Damilola Balogun | E78: Kano Disco | F78: Bulk Trader | G78: Service Request | H78: Medium | I78: In Progress
A79: CS00078 | B79: 45864 | C79: EMP0036 | D79: =IFERROR(INDEX(Dim_Employee!$B$2:$B$76,MATCH(C79,Dim_Employee!$A$2:$A$76,0)),"") -> Damilola Balogun | E79: Ikeja Electric Disco | F79: Government Agency | G79: Metering/Data Issue | H79: Medium | I79: In Progress
A80: CS00079 | B80: 45767 | C80: EMP0039 | D80: =IFERROR(INDEX(Dim_Employee!$B$2:$B$76,MATCH(C80,Dim_Employee!$A$2:$A$76,0)),"") -> Segun Ogunleye | E80: Port Harcourt Disco | F80: Bulk Trader | G80: Billing Dispute | H80: Medium | I80: Pending Customer Response
A81: CS00080 | B81: 45784 | C81: EMP0039 | D81: =IFERROR(INDEX(Dim_Employee!$B$2:$B$76,MATCH(C81,Dim_Employee!$A$2:$A$76,0)),"") -> Segun Ogunleye | E81: Eko Disco | F81: Government Agency | G81: Power Supply Interruption | H81: Urgent | I81: Escalated
... A83: CS00082 | B83: 45907 | C83: EMP0039 | D83: =IFERROR(INDEX(Dim_Employee!$B$2:$B$76,MATCH(C83,Dim_Employee!$A$2:$A$76,0)),"") -> Segun Ogunleye | E83: Ibadan Disco | F83: Government Agency | G83: Contract Query | H83: Urgent | I83: In Progress
A84: CS00083 | B84: 45798 | C84: EMP0036 | D84: =IFERROR(INDEX(Dim_Employee!$B$2:$B$76,MATCH(C84,Dim_Employee!$A$2:$A$76,0)),"") -> Damilola Balogun | E84: Ikeja Electric Disco | F84: Government Agency | G84: Power Supply Interruption | H84: High | I84: Resolved | J84: 66.7 | K84: 3
A85: CS00084 | B85: 45948 | C85: EMP0040 | D85: =IFERROR(INDEX(Dim_Employee!$B$2:$B$76,MATCH(C85,Dim_Employee!$A$2:$A$76,0)),"") -> Emeka Bello | E85: Ibadan Disco | F85: Bulk Trader | G85: Billing Dispute | H85: High | I85: Pending Customer Response
A86: CS00085 | B86: 45842 | C86: EMP0036 | D86: =IFERROR(INDEX(Dim_Employee!$B$2:$B$76,MATCH(C86,Dim_Employee!$A$2:$A$76,0)),"") -> Damilola Balogun | E86: Eko Disco | F86: Distribution Company | G86: Billing Dispute | H86: Low | I86: In Progress
A87: CS00086 | B87: 45888 | C87: EMP0038 | D87: =IFERROR(INDEX(Dim_Employee!$B$2:$B$76,MATCH(C87,Dim_Employee!$A$2:$A$76,0)),"") -> Ibrahim Nwosu | E87: Abuja Disco | F87: Bulk Trader | G87: Metering/Data Issue | H87: High | I87: Pending Customer Response
A88: CS00087 | B88: 45780 | C88: EMP0042 | D88: =IFERROR(INDEX(Dim_Employee!$B$2:$B$76,MATCH(C88,Dim_Employee!$A$2:$A$76,0)),"") -> Funmilayo Yakubu | E88: Enugu Disco | F88: Distribution Company | G88: Power Supply Interruption | H88: Medium | I88: Resolved | J88: 29.7 | K88: 5
A89: CS00088 | B89: 45674 | C89: EMP0040 | D89: =IFERROR(INDEX(Dim_Employee!$B$2:$B$76,MATCH(C89,Dim_Employee!$A$2:$A$76,0)),"") -> Emeka Bello | E89: Ibadan Disco | F89: Bulk Trader | G89: Contract Query | H89: Urgent | I89: In Progress
A90: CS00089 | B90: 45922 | C90: EMP0039 | D90: =IFERROR(INDEX(Dim_Employee!$B$2:$B$76,MATCH(C90,Dim_Employee!$A$2:$A$76,0)),"") -> Segun Ogunleye | E90: Nigerian Bulk Electricity Trading Plc | F90: Bulk Trader | G90: Metering/Data Issue | H90: Urgent | I90: In Progress
A91: CS00090 | B91: 45733 | C91: EMP0041 | D91: =IFERROR(INDEX(Dim_Employee!$B$2:$B$76,MATCH(C91,Dim_Employee!$A$2:$A$76,0)),"") -> Chukwudi Okonkwo | E91: Ibadan Disco | F91: Bulk Trader | G91: Service Request | H91: Urgent | I91: Pending Customer Response
A92: CS00091 | B92: 45855 | C92: EMP0039 | D92: =IFERROR(INDEX(Dim_Employee!$B$2:$B$76,MATCH(C92,Dim_Employee!$A$2:$A$76,0)),"") -> Segun Ogunleye | E92: Nigerian Bulk Electricity Trading Plc | F92: Bulk Trader | G92: Power Supply Interruption | H92: Low | I92: In Progress
A93: CS00092 | B93: 45834 | C93: EMP0038 | D93: =IFERROR(INDEX(Dim_Employee!$B$2:$B$76,MATCH(C93,Dim_Employee!$A$2:$A$76,0)),"") -> Ibrahim Nwosu | E93: Ibadan Disco | F93: Distribution Company | G93: Billing Dispute | H93: Low | I93: Escalated
A94: CS00093 | B94: 45947 | C94: EMP0041 | D94: =IFERROR(INDEX(Dim_Employee!$B$2:$B$76,MATCH(C94,Dim_Employee!$A$2:$A$76,0)),"") -> Chukwudi Okonkwo | E94: Ikeja Electric Disco | F94: Government Agency | G94: Metering/Data Issue | H94: Low | I94: Pending Customer Response
A95: CS00094 | B95: 45943 | C95: EMP0042 | D95: =IFERROR(INDEX(Dim_Employee!$B$2:$B$76,MATCH(C95,Dim_Employee!$A$2:$A$76,0)),"") -> Funmilayo Yakubu | E95: Kaduna Disco | F95: Government Agency | G95: Billing Dispute | H95: High | I95: In Progress
A96: CS00095 | B96: 45704 | C96: EMP0037 | D96: =IFERROR(INDEX(Dim_Employee!$B$2:$B$76,MATCH(C96,Dim_Employee!$A$2:$A$76,0)),"") -> Yusuf Usman | E96: Port Harcourt Disco | F96: Distribution Company | G96: Contract Query | H96: Urgent | I96: Escalated
A97: CS00096 | B97: 45854 | C97: EMP0036 | D97: =IFERROR(INDEX(Dim_Employee!$B$2:$B$76,MATCH(C97,Dim_Employee!$A$2:$A$76,0)),"") -> Damilola Balogun | E97: Kaduna Disco | F97: Bulk Trader | G97: Contract Query | H97: High | I97: Pending Customer Response
A98: CS00097 | B98: 45864 | C98: EMP0037 | D98: =IFERROR(INDEX(Dim_Employee!$B$2:$B$76,MATCH(C98,Dim_Employee!$A$2:$A$76,0)),"") -> Yusuf Usman | E98: Ibadan Disco | F98: Bulk Trader | G98: Power Supply Interruption | H98: High | I98: In Progress
A99: CS00098 | B99: 45924 | C99: EMP0041 | D99: =IFERROR(INDEX(Dim_Employee!$B$2:$B$76,MATCH(C99,Dim_Employee!$A$2:$A$76,0)),"") -> Chukwudi Okonkwo | E99: Abuja Disco | F99: Government Agency | G99: Metering/Data Issue | H99: Urgent | I99: In Progress
A100: CS00099 | B100: 45902 | C100: EMP0042 | D100: =IFERROR(INDEX(Dim_Employee!$B$2:$B$76,MATCH(C100,Dim_Employee!$A$2:$A$76,0)),"") -> Funmilayo Yakubu | E100: Kano Disco | F100: Government Agency | G100: Service Request | H100: High | I100: In Progress
A101: CS00100 | B101: 45844 | C101: EMP0041 | D101: =IFERROR(INDEX(Dim_Employee!$B$2:$B$76,MATCH(C101,Dim_Employee!$A$2:$A$76,0)),"") -> Chukwudi Okonkwo | E101: Abuja Disco | F101: Bulk Trader | G101: Metering/Data Issue | H101: Low | I101: Resolved | J101: 86.7 | K101: 1
...

Sheet IT
A1: Ticket_ID | B1: Date | C1: Employee_ID | D1: Employee_Name | E1: System_Affected | F1: Issue_Type | G1: Priority | H1: Status | I1: Resolution_Time_Hours | J1: Downtime_Minutes
A2: ITK00001 | B2: 45761 | C2: EMP0046 | D2: =IFERROR(INDEX(Dim_Employee!$B$2:$B$76,MATCH(C2,Dim_Employee!$A$2:$A$76,0)),"") -> Musa Yakubu | E2: Email/Collaboration | F2: Hardware Failure | G2: Low | H2: In Progress | J2: 0
A3: ITK00002 | B3: 45860 | C3: EMP0046 | D3: =IFERROR(INDEX(Dim_Employee!$B$2:$B$76,MATCH(C3,Dim_Employee!$A$2:$A$76,0)),"") -> Musa Yakubu | E3: Access Control System | F3: System Outage | G3: Medium | H3: Open | J3: 0
A4: ITK00003 | B4: 45785 | C4: EMP0047 | D4: =IFERROR(INDEX(Dim_Employee!$B$2:$B$76,MATCH(C4,Dim_Employee!$A$2:$A$76,0)),"") -> Fatima Abubakar | E4: Email/Collaboration | F4: Software Bug | G4: Low | H4: Open | J4: 225
A5: ITK00004 | B5: 46003 | C5: EMP0044 | D5: =IFERROR(INDEX(Dim_Employee!$B$2:$B$76,MATCH(C5,Dim_Employee!$A$2:$A$76,0)),"") -> Adaeze Adeyemi | E5: SCADA | F5: Access Request | G5: High | H5: Closed | I5: 45.4 | J5: 0
A6: ITK00005 | B6: 45765 | C6: EMP0043 | D6: =IFERROR(INDEX(Dim_Employee!$B$2:$B$76,MATCH(C6,Dim_Employee!$A$2:$A$76,0)),"") -> Suleiman Garba | E6: SCADA | F6: Access Request | G6: Low | H6: Open | J6: 112
A7: ITK00006 | B7: 45911 | C7: EMP0049 | D7: =IFERROR(INDEX(Dim_Employee!$B$2:$B$76,MATCH(C7,Dim_Employee!$A$2:$A$76,0)),"") -> Rukayat Ude | E7: Email/Collaboration | F7: Access Request | G7: Low | H7: Open | J7: 0
A8: ITK00007 | B8: 45867 | C8: EMP0046 | D8: =IFERROR(INDEX(Dim_Employee!$B$2:$B$76,MATCH(C8,Dim_Employee!$A$2:$A$76,0)),"") -> Musa Yakubu | E8: Corporate Network | F8: Software Bug | G8: Low | H8: On Hold | J8: 0
A9: ITK00008 | B9: 45847 | C9: EMP0043 | D9: =IFERROR(INDEX(Dim_Employee!$B$2:$B$76,MATCH(C9,Dim_Employee!$A$2:$A$76,0)),"") -> Suleiman Garba | E9: Access Control System | F9: Security Alert | G9: High | H9: In Progress | J9: 93
A10: ITK00009 | B10: 45888 | C10: EMP0049 | D10: =IFERROR(INDEX(Dim_Employee!$B$2:$B$76,MATCH(C10,Dim_Employee!$A$2:$A$76,0)),"") -> Rukayat Ude | E10: Corporate Network | F10: Access Request | G10: High | H10: Open | J10: 0
A11: ITK00010 | B11: 45793 | C11: EMP0043 | D11: =IFERROR(INDEX(Dim_Employee!$B$2:$B$76,MATCH(C11,Dim_Employee!$A$2:$A$76,0)),"") -> Suleiman Garba | E11: Corporate Network | F11: Performance Issue | G11: Medium | H11: Open | J11: 0
A12: ITK00011 | B12: 46006 | C12: EMP0044 | D12: =IFERROR(INDEX(Dim_Employee!$B$2:$B$76,MATCH(C12,Dim_Employee!$A$2:$A$76,0)),"") -> Adaeze Adeyemi | E12: ERP System | F12: Performance Issue | G12: High | H12: Closed | I12: 35.8 | J12: 0
A13: ITK00012 | B13: 45878 | C13: EMP0043 | D13: =IFERROR(INDEX(Dim_Employee!$B$2:$B$76,MATCH(C13,Dim_Employee!$A$2:$A$76,0)),"") -> Suleiman Garba | E13: SCADA | F13: System Outage | G13: Critical | H13: In Progress | J13: 84
A14: ITK00013 | B14: 45762 | C14: EMP0047 | D14: =IFERROR(INDEX(Dim_Employee!$B$2:$B$76,MATCH(C14,Dim_Employee!$A$2:$A$76,0)),"") -> Fatima Abubakar | E14: SCADA | F14: Performance Issue | G14: High | H14: Closed | I14: 19.7 | J14: 129
A15: ITK00014 | B15: 45770 | C15: EMP0043 | D15: =IFERROR(INDEX(Dim_Employee!$B$2:$B$76,MATCH(C15,Dim_Employee!$A$2:$A$76,0)),"") -> Suleiman Garba | E15: Email/Collaboration | F15: Hardware Failure | G15: Medium | H15: Closed | I15: 28 | J15: 114
A16: ITK00015 | B16: 45822 | C16: EMP0049 | D16: =IFERROR(INDEX(Dim_Employee!$B$2:$B$76,MATCH(C16,Dim_Employee!$A$2:$A$76,0)),"") -> Rukayat Ude | E16: ERP System | F16: Access Request | G16: Low | H16: Open | J16: 94
A17: ITK00016 | B17: 45686 | C17: EMP0044 | D17: =IFERROR(INDEX(Dim_Employee!$B$2:$B$76,MATCH(C17,Dim_Employee!$A$2:$A$76,0)),"") -> Adaeze Adeyemi | E17: ERP System | F17: Software Bug | G17: High | H17: On Hold | J17: 0
A18: ITK00017 | B18: 45948 | C18: EMP0046 | D18: =IFERROR(INDEX(Dim_Employee!$B$2:$B$76,MATCH(C18,Dim_Employee!$A$2:$A$76,0)),"") -> Musa Yakubu | E18: SCADA | F18: System Outage | G18: Critical | H18: On Hold | J18: 0
A19: ITK00018 | B19: 45854 | C19: EMP0046 | D19: =IFERROR(INDEX(Dim_Employee!$B$2:$B$76,MATCH(C19,Dim_Employee!$A$2:$A$76,0)),"") -> Musa Yakubu | E19: Access Control System | F19: Performance Issue | G19: Critical | H19: On Hold | J19: 0
A20: ITK00019 | B20: 45886 | C20: EMP0047 | D20: =IFERROR(INDEX(Dim_Employee!$B$2:$B$76,MATCH(C20,Dim_Employee!$A$2:$A$76,0)),"") -> Fatima Abubakar | E20: Corporate Network | F20: Software Bug | G20: Low | H20: Closed | I20: 25 | J20: 151
A21: ITK00020 | B21: 45789 | C21: EMP0047 | D21: =IFERROR(INDEX(Dim_Employee!$B$2:$B$76,MATCH(C21,Dim_Employee!$A$2:$A$76,0)),"") -> Fatima Abubakar | E21: CCTV/Security System | F21: Software Bug | G21: High | H21: Closed | I21: 44.8 | J21: 112
A22: ITK00021 | B22: 45863 | C22: EMP0044 | D22: =IFERROR(INDEX(Dim_Employee!$B$2:$B$76,MATCH(C22,Dim_Employee!$A$2:$A$76,0)),"") -> Adaeze Adeyemi | E22: SCADA | F22: Performance Issue | G22: Critical | H22: On Hold | J22: 0
A23: ITK00022 | B23: 45730 | C23: EMP0043 | D23: =IFERROR(INDEX(Dim_Employee!$B$2:$B$76,MATCH(C23,Dim_Employee!$A$2:$A$76,0)),"") -> Suleiman Garba | E23: SCADA | F23: System Outage | G23: High | H23: In Progress | J23: 222
A24: ITK00023 | B24: 45923 | C24: EMP0045 | D24: =IFERROR(INDEX(Dim_Employee!$B$2:$B$76,MATCH(C24,Dim_Employee!$A$2:$A$76,0)),"") -> Chiamaka Bakare | E24: Corporate Network | F24: Hardware Failure | G24: Medium | H24: Closed | I24: 9.3 | J24: 82
A25: ITK00024 | B25: 45987 | C25: EMP0047 | D25: =IFERROR(INDEX(Dim_Employee!$B$2:$B$76,MATCH(C25,Dim_Employee!$A$2:$A$76,0)),"") -> Fatima Abubakar | E25: ERP System | F25: System Outage | G25: Low | H25: Closed | I25: 41.6 | J25: 67
A26: ITK00025 | B26: 45909 | C26: EMP0047 | D26: =IFERROR(INDEX(Dim_Employee!$B$2:$B$76,MATCH(C26,Dim_Employee!$A$2:$A$76,0)),"") -> Fatima Abubakar | E26: ERP System | F26: System Outage | G26: Critical | H26: On Hold | J26: 0
A27: ITK00026 | B27: 45691 | C27: EMP0049 | D27: =IFERROR(INDEX(Dim_Employee!$B$2:$B$76,MATCH(C27,Dim_Employee!$A$2:$A$76,0)),"") -> Rukayat Ude | E27: ERP System | F27: Access Request | G27: Medium | H27: Closed | I27: 37.1 | J27: 0
A28: ITK00027 | B28: 45770 | C28: EMP0043 | D28: =IFERROR(INDEX(Dim_Employee!$B$2:$B$76,MATCH(C28,Dim_Employee!$A$2:$A$76,0)),"") -> Suleiman Garba | E28: Corporate Network | F28: System Outage | G28: Critical | H28: Open | J28: 83
A29: ITK00028 | B29: 45896 | C29: EMP0044 | D29: =IFERROR(INDEX(Dim_Employee!$B$2:$B$76,MATCH(C29,Dim_Employee!$A$2:$A$76,0)),"") -> Adaeze Adeyemi | E29: Email/Collaboration | F29: System Outage | G29: Low | H29: On Hold | J29: 164
A30: ITK00029 | B30: 45819 | C30: EMP0048 | D30: =IFERROR(INDEX(Dim_Employee!$B$2:$B$76,MATCH(C30,Dim_Employee!$A$2:$A$76,0)),"") -> Rukayat Usman | E30: CCTV/Security System | F30: Performance Issue | G30: Critical | H30: In Progress | J30: 0
A31: ITK00030 | B31: 45980 | C31: EMP0046 | D31: =IFERROR(INDEX(Dim_Employee!$B$2:$B$76,MATCH(C31,Dim_Employee!$A$2:$A$76,0)),"") -> Musa Yakubu | E31: Corporate Network | F31: Security Alert | G31: Medium | H31: Closed | I31: 39.3 | J31: 0
A32: ITK00031 | B32: 46013 | C32: EMP0048 | D32: =IFERROR(INDEX(Dim_Employee!$B$2:$B$76,MATCH(C32,Dim_Employee!$A$2:$A$76,0)),"") -> Rukayat Usman | E32: Access Control System | F32: Hardware Failure | G32: Low | H32: In Progress | J32: 31
A33: ITK00032 | B33: 45970 | C33: EMP0044 | D33: =IFERROR(INDEX(Dim_Employee!$B$2:$B$76,MATCH(C33,Dim_Employee!$A$2:$A$76,0)),"") -> Adaeze Adeyemi | E33: Access Control System | F33: Access Request | G33: High | H33: Open | J33: 226
A34: ITK00033 | B34: 45842 | C34: EMP0044 | D34: =IFERROR(INDEX(Dim_Employee!$B$2:$B$76,MATCH(C34,Dim_Employee!$A$2:$A$76,0)),"") -> Adaeze Adeyemi | E34: Corporate Network | F34: Hardware Failure | G34: Medium | H34: Closed | I34: 47.8 | J34: 0
A35: ITK00034 | B35: 45971 | C35: EMP0044 | D35: =IFERROR(INDEX(Dim_Employee!$B$2:$B$76,MATCH(C35,Dim_Employee!$A$2:$A$76,0)),"") -> Adaeze Adeyemi | E35: Email/Collaboration | F35: Access Request | G35: Critical | H35: Closed | I35: 30.5 | J35: 0
A36: ITK00035 | B36: 45778 | C36: EMP0044 | D36: =IFERROR(INDEX(Dim_Employee!$B$2:$B$76,MATCH(C36,Dim_Employee!$A$2:$A$76,0)),"") -> Adaeze Adeyemi | E36: Email/Collaboration | F36: Software Bug | G36: Low | H36: Closed | I36: 45.2 | J36: 169
A37: ITK00036 | B37: 46004 | C37: EMP0045 | D37: =IFERROR(INDEX(Dim_Employee!$B$2:$B$76,MATCH(C37,Dim_Employee!$A$2:$A$76,0)),"") -> Chiamaka Bakare | E37: CCTV/Security System | F37: Hardware Failure | G37: Medium | H37: Closed | I37: 42 | J37: 205
A38: ITK00037 | B38: 45770 | C38: EMP0046 | D38: =IFERROR(INDEX(Dim_Employee!$B$2:$B$76,MATCH(C38,Dim_Employee!$A$2:$A$76,0)),"") -> Musa Yakubu | E38: Email/Collaboration | F38: Security Alert | G38: Low | H38: On Hold | J38: 99
A39: ITK00038 | B39: 45995 | C39: EMP0045 | D39: =IFERROR(INDEX(Dim_Employee!$B$2:$B$76,MATCH(C39,Dim_Employee!$A$2:$A$76,0)),"") -> Chiamaka Bakare | E39: Corporate Network | F39: Access Request | G39: Low | H39: On Hold | J39: 140
A40: ITK00039 | B40: 45961 | C40: EMP0048 | D40: =IFERROR(INDEX(Dim_Employee!$B$2:$B$76,MATCH(C40,Dim_Employee!$A$2:$A$76,0)),"") -> Rukayat Usman | E40: Corporate Network | F40: Hardware Failure | G40: Critical | H40: In Progress | J40: 90
A41: ITK00040 | B41: 45960 | C41: EMP0045 | D41: =IFERROR(INDEX(Dim_Employee!$B$2:$B$76,MATCH(C41,Dim_Employee!$A$2:$A$76,0)),"") -> Chiamaka Bakare | E41: SCADA | F41: Software Bug | G41: Low | H41: Open | J41: 211
A42: ITK00041 | B42: 45849 | C42: EMP0046 | D42: =IFERROR(INDEX(Dim_Employee!$B$2:$B$76,MATCH(C42,Dim_Employee!$A$2:$A$76,0)),"") -> Musa Yakubu | E42: SCADA | F42: Security Alert | G42: High | H42: In Progress | J42: 87
A43: ITK00042 | B43: 45745 | C43: EMP0049 | D43: =IFERROR(INDEX(Dim_Employee!$B$2:$B$76,MATCH(C43,Dim_Employee!$A$2:$A$76,0)),"") -> Rukayat Ude | E43: Email/Collaboration | F43: Software Bug | G43: High | H43: Closed | I43: 32.2 | J43: 17
A44: ITK00043 | B44: 45860 | C44: EMP0046 | D44: =IFERROR(INDEX(Dim_Employee!$B$2:$B$76,MATCH(C44,Dim_Employee!$A$2:$A$76,0)),"") -> Musa Yakubu | E44: Email/Collaboration | F44: Performance Issue | G44: Low | H44: Closed | I44: 46.6 | J44: 0
A45: ITK00044 | B45: 45993 | C45: EMP0043 | D45: =IFERROR(INDEX(Dim_Employee!$B$2:$B$76,MATCH(C45,Dim_Employee!$A$2:$A$76,0)),"") -> Suleiman Garba | E45: ERP System | F45: Software Bug | G45: Medium | H45: Closed | I45: 48 | J45: 0
A46: ITK00045 | B46: 45921 | C46: EMP0046 | D46: =IFERROR(INDEX(Dim_Employee!$B$2:$B$76,MATCH(C46,Dim_Employee!$A$2:$A$76,0)),"") -> Musa Yakubu | E46: Email/Collaboration | F46: System Outage | G46: Low | H46: Open | J46: 0
A47: ITK00046 | B47: 46014 | C47: EMP0043 | D47: =IFERROR(INDEX(Dim_Employee!$B$2:$B$76,MATCH(C47,Dim_Employee!$A$2:$A$76,0)),"") -> Suleiman Garba | E47: Access Control System | F47: Security Alert | G47: High | H47: In Progress | J47: 0
A48: ITK00047 | B48: 45719 | C48: EMP0048 | D48: =IFERROR(INDEX(Dim_Employee!$B$2:$B$76,MATCH(C48,Dim_Employee!$A$2:$A$76,0)),"") -> Rukayat Usman | E48: Email/Collaboration | F48: Hardware Failure | G48: Medium | H48: On Hold | J48: 0
A49: ITK00048 | B49: 45670 | C49: EMP0043 | D49: =IFERROR(INDEX(Dim_Employee!$B$2:$B$76,MATCH(C49,Dim_Employee!$A$2:$A$76,0)),"") -> Suleiman Garba | E49: SCADA | F49: Access Request | G49: Critical | H49: Open | J49: 0
A50: ITK00049 | B50: 45946 | C50: EMP0047 | D50: =IFERROR(INDEX(Dim_Employee!$B$2:$B$76,MATCH(C50,Dim_Employee!$A$2:$A$76,0)),"") -> Fatima Abubakar | E50: SCADA | F50: System Outage | G50: Medium | H50: Closed | I50: 37.4 | J50: 240
A51: ITK00050 | B51: 45783 | C51: EMP0044 | D51: =IFERROR(INDEX(Dim_Employee!$B$2:$B$76,MATCH(C51,Dim_Employee!$A$2:$A$76,0)),"") -> Adaeze Adeyemi | E51: ERP System | F51: Software Bug | G51: Critical | H51: Closed | I51: 24.7 | J51: 85
A52: ITK00051 | B52: 45745 | C52: EMP0046 | D52: =IFERROR(INDEX(Dim_Employee!$B$2:$B$76,MATCH(C52,Dim_Employee!$A$2:$A$76,0)),"") -> Musa Yakubu | E52: Access Control System | F52: System Outage | G52: Critical | H52: Closed | I52: 47.5 | J52: 0
A53: ITK00052 | B53: 45731 | C53: EMP0044 | D53: =IFERROR(INDEX(Dim_Employee!$B$2:$B$76,MATCH(C53,Dim_Employee!$A$2:$A$76,0)),"") -> Adaeze Adeyemi | E53: Access Control System | F53: Software Bug | G53: Medium | H53: Closed | I53: 39 | J53: 0
A54: ITK00053 | B54: 45714 | C54: EMP0046 | D54: =IFERROR(INDEX(Dim_Employee!$B$2:$B$76,MATCH(C54,Dim_Employee!$A$2:$A$76,0)),"") -> Musa Yakubu | E54: CCTV/Security System | F54: Security Alert | G54: Critical | H54: Closed | I54: 20.1 | J54: 37
A55: ITK00054 | B55: 45672 | C55: EMP0044 | D55: =IFERROR(INDEX(Dim_Employee!$B$2:$B$76,MATCH(C55,Dim_Employee!$A$2:$A$76,0)),"") -> Adaeze Adeyemi | E55: Email/Collaboration | F55: System Outage | G55: Critical | H55: Open | J55: 0
A56: ITK00055 | B56: 45932 | C56: EMP0045 | D56: =IFERROR(INDEX(Dim_Employee!$B$2:$B$76,MATCH(C56,Dim_Employee!$A$2:$A$76,0)),"") -> Chiamaka Bakare | E56: SCADA | F56: Security Alert | G56: Critical | H56: Closed | I56: 19 | J56: 52
A57: ITK00056 | B57: 45944 | C57: EMP0045 | D57: =IFERROR(INDEX(Dim_Employee!$B$2:$B$76,MATCH(C57,Dim_Employee!$A$2:$A$76,0)),"") -> Chiamaka Bakare | E57: ERP System | F57: Software Bug | G57: Low | H57: On Hold | J57: 238
A58: ITK00057 | B58: 45770 | C58: EMP0046 | D58: =IFERROR(INDEX(Dim_Employee!$B$2:$B$76,MATCH(C58,Dim_Employee!$A$2:$A$76,0)),"") -> Musa Yakubu | E58: Corporate Network | F58: System Outage | G58: Critical | H58: Open | J58: 144
A59: ITK00058 | B59: 45828 | C59: EMP0049 | D59: =IFERROR(INDEX(Dim_Employee!$B$2:$B$76,MATCH(C59,Dim_Employee!$A$2:$A$76,0)),"") -> Rukayat Ude | E59: Email/Collaboration | F59: System Outage | G59: Low | H59: On Hold | J59: 156
A60: ITK00059 | B60: 45772 | C60: EMP0045 | D60: =IFERROR(INDEX(Dim_Employee!$B$2:$B$76,MATCH(C60,Dim_Employee!$A$2:$A$76,0)),"") -> Chiamaka Bakare | E60: CCTV/Security System | F60: System Outage | G60: High | H60: Closed | I60: 8.3 | J60: 77
A61: ITK00060 | B61: 45924 | C61: EMP0043 | D61: =IFERROR(INDEX(Dim_Employee!$B$2:$B$76,MATCH(C61,Dim_Employee!$A$2:$A$76,0)),"") -> Suleiman Garba | E61: CCTV/Security System | F61: Software Bug | G61: Critical | H61: Open | J61: 228
A62: ITK00061 | B62: 45711 | C62: EMP0048 | D62: =IFERROR(INDEX(Dim_Employee!$B$2:$B$76,MATCH(C62,Dim_Employee!$A$2:$A$76,0)),"") -> Rukayat Usman | E62: SCADA | F62: Security Alert | G62: High | H62: Closed | I62: 18.2 | J62: 0
A63: ITK00062 | B63: 46013 | C63: EMP0044 | D63: =IFERROR(INDEX(Dim_Employee!$B$2:$B$76,MATCH(C63,Dim_Employee!$A$2:$A$76,0)),"") -> Adaeze Adeyemi | E63: Corporate Network | F63: Access Request | G63: Medium | H63: Open | J63: 0
A64: ITK00063 | B64: 45922 | C64: EMP0047 | D64: =IFERROR(INDEX(Dim_Employee!$B$2:$B$76,MATCH(C64,Dim_Employee!$A$2:$A$76,0)),"") -> Fatima Abubakar | E64: Corporate Network | F64: System Outage | G64: Low | H64: Closed | I64: 15.5 | J64: 0
A65: ITK00064 | B65: 45875 | C65: EMP0044 | D65: =IFERROR(INDEX(Dim_Employee!$B$2:$B$76,MATCH(C65,Dim_Employee!$A$2:$A$76,0)),"") -> Adaeze Adeyemi | E65: CCTV/Security System | F65: Access Request | G65: Critical | H65: Open | J65: 0
A66: ITK00065 | B66: 45707 | C66: EMP0043 | D66: =IFERROR(INDEX(Dim_Employee!$B$2:$B$76,MATCH(C66,Dim_Employee!$A$2:$A$76,0)),"") -> Suleiman Garba | E66: SCADA | F66: Hardware Failure | G66: Medium | H66: Open | J66: 0
A67: ITK00066 | B67: 45737 | C67: EMP0049 | D67: =IFERROR(INDEX(Dim_Employee!$B$2:$B$76,MATCH(C67,Dim_Employee!$A$2:$A$76,0)),"") -> Rukayat Ude | E67: Corporate Network | F67: Security Alert | G67: High | H67: Open | J67: 76
A68: ITK00067 | B68: 45940 | C68: EMP0043 | D68: =IFERROR(INDEX(Dim_Employee!$B$2:$B$76,MATCH(C68,Dim_Employee!$A$2:$A$76,0)),"") -> Suleiman Garba | E68: ERP System | F68: Access Request | G68: Low | H68: On Hold | J68: 150
A69: ITK00068 | B69: 45660 | C69: EMP0047 | D69: =IFERROR(INDEX(Dim_Employee!$B$2:$B$76,MATCH(C69,Dim_Employee!$A$2:$A$76,0)),"") -> Fatima Abubakar | E69: CCTV/Security System | F69: Hardware Failure | G69: Critical | H69: In Progress | J69: 0
A70: ITK00069 | B70: 45729 | C70: EMP0045 | D70: =IFERROR(INDEX(Dim_Employee!$B$2:$B$76,MATCH(C70,Dim_Employee!$A$2:$A$76,0)),"") -> Chiamaka Bakare | E70: Email/Collaboration | F70: Hardware Failure | G70: Critical | H70: Closed | I70: 8.7 | J70: 164
A71: ITK00070 | B71: 45694 | C71: EMP0049 | D71: =IFERROR(INDEX(Dim_Employee!$B$2:$B$76,MATCH(C71,Dim_Employee!$A$2:$A$76,0)),"") -> Rukayat Ude | E71: SCADA | F71: Access Request | G71: Low | H71: Closed | I71: 21.6 | J71: 0
A72: ITK00071 | B72: 45992 | C72: EMP0048 | D72: =IFERROR(INDEX(Dim_Employee!$B$2:$B$76,MATCH(C72,Dim_Employee!$A$2:$A$76,0)),"") -> Rukayat Usman | E72: Access Control System | F72: System Outage | G72: Medium | H72: Closed | I72: 19.4 | J72: 0
A73: ITK00072 | B73: 45721 | C73: EMP0043 | D73: =IFERROR(INDEX(Dim_Employee!$B$2:$B$76,MATCH(C73,Dim_Employee!$A$2:$A$76,0)),"") -> Suleiman Garba | E73: ERP System | F73: Access Request | G73: Critical | H73: On Hold | J73: 34
A74: ITK00073 | B74: 45760 | C74: EMP0046 | D74: =IFERROR(INDEX(Dim_Employee!$B$2:$B$76,MATCH(C74,Dim_Employee!$A$2:$A$76,0)),"") -> Musa Yakubu | E74: CCTV/Security System | F74: Security Alert | G74: Critical | H74: Closed | I74: 43.1 | J74: 0
A75: ITK00074 | B75: 45856 | C75: EMP0046 | D75: =IFERROR(INDEX(Dim_Employee!$B$2:$B$76,MATCH(C75,Dim_Employee!$A$2:$A$76,0)),"") -> Musa Yakubu | E75: Access Control System | F75: Hardware Failure | G75: Low | H75: On Hold | J75: 0
A76: ITK00075 | B76: 45823 | C76: EMP0047 | D76: =IFERROR(INDEX(Dim_Employee!$B$2:$B$76,MATCH(C76,Dim_Employee!$A$2:$A$76,0)),"") -> Fatima Abubakar | E76: ERP System | F76: System Outage | G76: High | H76: In Progress | J76: 0
A77: ITK00076 | B77: 45851 | C77: EMP0049 | D77: =IFERROR(INDEX(Dim_Employee!$B$2:$B$76,MATCH(C77,Dim_Employee!$A$2:$A$76,0)),"") -> Rukayat Ude | E77: Access Control System | F77: Software Bug | G77: Critical | H77: In Progress | J77: 0
A78: ITK00077 | B78: 45904 | C78: EMP0046 | D78: =IFERROR(INDEX(Dim_Employee!$B$2:$B$76,MATCH(C78,Dim_Employee!$A$2:$A$76,0)),"") -> Musa Yakubu | E78: CCTV/Security System | F78: Hardware Failure | G78: High | H78: On Hold | J78: 140
A79: ITK00078 | B79: 45868 | C79: EMP0043 | D79: =IFERROR(INDEX(Dim_Employee!$B$2:$B$76,MATCH(C79,Dim_Employee!$A$2:$A$76,0)),"") -> Suleiman Garba | E79: Access Control System | F79: System Outage | G79: High | H79: On Hold | J79: 63
A80: ITK00079 | B80: 45879 | C80: EMP0043 | D80: =IFERROR(INDEX(Dim_Employee!$B$2:$B$76,MATCH(C80,Dim_Employee!$A$2:$A$76,0)),"") -> Suleiman Garba | E80: Access Control System | F80: System Outage | G80: Medium | H80: Open | J80: 172
A81: ITK00080 | B81: 45753 | C81: EMP0046 | D81: =IFERROR(INDEX(Dim_Employee!$B$2:$B$76,MATCH(C81,Dim_Employee!$A$2:$A$76,0)),"") -> Musa Yakubu | E81: Access Control System | F81: System Outage | G81: High | H81: On Hold | J81: 28
A82: ITK00081 | B82: 45948 | C82: EMP0047 | D82: =IFERROR(INDEX(Dim_Employee!$B$2:$B$76,MATCH(C82,Dim_Employee!$A$2:$A$76,0)),"") -> Fatima Abubakar | E82: ERP System | F82: Software Bug | G82: Critical | H82: In Progress | J82: 168
A83: ITK00082 | B83: 45840 | C83: EMP0045 | D83: =IFERROR(INDEX(Dim_Employee!$B$2:$B$76,MATCH(C83,Dim_Employee!$A$2:$A$76,0)),"") -> Chiamaka Bakare | E83: Corporate Network | F83: System Outage | G83: Medium | H83: On Hold | J83: 228
A84: ITK00083 | B84: 45931 | C84: EMP0049 | D84: =IFERROR(INDEX(Dim_Employee!$B$2:$B$76,MATCH(C84,Dim_Employee!$A$2:$A$76,0)),"") -> Rukayat Ude | E84: CCTV/Security System | F84: Software Bug | G84: High | H84: In Progress | J84: 48
A85: ITK00084 | B85: 45956 | C85: EMP0043 | D85: =IFERROR(INDEX(Dim_Employee!$B$2:$B$76,MATCH(C85,Dim_Employee!$A$2:$A$76,0)),"") -> Suleiman Garba | E85: ERP System | F85: Access Request | G85: High | H85: In Progress | J85: 0
A86: ITK00085 | B86: 45806 | C86: EMP0045 | D86: =IFERROR(INDEX(Dim_Employee!$B$2:$B$76,MATCH(C86,Dim_Employee!$A$2:$A$76,0)),"") -> Chiamaka Bakare | E86: Access Control System | F86: Security Alert | G86: High | H86: Closed | I86: 45.7 | J86: 0
A87: ITK00086 | B87: 45787 | C87: EMP0043 | D87: =IFERROR(INDEX(Dim_Employee!$B$2:$B$76,MATCH(C87,Dim_Employee!$A$2:$A$76,0)),"") -> Suleiman Garba | E87: CCTV/Security System | F87: Access Request | G87: High | H87: In Progress | J87: 41
A88: ITK00087 | B88: 45672 | C88: EMP0045 | D88: =IFERROR(INDEX(Dim_Employee!$B$2:$B$76,MATCH(C88,Dim_Employee!$A$2:$A$76,0)),"") -> Chiamaka Bakare | E88: Corporate Network | F88: Access Request | G88: Medium | H88: In Progress | J88: 18
A89: ITK00088 | B89: 45725 | C89: EMP0049 | D89: =IFERROR(INDEX(Dim_Employee!$B$2:$B$76,MATCH(C89,Dim_Employee!$A$2:$A$76,0)),"") -> Rukayat Ude | E89: Access Control System | F89: System Outage | G89: Medium | H89: On Hold | J89: 206
A90: ITK00089 | B90: 45843 | C90: EMP0047 | D90: =IFERROR(INDEX(Dim_Employee!$B$2:$B$76,MATCH(C90,Dim_Employee!$A$2:$A$76,0)),"") -> Fatima Abubakar | E90: CCTV/Security System | F90: Software Bug | G90: Medium | H90: Open | J90: 103
A91: ITK00090 | B91: 45834 | C91: EMP0046 | D91: =IFERROR(INDEX(Dim_Employee!$B$2:$B$76,MATCH(C91,Dim_Employee!$A$2:$A$76,0)),"") -> Musa Yakubu | E91: CCTV/Security System | F91: Performance Issue | G91: High | H91: On Hold | J91: 0
A92: ITK00091 | B92: 45696 | C92: EMP0047 | D92: =IFERROR(INDEX(Dim_Employee!$B$2:$B$76,MATCH(C92,Dim_Employee!$A$2:$A$76,0)),"") -> Fatima Abubakar | E92: Access Control System | F92: System Outage | G92: Low | H92: Open | J92: 0
A93: ITK00092 | B93: 45719 | C93: EMP0045 | D93: =IFERROR(INDEX(Dim_Employee!$B$2:$B$76,MATCH(C93,Dim_Employee!$A$2:$A$76,0)),"") -> Chiamaka Bakare | E93: ERP System | F93: Access Request | G93: High | H93: Closed | I93: 5.3 | J93: 0
A94: ITK00093 | B94: 45692 | C94: EMP0045 | D94: =IFERROR(INDEX(Dim_Employee!$B$2:$B$76,MATCH(C94,Dim_Employee!$A$2:$A$76,0)),"") -> Chiamaka Bakare | E94: ERP System | F94: System Outage | G94: Critical | H94: In Progress | J94: 160
A95: ITK00094 | B95: 46008 | C95: EMP0047 | D95: =IFERROR(INDEX(Dim_Employee!$B$2:$B$76,MATCH(C95,Dim_Employee!$A$2:$A$76,0)),"") -> Fatima Abubakar | E95: Access Control System | F95: Software Bug | G95: Low | H95: In Progress | J95: 0
A96: ITK00095 | B96: 45971 | C96: EMP0046 | D96: =IFERROR(INDEX(Dim_Employee!$B$2:$B$76,MATCH(C96,Dim_Employee!$A$2:$A$76,0)),"") -> Musa Yakubu | E96: Email/Collaboration | F96: Performance Issue | G96: Low | H96: In Progress | J96: 167
A97: ITK00096 | B97: 45698 | C97: EMP0046 | D97: =IFERROR(INDEX(Dim_Employee!$B$2:$B$76,MATCH(C97,Dim_Employee!$A$2:$A$76,0)),"") -> Musa Yakubu | E97: CCTV/Security System | F97: Hardware Failure | G97: Low | H97: In Progress | J97: 0
A98: ITK00097 | B98: 46017 | C98: EMP0047 | D98: =IFERROR(INDEX(Dim_Employee!$B$2:$B$76,MATCH(C98,Dim_Employee!$A$2:$A$76,0)),"") -> Fatima Abubakar | E98: Corporate Network | F98: Performance Issue | G98: Medium | H98: Closed | I98: 6.9 | J98: 81
A99: ITK00098 | B99: 45668 | C99: EMP0049 | D99: =IFERROR(INDEX(Dim_Employee!$B$2:$B$76,MATCH(C99,Dim_Employee!$A$2:$A$76,0)),"") -> Rukayat Ude | E99: Access Control System | F99: Hardware Failure | G99: High | H99: On Hold | J99: 0
A100: ITK00099 | B100: 45713 | C100: EMP0044 | D100: =IFERROR(INDEX(Dim_Employee!$B$2:$B$76,MATCH(C100,Dim_Employee!$A$2:$A$76,0)),"") -> Adaeze Adeyemi | E100: SCADA | F100: Access Request | G100: High | H100: Closed | I100: 37 | J100: 219
...

Sheet Accounts_Finance
A1: Transaction_ID | B1: Date | C1: Employee_ID | D1: Employee_Name | E1: Department_Linked | F1: Transaction_Type | G1: Category | H1: Amount_NGN | I1: Budget_NGN | J1: Variance_NGN | K1: Approval_Status
A2: FIN00001 | B2: 45670 | C2: EMP0056 | D2: =IFERROR(INDEX(Dim_Employee!$B$2:$B$76,MATCH(C2,Dim_Employee!$A$2:$A$76,0)),"") -> Tunde Ndukwe | E2: Supply Chain | F2: Opex | G2: Payroll Recharge | H2: 27130330 | I2: 36925660 | J2: =H2-I2 -> -9795330 | K2: Approved
A3: FIN00002 | B3: 45974 | C3: EMP0052 | D3: =IFERROR(INDEX(Dim_Employee!$B$2:$B$76,MATCH(C3,Dim_Employee!$A$2:$A$76,0)),"") -> Amaka Aliyu | E3: Human Resources | F3: Opex | G3: Payroll Recharge | H3: 51628609 | I3: 58328731 | J3: =H3-I3 -> -6700122.9 | K3: Rejected
A4: FIN00003 | B4: 45840 | C4: EMP0057 | D4: =IFERROR(INDEX(Dim_Employee!$B$2:$B$76,MATCH(C4,Dim_Employee!$A$2:$A$76,0)),"") -> Abdullahi Ojo | E4: Supply Chain | F4: Opex | G4: Utilities | H4: 32897432 | I4: 37622597 | J4: =H4-I4 -> -4725164.6 | K4: Rejected
A5: FIN00004 | B5: 45828 | C5: EMP0056 | D5: =IFERROR(INDEX(Dim_Employee!$B$2:$B$76,MATCH(C5,Dim_Employee!$A$2:$A$76,0)),"") -> Tunde Ndukwe | E5: IT | F5: Opex | G5: Maintenance Cost | H5: 31109358 | I5: 32637196 | J5: =H5-I5 -> -1527838.1 | K5: Rejected
A6: FIN00005 | B6: 45805 | C6: EMP0052 | D6: =IFERROR(INDEX(Dim_Employee!$B$2:$B$76,MATCH(C6,Dim_Employee!$A$2:$A$76,0)),"") -> Amaka Aliyu | E6: Customer Service | F6: Opex | G6: Maintenance Cost | H6: 38209312 | I6: 30776690 | J6: =H6-I6 -> 7432622.5 | K6: Rejected
A7: FIN00006 | B7: 46017 | C7: EMP0055 | D7: =IFERROR(INDEX(Dim_Employee!$B$2:$B$76,MATCH(C7,Dim_Employee!$A$2:$A$76,0)),"") -> Emeka Adeyemi | E7: Admin | F7: Revenue | G7: Ancillary Services | H7: 30905462 | I7: 33519411 | J7: =H7-I7 -> -2613949.8 | K7: Rejected
A8: FIN00007 | B8: 45944 | C8: EMP0051 | D8: =IFERROR(INDEX(Dim_Employee!$B$2:$B$76,MATCH(C8,Dim_Employee!$A$2:$A$76,0)),"") -> Ngozi Ndukwe | E8: Operations | F8: Capex | G8: Facility Expansion | H8: 36878797 | I8: 41394630 | J8: =H8-I8 -> -4515832.3 | K8: Rejected
A9: FIN00008 | B9: 45795 | C9: EMP0056 | D9: =IFERROR(INDEX(Dim_Employee!$B$2:$B$76,MATCH(C9,Dim_Employee!$A$2:$A$76,0)),"") -> Tunde Ndukwe | E9: IT | F9: Capex | G9: Facility Expansion | H9: 581857.02 | I9: 597957.07 | J9: =H9-I9 -> -16100.05 | K9: Approved
A10: FIN00009 | B10: 45986 | C10: EMP0051 | D10: =IFERROR(INDEX(Dim_Employee!$B$2:$B$76,MATCH(C10,Dim_Employee!$A$2:$A$76,0)),"") -> Ngozi Ndukwe | E10: Supply Chain | F10: Opex | G10: Fuel Cost | H10: 29047371 | I10: 30101364 | J10: =H10-I10 -> -1053993 | K10: Pending Approval
A11: FIN00010 | B11: 45778 | C11: EMP0057 | D11: =IFERROR(INDEX(Dim_Employee!$B$2:$B$76,MATCH(C11,Dim_Employee!$A$2:$A$76,0)),"") -> Abdullahi Ojo | E11: Human Resources | F11: Revenue | G11: Ancillary Services | H11: 6309914.2 | I11: 5535180.4 | J11: =H11-I11 -> 774733.72 | K11: Approved
A12: FIN00011 | B12: 45876 | C12: EMP0054 | D12: =IFERROR(INDEX(Dim_Employee!$B$2:$B$76,MATCH(C12,Dim_Employee!$A$2:$A$76,0)),"") -> Titilayo Chukwu | E12: Admin | F12: Revenue | G12: Capacity Payment | H12: 52980680 | I12: 54218318 | J12: =H12-I12 -> -1237638.2 | K12: Approved
A13: FIN00012 | B13: 45819 | C13: EMP0051 | D13: =IFERROR(INDEX(Dim_Employee!$B$2:$B$76,MATCH(C13,Dim_Employee!$A$2:$A$76,0)),"") -> Ngozi Ndukwe | E13: Customer Service | F13: Opex | G13: Utilities | H13: 40444147 | I13: 51632156 | J13: =H13-I13 -> -11188008 | K13: Rejected
... A161: FIN00160 | B161: 45885 | C161: EMP0055 | D161: =IFERROR(INDEX(Dim_Employee!$B$2:$B$76,MATCH(C161,Dim_Employee!$A$2:$A$76,0)),"") -> Emeka Adeyemi | E161: Customer Service | F161: Revenue | G161: Energy Sales - NBET | H161: 10179016 | I161: 11467151 | J161: =H161-I161 -> -1288134.8 | K161: Approved

Sheet Human_Resources
A1: Record_ID | B1: Employee_ID | C1: Employee_Name | D1: Department | E1: Date | F1: Record_Type | G1: Details | H1: Days_Duration | I1: Performance_Rating | J1: Status
A2: HR00001 | B2: EMP0006 | C2: =IFERROR(INDEX(Dim_Employee!$B$2:$B$76,MATCH(B2,Dim_Employee!$A$2:$A$76,0)),"") -> Halima Nwosu | D2: Operations | E2: 45719 | F2: Promotion | G2: Grade Level Advancement | J2: Rejected
A3: HR00002 | B3: EMP0045 | C3: =IFERROR(INDEX(Dim_Employee!$B$2:$B$76,MATCH(B3,Dim_Employee!$A$2:$A$76,0)),"") -> Chiamaka Bakare | D3: IT | E3: 45806 | F3: Promotion | G3: Grade Level Advancement | J3: Approved
A4: HR00003 | B4: EMP0014 | C4: =IFERROR(INDEX(Dim_Employee!$B$2:$B$76,MATCH(B4,Dim_Employee!$A$2:$A$76,0)),"") -> Peace Balogun | D4: Operations | E4: 45825 | F4: Performance Review | G4: Annual Appraisal | I4: 4 | J4: Completed
A5: HR00004 | B5: EMP0042 | C5: =IFERROR(INDEX(Dim_Employee!$B$2:$B$76,MATCH(B5,Dim_Employee!$A$2:$A$76,0)),"") -> Funmilayo Yakubu | D5: Customer Service | E5: 45949 | F5: Performance Review | G5: Mid-Year Appraisal | I5: 1 | J5: Completed
A6: HR00005 | B6: EMP0026 | C6: =IFERROR(INDEX(Dim_Employee!$B$2:$B$76,MATCH(B6,Dim_Employee!$A$2:$A$76,0)),"") -> Ibrahim Abubakar | D6: Supply Chain | E6: 45891 | F6: Leave | G6: Maternity/Paternity Leave | H6: 18 | J6: Completed
A7: HR00006 | B7: EMP0013 | C7: =IFERROR(INDEX(Dim_Employee!$B$2:$B$76,MATCH(B7,Dim_Employee!$A$2:$A$76,0)),"") -> Chukwudi Eze | D7: Operations | E7: 45708 | F7: Disciplinary Action | G7: Suspension | H7: 1 | J7: Rejected
A8: HR00007 | B8: EMP0051 | C8: =IFERROR(INDEX(Dim_Employee!$B$2:$B$76,MATCH(B8,Dim_Employee!$A$2:$A$76,0)),"") -> Ngozi Ndukwe | D8: Accounts and Finance | E8: 45950 | F8: Disciplinary Action | G8: Suspension | H8: 10 | J8: Pending
A9: HR00008 | B9: EMP0053 | C9: =IFERROR(INDEX(Dim_Employee!$B$2:$B$76,MATCH(B9,Dim_Employee!$A$2:$A$76,0)),"") -> Chukwudi Yakubu | D9: Accounts and Finance | E9: 45953 | F9: Training | G9: HSE Refresher | H9: 5 | J9: Pending
A10: HR00009 | B10: EMP0050 | C10: =IFERROR(INDEX(Dim_Employee!$B$2:$B$76,MATCH(B10,Dim_Employee!$A$2:$A$76,0)),"") -> Funmilayo Adeyemi | D10: Accounts and Finance | E10: 45726 | F10: Training | G10: Technical Certification | H10: 2 | J10: Completed
A11: HR00010 | B11: EMP0071 | C11: =IFERROR(INDEX(Dim_Employee!$B$2:$B$76,MATCH(B11,Dim_Employee!$A$2:$A$76,0)),"") -> Bola Bakare | D11: Risk Management and Compliance | E11: 45892 | F11: Confirmation | G11: Confirmation After Probation | J11: Rejected
A12: HR00011 | B12: EMP0062 | C12: =IFERROR(INDEX(Dim_Employee!$B$2:$B$76,MATCH(B12,Dim_Employee!$A$2:$A$76,0)),"") -> Amaka Danjuma | D12: Human Resources | E12: 45719 | F12: Promotion | G12: Grade Level Advancement | J12: Rejected
A13: HR00012 | B13: EMP0048 | C13: =IFERROR(INDEX(Dim_Employee!$B$2:$B$76,MATCH(B13,Dim_Employee!$A$2:$A$76,0)),"") -> Rukayat Usman | D13: IT | E13: 45751 | F13: Disciplinary Action | G13: Query - Lateness | H13: 18 | J13: Pending
A14: HR00013 | B14: EMP0012 | C14: =IFERROR(INDEX(Dim_Employee!$B$2:$B$76,MATCH(B14,Dim_Employee!$A$2:$A$76,0)),"") -> Uche Ojo | D14: Operations | E14: 45850 | F14: Leave | G14: Maternity/Paternity Leave | H14: 15 | J14: Completed
A15: HR00014 | B15: EMP0034 | C15: =IFERROR(INDEX(Dim_Employee!$B$2:$B$76,MATCH(B15,Dim_Employee!$A$2:$A$76,0)),"") -> Peace Balogun | D15: Admin | E15: 45803 | F15: Training | G15: Technical Certification | H15: 4 | J15: Rejected
A16: HR00015 | B16: EMP0038 | C16: =IFERROR(INDEX(Dim_Employee!$B$2:$B$76,MATCH(B16,Dim_Employee!$A$2:$A$76,0)),"") -> Ibrahim Nwosu | D16: Customer Service | E16: 45745 | F16: Confirmation | G16: Confirmation After Probation | J16: Rejected
A17: HR00016 | B17: EMP0039 | C17: =IFERROR(INDEX(Dim_Employee!$B$2:$B$76,MATCH(B17,Dim_Employee!$A$2:$A$76,0)),"") -> Segun Ogunleye | D17: Customer Service | E17: 45697 | F17: Performance Review | G17: Mid-Year Appraisal | I17: 1 | J17: Approved
A18: HR00017 | B18: EMP0054 | C18: =IFERROR(INDEX(Dim_Employee!$B$2:$B$76,MATCH(B18,Dim_Employee!$A$2:$A$76,0)),"") -> Titilayo Chukwu | D18: Accounts and Finance | E18: 45692 | F18: Leave | G18: Maternity/Paternity Leave | H18: 15 | J18: Rejected
A19: HR00018 | B19: EMP0003 | C19: =IFERROR(INDEX(Dim_Employee!$B$2:$B$76,MATCH(B19,Dim_Employee!$A$2:$A$76,0)),"") -> Olamide Sani | D19: Operations | E19: 45990 | F19: Training | G19: Leadership Development | H19: 4 | J19: Completed
A20: HR00019 | B20: EMP0011 | C20: =IFERROR(INDEX(Dim_Employee!$B$2:$B$76,MATCH(B20,Dim_Employee!$A$2:$A$76,0)),"") -> Titilayo Danjuma | D20: Operations | E20: 45878 | F20: Training | G20: Leadership Development | H20: 2 | J20: Rejected
A21: HR00020 | B21: EMP0015 | C21: =IFERROR(INDEX(Dim_Employee!$B$2:$B$76,MATCH(B21,Dim_Employee!$A$2:$A$76,0)),"") -> Olamide Anyanwu | D21: Operations | E21: 45898 | F21: Training | G21: HSE Refresher | H21: 5 | J21: Rejected
A22: HR00021 | B22: EMP0020 | C22: =IFERROR(INDEX(Dim_Employee!$B$2:$B$76,MATCH(B22,Dim_Employee!$A$2:$A$76,0)),"") -> Aisha Danjuma | D22: Legal | E22: 45975 | F22: Leave | G22: Compassionate Leave | H22: 13 | J22: Completed
A23: HR00022 | B23: EMP0073 | C23: =IFERROR(INDEX(Dim_Employee!$B$2:$B$76,MATCH(B23,Dim_Employee!$A$2:$A$76,0)),"") -> Grace Chukwu | D23: Risk Management and Compliance | E23: 45959 | F23: Promotion | G23: Grade Level Advancement | J23: Approved
A24: HR00023 | B24: EMP0027 | C24: =IFERROR(INDEX(Dim_Employee!$B$2:$B$76,MATCH(B24,Dim_Employee!$A$2:$A$76,0)),"") -> Adaeze Onyeka | D24: Supply Chain | E24: 45820 | F24: Performance Review | G24: Mid-Year Appraisal | I24: 5 | J24: Completed
A25: HR00024 | B25: EMP0036 | C25: =IFERROR(INDEX(Dim_Employee!$B$2:$B$76,MATCH(B25,Dim_Employee!$A$2:$A$76,0)),"") -> Damilola Balogun | D25: Customer Service | E25: 45765 | F25: Confirmation | G25: Confirmation After Probation | J25: Pending
A26: HR00025 | B26: EMP0038 | C26: =IFERROR(INDEX(Dim_Employee!$B$2:$B$76,MATCH(B26,Dim_Employee!$A$2:$A$76,0)),"") -> Ibrahim Nwosu | D26: Customer Service | E26: 45896 | F26: Promotion | G26: Grade Level Advancement | J26: Approved
A27: HR00026 | B27: EMP0066 | C27: =IFERROR(INDEX(Dim_Employee!$B$2:$B$76,MATCH(B27,Dim_Employee!$A$2:$A$76,0)),"") -> Aisha Aliyu | D27: Internal Control | E27: 45814 | F27: Performance Review | G27: Annual Appraisal | I27: 5 | J27: Rejected
A28: HR00027 | B28: EMP0062 | C28: =IFERROR(INDEX(Dim_Employee!$B$2:$B$76,MATCH(B28,Dim_Employee!$A$2:$A$76,0)),"") -> Amaka Danjuma | D28: Human Resources | E28: 45737 | F28: Leave | G28: Annual Leave | H28: 8 | J28: Rejected
A29: HR00028 | B29: EMP0015 | C29: =IFERROR(INDEX(Dim_Employee!$B$2:$B$76,MATCH(B29,Dim_Employee!$A$2:$A$76,0)),"") -> Olamide Anyanwu | D29: Operations | E29: 45960 | F29: Promotion | G29: Grade Level Advancement | J29: Approved
A30: HR00029 | B30: EMP0060 | C30: =IFERROR(INDEX(Dim_Employee!$B$2:$B$76,MATCH(B30,Dim_Employee!$A$2:$A$76,0)),"") -> Femi Onyeka | D30: Human Resources | E30: 45852 | F30: Confirmation | G30: Confirmation After Probation | J30: Approved
A31: HR00030 | B31: EMP0048 | C31: =IFERROR(INDEX(Dim_Employee!$B$2:$B$76,MATCH(B31,Dim_Employee!$A$2:$A$76,0)),"") -> Rukayat Usman | D31: IT | E31: 45827 | F31: Training | G31: HSE Refresher | H31: 4 | J31: Rejected
A32: HR00031 | B32: EMP0053 | C32: =IFERROR(INDEX(Dim_Employee!$B$2:$B$76,MATCH(B32,Dim_Employee!$A$2:$A$76,0)),"") -> Chukwudi Yakubu | D32: Accounts and Finance | E32: 45678 | F32: Promotion | G32: Grade Level Advancement | J32: Completed
A33: HR00032 | B33: EMP0041 | C33: =IFERROR(INDEX(Dim_Employee!$B$2:$B$76,MATCH(B33,Dim_Employee!$A$2:$A$76,0)),"") -> Chukwudi Okonkwo | D33: Customer Service | E33: 45892 | F33: Disciplinary Action | G33: Suspension | H33: 12 | J33: Approved
A34: HR00033 | B34: EMP0006 | C34: =IFERROR(INDEX(Dim_Employee!$B$2:$B$76,MATCH(B34,Dim_Employee!$A$2:$A$76,0)),"") -> Halima Nwosu | D34: Operations | E34: 45798 | F34: Performance Review | G34: Mid-Year Appraisal | I34: 3 | J34: Pending
A35: HR00034 | B35: EMP0051 | C35: =IFERROR(INDEX(Dim_Employee!$B$2:$B$76,MATCH(B35,Dim_Employee!$A$2:$A$76,0)),"") -> Ngozi Ndukwe | D35: Accounts and Finance | E35: 45742 | F35: Leave | G35: Maternity/Paternity Leave | H35: 6 | J35: Completed
A36: HR00035 | B36: EMP0066 | C36: =IFERROR(INDEX(Dim_Employee!$B$2:$B$76,MATCH(B36,Dim_Employee!$A$2:$A$76,0)),"") -> Aisha Aliyu | D36: Internal Control | E36: 45958 | F36: Leave | G36: Maternity/Paternity Leave | H36: 2 | J36: Completed
A37: HR00036 | B37: EMP0018 | C37: =IFERROR(INDEX(Dim_Employee!$B$2:$B$76,MATCH(B37,Dim_Employee!$A$2:$A$76,0)),"") -> Abdullahi Yakubu | D37: Legal | E37: 45824 | F37: Promotion | G37: Grade Level Advancement | J37: Completed
A38: HR00037 | B38: EMP0036 | C38: =IFERROR(INDEX(Dim_Employee!$B$2:$B$76,MATCH(B38,Dim_Employee!$A$2:$A$76,0)),"") -> Damilola Balogun | D38: Customer Service | E38: 45785 | F38: Training | G38: Leadership Development | H38: 2 | J38: Completed
A39: HR00038 | B39: EMP0057 | C39: =IFERROR(INDEX(Dim_Employee!$B$2:$B$76,MATCH(B39,Dim_Employee!$A$2:$A$76,0)),"") -> Abdullahi Ojo | D39: Accounts and Finance | E39: 46013 | F39: Training | G39: Technical Certification | H39: 1 | J39: Approved
A40: HR00039 | B40: EMP0071 | C40: =IFERROR(INDEX(Dim_Employee!$B$2:$B$76,MATCH(B40,Dim_Employee!$A$2:$A$76,0)),"") -> Bola Bakare | D40: Risk Management and Compliance | E40: 45773 | F40: Disciplinary Action | G40: Query - Policy Breach | H40: 19 | J40: Completed
A41: HR00040 | B41: EMP0031 | C41: =IFERROR(INDEX(Dim_Employee!$B$2:$B$76,MATCH(B41,Dim_Employee!$A$2:$A$76,0)),"") -> Emmanuel Aliyu | D41: Admin | E41: 45835 | F41: Performance Review | G41: Annual Appraisal | I41: 2 | J41: Pending
A42: HR00041 | B42: EMP0072 | C42: =IFERROR(INDEX(Dim_Employee!$B$2:$B$76,MATCH(B42,Dim_Employee!$A$2:$A$76,0)),"") -> Tobi Adebayo | D42: Risk Management and Compliance | E42: 45688 | F42: Disciplinary Action | G42: Suspension | H42: 10 | J42: Rejected
A43: HR00042 | B43: EMP0016 | C43: =IFERROR(INDEX(Dim_Employee!$B$2:$B$76,MATCH(B43,Dim_Employee!$A$2:$A$76,0)),"") -> Tunde Okonkwo | D43: Operations | E43: 45690 | F43: Training | G43: Technical Certification | H43: 5 | J43: Pending
A44: HR00043 | B44: EMP0050 | C44: =IFERROR(INDEX(Dim_Employee!$B$2:$B$76,MATCH(B44,Dim_Employee!$A$2:$A$76,0)),"") -> Funmilayo Adeyemi | D44: Accounts and Finance | E44: 45801 | F44: Promotion | G44: Grade Level Advancement | J44: Approved
A45: HR00044 | B45: EMP0058 | C45: =IFERROR(INDEX(Dim_Employee!$B$2:$B$76,MATCH(B45,Dim_Employee!$A$2:$A$76,0)),"") -> Chioma Okafor | D45: Human Resources | E45: 45875 | F45: Leave | G45: Annual Leave | H45: 17 | J45: Pending
A46: HR00045 | B46: EMP0040 | C46: =IFERROR(INDEX(Dim_Employee!$B$2:$B$76,MATCH(B46,Dim_Employee!$A$2:$A$76,0)),"") -> Emeka Bello | D46: Customer Service | E46: 45782 | F46: Promotion | G46: Grade Level Advancement | J46: Rejected
A47: HR00046 | B47: EMP0054 | C47: =IFERROR(INDEX(Dim_Employee!$B$2:$B$76,MATCH(B47,Dim_Employee!$A$2:$A$76,0)),"") -> Titilayo Chukwu | D47: Accounts and Finance | E47: 45727 | F47: Confirmation | G47: Confirmation After Probation | J47: Pending
A48: HR00047 | B48: EMP0059 | C48: =IFERROR(INDEX(Dim_Employee!$B$2:$B$76,MATCH(B48,Dim_Employee!$A$2:$A$76,0)),"") -> Zainab Nwosu | D48: Human Resources | E48: 45902 | F48: Training | G48: HSE Refresher | H48: 5 | J48: Approved
A49: HR00048 | B49: EMP0052 | C49: =IFERROR(INDEX(Dim_Employee!$B$2:$B$76,MATCH(B49,Dim_Employee!$A$2:$A$76,0)),"") -> Amaka Aliyu | D49: Accounts and Finance | E49: 45690 | F49: Disciplinary Action | G49: Suspension | H49: 19 | J49: Completed
A50: HR00049 | B50: EMP0031 | C50: =IFERROR(INDEX(Dim_Employee!$B$2:$B$76,MATCH(B50,Dim_Employee!$A$2:$A$76,0)),"") -> Emmanuel Aliyu | D50: Admin | E50: 45785 | F50: Leave | G50: Maternity/Paternity Leave | H50: 9 | J50: Pending
A51: HR00050 | B51: EMP0067 | C51: =IFERROR(INDEX(Dim_Employee!$B$2:$B$76,MATCH(B51,Dim_Employee!$A$2:$A$76,0)),"") -> Tobi Okonkwo | D51: Internal Control | E51: 45895 | F51: Disciplinary Action | G51: Query - Policy Breach | H51: 9 | J51: Completed
A52: HR00051 | B52: EMP0018 | C52: =IFERROR(INDEX(Dim_Employee!$B$2:$B$76,MATCH(B52,Dim_Employee!$A$2:$A$76,0)),"") -> Abdullahi Yakubu | D52: Legal | E52: 45876 | F52: Leave | G52: Annual Leave | H52: 6 | J52: Approved
A53: HR00052 | B53: EMP0063 | C53: =IFERROR(INDEX(Dim_Employee!$B$2:$B$76,MATCH(B53,Dim_Employee!$A$2:$A$76,0)),"") -> Halima Ibe | D53: Human Resources | E53: 45828 | F53: Promotion | G53: Grade Level Advancement | J53: Approved
A54: HR00053 | B54: EMP0024 | C54: =IFERROR(INDEX(Dim_Employee!$B$2:$B$76,MATCH(B54,Dim_Employee!$A$2:$A$76,0)),"") -> Titilayo Okafor | D54: Supply Chain | E54: 45813 | F54: Leave | G54: Annual Leave | H54: 18 | J54: Completed
A55: HR00054 | B55: EMP0010 | C55: =IFERROR(INDEX(Dim_Employee!$B$2:$B$76,MATCH(B55,Dim_Employee!$A$2:$A$76,0)),"") -> Amaka Bakare | D55: Operations | E55: 45931 | F55: Leave | G55: Maternity/Paternity Leave | H55: 3 | J55: Completed
A56: HR00055 | B56: EMP0005 | C56: =IFERROR(INDEX(Dim_Employee!$B$2:$B$76,MATCH(B56,Dim_Employee!$A$2:$A$76,0)),"") -> Kelechi Ojo | D56: Operations | E56: 46010 | F56: Leave | G56: Maternity/Paternity Leave | H56: 13 | J56: Approved
A57: HR00056 | B57: EMP0048 | C57: =IFERROR(INDEX(Dim_Employee!$B$2:$B$76,MATCH(B57,Dim_Employee!$A$2:$A$76,0)),"") -> Rukayat Usman | D57: IT | E57: 45734 | F57: Performance Review | G57: Mid-Year Appraisal | I57: 3 | J57: Completed
A58: HR00057 | B58: EMP0006 | C58: =IFERROR(INDEX(Dim_Employee!$B$2:$B$76,MATCH(B58,Dim_Employee!$A$2:$A$76,0)),"") -> Halima Nwosu | D58: Operations | E58: 45717 | F58: Performance Review | G58: Annual Appraisal | I58: 2 | J58: Rejected
A59: HR00058 | B59: EMP0046 | C59: =IFERROR(INDEX(Dim_Employee!$B$2:$B$76,MATCH(B59,Dim_Employee!$A$2:$A$76,0)),"") -> Musa Yakubu | D59: IT | E59: 45712 | F59: Performance Review | G59: Mid-Year Appraisal | I59: 4 | J59: Completed
A60: HR00059 | B60: EMP0022 | C60: =IFERROR(INDEX(Dim_Employee!$B$2:$B$76,MATCH(B60,Dim_Employee!$A$2:$A$76,0)),"") -> Zainab Igwe | D60: Supply Chain | E60: 45855 | F60: Performance Review | G60: Annual Appraisal | I60: 5 | J60: Completed
A61: HR00060 | B61: EMP0027 | C61: =IFERROR(INDEX(Dim_Employee!$B$2:$B$76,MATCH(B61,Dim_Employee!$A$2:$A$76,0)),"") -> Adaeze Onyeka | D61: Supply Chain | E61: 45909 | F61: Promotion | G61: Grade Level Advancement | J61: Completed
A62: HR00061 | B62: EMP0063 | C62: =IFERROR(INDEX(Dim_Employee!$B$2:$B$76,MATCH(B62,Dim_Employee!$A$2:$A$76,0)),"") -> Halima Ibe | D62: Human Resources | E62: 45748 | F62: Training | G62: Tableau/Data Analytics Training | H62: 5 | J62: Pending
A63: HR00062 | B63: EMP0050 | C63: =IFERROR(INDEX(Dim_Employee!$B$2:$B$76,MATCH(B63,Dim_Employee!$A$2:$A$76,0)),"") -> Funmilayo Adeyemi | D63: Accounts and Finance | E63: 45693 | F63: Training | G63: Tableau/Data Analytics Training | H63: 5 | J63: Approved
A64: HR00063 | B64: EMP0014 | C64: =IFERROR(INDEX(Dim_Employee!$B$2:$B$76,MATCH(B64,Dim_Employee!$A$2:$A$76,0)),"") -> Peace Balogun | D64: Operations | E64: 45929 | F64: Training | G64: Technical Certification | H64: 4 | J64: Pending
A65: HR00064 | B65: EMP0069 | C65: =IFERROR(INDEX(Dim_Employee!$B$2:$B$76,MATCH(B65,Dim_Employee!$A$2:$A$76,0)),"") -> Segun Okafor | D65: Internal Control | E65: 45927 | F65: Leave | G65: Maternity/Paternity Leave | H65: 20 | J65: Approved
A66: HR00065 | B66: EMP0025 | C66: =IFERROR(INDEX(Dim_Employee!$B$2:$B$76,MATCH(B66,Dim_Employee!$A$2:$A$76,0)),"") -> Emeka Bakare | D66: Supply Chain | E66: 45735 | F66: Performance Review | G66: Mid-Year Appraisal | I66: 5 | J66: Completed
A67: HR00066 | B67: EMP0006 | C67: =IFERROR(INDEX(Dim_Employee!$B$2:$B$76,MATCH(B67,Dim_Employee!$A$2:$A$76,0)),"") -> Halima Nwosu | D67: Operations | E67: 45792 | F67: Confirmation | G67: Confirmation After Probation | J67: Rejected
A68: HR00067 | B68: EMP0060 | C68: =IFERROR(INDEX(Dim_Employee!$B$2:$B$76,MATCH(B68,Dim_Employee!$A$2:$A$76,0)),"") -> Femi Onyeka | D68: Human Resources | E68: 45691 | F68: Training | G68: Technical Certification | H68: 5 | J68: Completed
A69: HR00068 | B69: EMP0073 | C69: =IFERROR(INDEX(Dim_Employee!$B$2:$B$76,MATCH(B69,Dim_Employee!$A$2:$A$76,0)),"") -> Grace Chukwu | D69: Risk Management and Compliance | E69: 45991 | F69: Promotion | G69: Grade Level Advancement | J69: Approved
A70: HR00069 | B70: EMP0067 | C70: =IFERROR(INDEX(Dim_Employee!$B$2:$B$76,MATCH(B70,Dim_Employee!$A$2:$A$76,0)),"") -> Tobi Okonkwo | D70: Internal Control | E70: 45946 | F70: Confirmation | G70: Confirmation After Probation | J70: Rejected
A71: HR00070 | B71: EMP0050 | C71: =IFERROR(INDEX(Dim_Employee!$B$2:$B$76,MATCH(B71,Dim_Employee!$A$2:$A$76,0)),"") -> Funmilayo Adeyemi | D71: Accounts and Finance | E71: 45819 | F71: Promotion | G71: Grade Level Advancement | J71: Rejected
A72: HR00071 | B72: EMP0017 | C72: =IFERROR(INDEX(Dim_Employee!$B$2:$B$76,MATCH(B72,Dim_Employee!$A$2:$A$76,0)),"") -> Titilayo Abubakar | D72: Legal | E72: 45932 | F72: Promotion | G72: Grade Level Advancement | J72: Pending
A73: HR00072 | B73: EMP0007 | C73: =IFERROR(INDEX(Dim_Employee!$B$2:$B$76,MATCH(B73,Dim_Employee!$A$2:$A$76,0)),"") -> Emmanuel Yakubu | D73: Operations | E73: 45858 | F73: Confirmation | G73: Confirmation After Probation | J73: Pending
A74: HR00073 | B74: EMP0013 | C74: =IFERROR(INDEX(Dim_Employee!$B$2:$B$76,MATCH(B74,Dim_Employee!$A$2:$A$76,0)),"") -> Chukwudi Eze | D74: Operations | E74: 45699 | F74: Confirmation | G74: Confirmation After Probation | J74: Pending
A75: HR00074 | B75: EMP0062 | C75: =IFERROR(INDEX(Dim_Employee!$B$2:$B$76,MATCH(B75,Dim_Employee!$A$2:$A$76,0)),"") -> Amaka Danjuma | D75: Human Resources | E75: 45981 | F75: Disciplinary Action | G75: Query - Lateness | H75: 12 | J75: Rejected
A76: HR00075 | B76: EMP0006 | C76: =IFERROR(INDEX(Dim_Employee!$B$2:$B$76,MATCH(B76,Dim_Employee!$A$2:$A$76,0)),"") -> Halima Nwosu | D76: Operations | E76: 45669 | F76: Training | G76: Technical Certification | H76: 5 | J76: Pending
A77: HR00076 | B77: EMP0043 | C77: =IFERROR(INDEX(Dim_Employee!$B$2:$B$76,MATCH(B77,Dim_Employee!$A$2:$A$76,0)),"") -> Suleiman Garba | D77: IT | E77: 45735 | F77: Disciplinary Action | G77: Query - Policy Breach | H77: 15 | J77: Pending
A78: HR00077 | B78: EMP0037 | C78: =IFERROR(INDEX(Dim_Employee!$B$2:$B$76,MATCH(B78,Dim_Employee!$A$2:$A$76,0)),"") -> Yusuf Usman | D78: Customer Service | E78: 45924 | F78: Performance Review | G78: Annual Appraisal | I78: 3 | J78: Rejected
A79: HR00078 | B79: EMP0038 | C79: =IFERROR(INDEX(Dim_Employee!$B$2:$B$76,MATCH(B79,Dim_Employee!$A$2:$A$76,0)),"") -> Ibrahim Nwosu | D79: Customer Service | E79: 45863 | F79: Promotion | G79: Grade Level Advancement | J79: Completed
A80: HR00079 | B80: EMP0030 | C80: =IFERROR(INDEX(Dim_Employee!$B$2:$B$76,MATCH(B80,Dim_Employee!$A$2:$A$76,0)),"") -> Yusuf Abubakar | D80: Admin | E80: 45761 | F80: Promotion | G80: Grade Level Advancement | J80: Pending
A81: HR00080 | B81: EMP0025 | C81: =IFERROR(INDEX(Dim_Employee!$B$2:$B$76,MATCH(B81,Dim_Employee!$A$2:$A$76,0)),"") -> Emeka Bakare | D81: Supply Chain | E81: 46000 | F81: Leave | G81: Annual Leave | H81: 5 | J81: Approved
A82: HR00081 | B82: EMP0010 | C82: =IFERROR(INDEX(Dim_Employee!$B$2:$B$76,MATCH(B82,Dim_Employee!$A$2:$A$76,0)),"") -> Amaka Bakare | D82: Operations | E82: 45832 | F82: Performance Review | G82: Annual Appraisal | I82: 5 | J82: Approved
A83: HR00082 | B83: EMP0069 | C83: =IFERROR(INDEX(Dim_Employee!$B$2:$B$76,MATCH(B83,Dim_Employee!$A$2:$A$76,0)),"") -> Segun Okafor | D83: Internal Control | E83: 45890 | F83: Disciplinary Action | G83: Query - Policy Breach | H83: 14 | J83: Completed
A84: HR00083 | B84: EMP0009 | C84: =IFERROR(INDEX(Dim_Employee!$B$2:$B$76,MATCH(B84,Dim_Employee!$A$2:$A$76,0)),"") -> Kingsley Okonkwo | D84: Operations | E84: 45838 | F84: Promotion | G84: Grade Level Advancement | J84: Pending
A85: HR00084 | B85: EMP0026 | C85: =IFERROR(INDEX(Dim_Employee!$B$2:$B$76,MATCH(B85,Dim_Employee!$A$2:$A$76,0)),"") -> Ibrahim Abubakar | D85: Supply Chain | E85: 45842 | F85: Performance Review | G85: Annual Appraisal | I85: 2 | J85: Rejected
A86: HR00085 | B86: EMP0064 | C86: =IFERROR(INDEX(Dim_Employee!$B$2:$B$76,MATCH(B86,Dim_Employee!$A$2:$A$76,0)),"") -> Suleiman Igwe | D86: Human Resources | E86: 45825 | F86: Performance Review | G86: Annual Appraisal | I86: 2 | J86: Completed
A87: HR00086 | B87: EMP0055 | C87: =IFERROR(INDEX(Dim_Employee!$B$2:$B$76,MATCH(B87,Dim_Employee!$A$2:$A$76,0)),"") -> Emeka Adeyemi | D87: Accounts and Finance | E87: 45983 | F87: Disciplinary Action | G87: Suspension | H87: 9 | J87: Completed
A88: HR00087 | B88: EMP0057 | C88: =IFERROR(INDEX(Dim_Employee!$B$2:$B$76,MATCH(B88,Dim_Employee!$A$2:$A$76,0)),"") -> Abdullahi Ojo | D88: Accounts and Finance | E88: 45912 | F88: Leave | G88: Annual Leave | H88: 11 | J88: Pending
A89: HR00088 | B89: EMP0075 | C89: =IFERROR(INDEX(Dim_Employee!$B$2:$B$76,MATCH(B89,Dim_Employee!$A$2:$A$76,0)),"") -> Halima Okafor | D89: Risk Management and Compliance | E89: 45726 | F89: Training | G89: Technical Certification | H89: 3 | J89: Rejected
A90: HR00089 | B90: EMP0034 | C90: =IFERROR(INDEX(Dim_Employee!$B$2:$B$76,MATCH(B90,Dim_Employee!$A$2:$A$76,0)),"") -> Peace Balogun | D90: Admin | E90: 45819 | F90: Confirmation | G90: Confirmation After Probation | J90: Pending
A91: HR00090 | B91: EMP0063 | C91: =IFERROR(INDEX(Dim_Employee!$B$2:$B$76,MATCH(B91,Dim_Employee!$A$2:$A$76,0)),"") -> Halima Ibe | D91: Human Resources | E91: 45672 | F91: Confirmation | G91: Confirmation After Probation | J91: Rejected
A92: HR00091 | B92: EMP0075 | C92: =IFERROR(INDEX(Dim_Employee!$B$2:$B$76,MATCH(B92,Dim_Employee!$A$2:$A$76,0)),"") -> Halima Okafor | D92: Risk Management and Compliance | E92: 45800 | F92: Training | G92: Leadership Development | H92: 3 | J92: Completed
A93: HR00092 | B93: EMP0048 | C93: =IFERROR(INDEX(Dim_Employee!$B$2:$B$76,MATCH(B93,Dim_Employee!$A$2:$A$76,0)),"") -> Rukayat Usman | D93: IT | E93: 45820 | F93: Disciplinary Action | G93: Suspension | H93: 5 | J93: Pending
A94: HR00093 | B94: EMP0023 | C94: =IFERROR(INDEX(Dim_Employee!$B$2:$B$76,MATCH(B94,Dim_Employee!$A$2:$A$76,0)),"") -> Uche Ibe | D94: Supply Chain | E94: 45716 | F94: Promotion | G94: Grade Level Advancement | J94: Completed
A95: HR00094 | B95: EMP0036 | C95: =IFERROR(INDEX(Dim_Employee!$B$2:$B$76,MATCH(B95,Dim_Employee!$A$2:$A$76,0)),"") -> Damilola Balogun | D95: Customer Service | E95: 45956 | F95: Performance Review | G95: Annual Appraisal | I95: 3 | J95: Approved
A96: HR00095 | B96: EMP0034 | C96: =IFERROR(INDEX(Dim_Employee!$B$2:$B$76,MATCH(B96,Dim_Employee!$A$2:$A$76,0)),"") -> Peace Balogun | D96: Admin | E96: 45729 | F96: Confirmation | G96: Confirmation After Probation | J96: Approved
A97: HR00096 | B97: EMP0065 | C97: =IFERROR(INDEX(Dim_Employee!$B$2:$B$76,MATCH(B97,Dim_Employee!$A$2:$A$76,0)),"") -> Aisha Igwe | D97: Internal Control | E97: 46003 | F97: Performance Review | G97: Annual Appraisal | I97: 1 | J97: Approved
A98: HR00097 | B98: EMP0037 | C98: =IFERROR(INDEX(Dim_Employee!$B$2:$B$76,MATCH(B98,Dim_Employee!$A$2:$A$76,0)),"") -> Yusuf Usman | D98: Customer Service | E98: 45900 | F98: Disciplinary Action | G98: Query - Policy Breach | H98: 6 | J98: Pending
A99: HR00098 | B99: EMP0044 | C99: =IFERROR(INDEX(Dim_Employee!$B$2:$B$76,MATCH(B99,Dim_Employee!$A$2:$A$76,0)),"") -> Adaeze Adeyemi | D99: IT | E99: 45687 | F99: Disciplinary Action | G99: Suspension | H99: 10 | J99: Pending
A100: HR00099 | B100: EMP0048 | C100: =IFERROR(INDEX(Dim_Employee!$B$2:$B$76,MATCH(B100,Dim_Employee!$A$2:$A$76,0)),"") -> Rukayat Usman | D100: IT | E100: 45888 | F100: Leave | G100: Annual Leave | H100: 12 | J100: Pending
...

Sheet Internal_Control
A1: Audit_ID | B1: Date | C1: Employee_ID | D1: Employee_Name | E1: Department_Audited | F1: Audit_Type | G1: Finding_Description | H1: Severity | I1: Status | J1: Closure_Date
A2: AUD0001 | B2: 45939 | C2: EMP0066 | D2: =IFERROR(INDEX(Dim_Employee!$B$2:$B$76,MATCH(C2,Dim_Employee!$A$2:$A$76,0)),"") -> Aisha Aliyu | E2: Supply Chain | F2: Compliance Audit | G2: Budget variance unexplained | H2: Medium | I2: In Remediation
A3: AUD0002 | B3: 45767 | C3: EMP0069 | D3: =IFERROR(INDEX(Dim_Employee!$B$2:$B$76,MATCH(C3,Dim_Employee!$A$2:$A$76,0)),"") -> Segun Okafor | E3: Accounts and Finance | F3: Financial Audit | G3: Budget variance unexplained | H3: Critical | I3: Closed | J3: 45811
A4: AUD0003 | B4: 45741 | C4: EMP0066 | D4: =IFERROR(INDEX(Dim_Employee!$B$2:$B$76,MATCH(C4,Dim_Employee!$A$2:$A$76,0)),"") -> Aisha Aliyu | E4: Admin | F4: IT General Controls Audit | G4: Asset register discrepancy | H4: Critical | I4: Open
A5: AUD0004 | B5: 45890 | C5: EMP0067 | D5: =IFERROR(INDEX(Dim_Employee!$B$2:$B$76,MATCH(C5,Dim_Employee!$A$2:$A$76,0)),"") -> Tobi Okonkwo | E5: Supply Chain | F5: Operational Audit | G5: No exceptions noted | H5: Medium | I5: In Remediation
A6: AUD0005 | B6: 45816 | C6: EMP0067 | D6: =IFERROR(INDEX(Dim_Employee!$B$2:$B$76,MATCH(C6,Dim_Employee!$A$2:$A$76,0)),"") -> Tobi Okonkwo | E6: Supply Chain | F6: Operational Audit | G6: Policy non-adherence | H6: Critical | I6: In Remediation
A7: AUD0006 | B7: 46020 | C7: EMP0067 | D7: =IFERROR(INDEX(Dim_Employee!$B$2:$B$76,MATCH(C7,Dim_Employee!$A$2:$A$76,0)),"") -> Tobi Okonkwo | E7: Admin | F7: Procurement Audit | G7: No exceptions noted | H7: High | I7: Closed | J7: 46053
A8: AUD0007 | B8: 45854 | C8: EMP0069 | D8: =IFERROR(INDEX(Dim_Employee!$B$2:$B$76,MATCH(C8,Dim_Employee!$A$2:$A$76,0)),"") -> Segun Okafor | E8: Accounts and Finance | F8: Compliance Audit | G8: Policy non-adherence | H8: Medium | I8: Open
A9: AUD0008 | B9: 45999 | C9: EMP0068 | D9: =IFERROR(INDEX(Dim_Employee!$B$2:$B$76,MATCH(C9,Dim_Employee!$A$2:$A$76,0)),"") -> Segun Onyeka | E9: IT | F9: Procurement Audit | G9: No exceptions noted | H9: Critical | I9: In Remediation
A10: AUD0009 | B10: 45997 | C10: EMP0065 | D10: =IFERROR(INDEX(Dim_Employee!$B$2:$B$76,MATCH(C10,Dim_Employee!$A$2:$A$76,0)),"") -> Aisha Igwe | E10: Legal | F10: IT General Controls Audit | G10: Late reconciliation | H10: Low | I10: Open
A11: AUD0010 | B11: 45733 | C11: EMP0065 | D11: =IFERROR(INDEX(Dim_Employee!$B$2:$B$76,MATCH(C11,Dim_Employee!$A$2:$A$76,0)),"") -> Aisha Igwe | E11: Supply Chain | F11: IT General Controls Audit | G11: Segregation of duties gap | H11: Critical | I11: Open
A12: AUD0011 | B12: 45711 | C12: EMP0067 | D12: =IFERROR(INDEX(Dim_Employee!$B$2:$B$76,MATCH(C12,Dim_Employee!$A$2:$A$76,0)),"") -> Tobi Okonkwo | E12: Human Resources | F12: Operational Audit | G12: Asset register discrepancy | H12: Low | I12: Closed | J12: 45786
A13: AUD0012 | B13: 45765 | C13: EMP0068 | D13: =IFERROR(INDEX(Dim_Employee!$B$2:$B$76,MATCH(C13,Dim_Employee!$A$2:$A$76,0)),"") -> Segun Onyeka | E13: Customer Service | F13: Compliance Audit | G13: No exceptions noted | H13: High | I13: In Remediation
A14: AUD0013 | B14: 45790 | C14: EMP0069 | D14: =IFERROR(INDEX(Dim_Employee!$B$2:$B$76,MATCH(C14,Dim_Employee!$A$2:$A$76,0)),"") -> Segun Okafor | E14: Customer Service | F14: Financial Audit | G14: No exceptions noted | H14: Critical | I14: In Remediation
A15: AUD0014 | B15: 45809 | C15: EMP0066 | D15: =IFERROR(INDEX(Dim_Employee!$B$2:$B$76,MATCH(C15,Dim_Employee!$A$2:$A$76,0)),"") -> Aisha Aliyu | E15: Customer Service | F15: Compliance Audit | G15: Segregation of duties gap | H15: Critical | I15: Closed | J15: 45889
A16: AUD0015 | B16: 45776 | C16: EMP0068 | D16: =IFERROR(INDEX(Dim_Employee!$B$2:$B$76,MATCH(C16,Dim_Employee!$A$2:$A$76,0)),"") -> Segun Onyeka | E16: Customer Service | F16: Procurement Audit | G16: No exceptions noted | H16: High | I16: In Remediation
A17: AUD0016 | B17: 46014 | C17: EMP0067 | D17: =IFERROR(INDEX(Dim_Employee!$B$2:$B$76,MATCH(C17,Dim_Employee!$A$2:$A$76,0)),"") -> Tobi Okonkwo | E17: Accounts and Finance | F17: Procurement Audit | G17: Missing approval documentation | H17: Low | I17: In Remediation
A18: AUD0017 | B18: 45937 | C18: EMP0065 | D18: =IFERROR(INDEX(Dim_Employee!$B$2:$B$76,MATCH(C18,Dim_Employee!$A$2:$A$76,0)),"") -> Aisha Igwe | E18: Supply Chain | F18: Compliance Audit | G18: Segregation of duties gap | H18: Critical | I18: Closed | J18: 45979
A19: AUD0018 | B19: 45905 | C19: EMP0065 | D19: =IFERROR(INDEX(Dim_Employee!$B$2:$B$76,MATCH(C19,Dim_Employee!$A$2:$A$76,0)),"") -> Aisha Igwe | E19: Operations | F19: Compliance Audit | G19: Late reconciliation | H19: High | I19: Closed | J19: 45936
A20: AUD0019 | B20: 45725 | C20: EMP0066 | D20: =IFERROR(INDEX(Dim_Employee!$B$2:$B$76,MATCH(C20,Dim_Employee!$A$2:$A$76,0)),"") -> Aisha Aliyu | E20: IT | F20: Procurement Audit | G20: Segregation of duties gap | H20: Low | I20: In Remediation
A21: AUD0020 | B21: 45914 | C21: EMP0065 | D21: =IFERROR(INDEX(Dim_Employee!$B$2:$B$76,MATCH(C21,Dim_Employee!$A$2:$A$76,0)),"") -> Aisha Igwe | E21: Customer Service | F21: Compliance Audit | G21: No exceptions noted | H21: Medium | I21: Open
A22: AUD0021 | B22: 45861 | C22: EMP0067 | D22: =IFERROR(INDEX(Dim_Employee!$B$2:$B$76,MATCH(C22,Dim_Employee!$A$2:$A$76,0)),"") -> Tobi Okonkwo | E22: Accounts and Finance | F22: Compliance Audit | G22: Asset register discrepancy | H22: Medium | I22: In Remediation
A23: AUD0022 | B23: 45805 | C23: EMP0068 | D23: =IFERROR(INDEX(Dim_Employee!$B$2:$B$76,MATCH(C23,Dim_Employee!$A$2:$A$76,0)),"") -> Segun Onyeka | E23: Human Resources | F23: Operational Audit | G23: Asset register discrepancy | H23: Low | I23: Closed | J23: 45887
A24: AUD0023 | B24: 45967 | C24: EMP0068 | D24: =IFERROR(INDEX(Dim_Employee!$B$2:$B$76,MATCH(C24,Dim_Employee!$A$2:$A$76,0)),"") -> Segun Onyeka | E24: Operations | F24: Procurement Audit | G24: Asset register discrepancy | H24: Critical | I24: In Remediation
A25: AUD0024 | B25: 45919 | C25: EMP0066 | D25: =IFERROR(INDEX(Dim_Employee!$B$2:$B$76,MATCH(C25,Dim_Employee!$A$2:$A$76,0)),"") -> Aisha Aliyu | E25: Supply Chain | F25: Compliance Audit | G25: Segregation of duties gap | H25: Critical | I25: Closed | J25: 45978
A26: AUD0025 | B26: 45738 | C26: EMP0067 | D26: =IFERROR(INDEX(Dim_Employee!$B$2:$B$76,MATCH(C26,Dim_Employee!$A$2:$A$76,0)),"") -> Tobi Okonkwo | E26: Legal | F26: IT General Controls Audit | G26: Policy non-adherence | H26: Critical | I26: Closed | J26: 45782
A27: AUD0026 | B27: 45902 | C27: EMP0065 | D27: =IFERROR(INDEX(Dim_Employee!$B$2:$B$76,MATCH(C27,Dim_Employee!$A$2:$A$76,0)),"") -> Aisha Igwe | E27: Customer Service | F27: Operational Audit | G27: Policy non-adherence | H27: Medium | I27: In Remediation
A28: AUD0027 | B28: 45813 | C28: EMP0065 | D28: =IFERROR(INDEX(Dim_Employee!$B$2:$B$76,MATCH(C28,Dim_Employee!$A$2:$A$76,0)),"") -> Aisha Igwe | E28: Human Resources | F28: Compliance Audit | G28: Policy non-adherence | H28: Medium | I28: In Remediation
A29: AUD0028 | B29: 45781 | C29: EMP0066 | D29: =IFERROR(INDEX(Dim_Employee!$B$2:$B$76,MATCH(C29,Dim_Employee!$A$2:$A$76,0)),"") -> Aisha Aliyu | E29: Customer Service | F29: IT General Controls Audit | G29: Policy non-adherence | H29: Critical | I29: In Remediation
A30: AUD0029 | B30: 45876 | C30: EMP0069 | D30: =IFERROR(INDEX(Dim_Employee!$B$2:$B$76,MATCH(C30,Dim_Employee!$A$2:$A$76,0)),"") -> Segun Okafor | E30: Accounts and Finance | F30: Operational Audit | G30: No exceptions noted | H30: Low | I30: In Remediation
A31: AUD0030 | B31: 46010 | C31: EMP0065 | D31: =IFERROR(INDEX(Dim_Employee!$B$2:$B$76,MATCH(C31,Dim_Employee!$A$2:$A$76,0)),"") -> Aisha Igwe | E31: Customer Service | F31: Procurement Audit | G31: Missing approval documentation | H31: Medium | I31: In Remediation
A32: AUD0031 | B32: 46022 | C32: EMP0069 | D32: =IFERROR(INDEX(Dim_Employee!$B$2:$B$76,MATCH(C32,Dim_Employee!$A$2:$A$76,0)),"") -> Segun Okafor | E32: Supply Chain | F32: Financial Audit | G32: Policy non-adherence | H32: Critical | I32: In Remediation
A33: AUD0032 | B33: 45741 | C33: EMP0066 | D33: =IFERROR(INDEX(Dim_Employee!$B$2:$B$76,MATCH(C33,Dim_Employee!$A$2:$A$76,0)),"") -> Aisha Aliyu | E33: Operations | F33: Financial Audit | G33: Asset register discrepancy | H33: Critical | I33: Open
A34: AUD0033 | B34: 45980 | C34: EMP0066 | D34: =IFERROR(INDEX(Dim_Employee!$B$2:$B$76,MATCH(C34,Dim_Employee!$A$2:$A$76,0)),"") -> Aisha Aliyu | E34: Supply Chain | F34: Procurement Audit | G34: Late reconciliation | H34: Medium | I34: In Remediation
A35: AUD0034 | B35: 45926 | C35: EMP0069 | D35: =IFERROR(INDEX(Dim_Employee!$B$2:$B$76,MATCH(C35,Dim_Employee!$A$2:$A$76,0)),"") -> Segun Okafor | E35: Operations | F35: IT General Controls Audit | G35: Budget variance unexplained | H35: Medium | I35: In Remediation
A36: AUD0035 | B36: 45816 | C36: EMP0065 | D36: =IFERROR(INDEX(Dim_Employee!$B$2:$B$76,MATCH(C36,Dim_Employee!$A$2:$A$76,0)),"") -> Aisha Igwe | E36: Admin | F36: Operational Audit | G36: Asset register discrepancy | H36: Critical | I36: Open
A37: AUD0036 | B37: 45725 | C37: EMP0068 | D37: =IFERROR(INDEX(Dim_Employee!$B$2:$B$76,MATCH(C37,Dim_Employee!$A$2:$A$76,0)),"") -> Segun Onyeka | E37: Human Resources | F37: Procurement Audit | G37: Asset register discrepancy | H37: High | I37: Closed | J37: 45776
A38: AUD0037 | B38: 45876 | C38: EMP0066 | D38: =IFERROR(INDEX(Dim_Employee!$B$2:$B$76,MATCH(C38,Dim_Employee!$A$2:$A$76,0)),"") -> Aisha Aliyu | E38: Supply Chain | F38: Financial Audit | G38: Segregation of duties gap | H38: Medium | I38: In Remediation
A39: AUD0038 | B39: 45948 | C39: EMP0065 | D39: =IFERROR(INDEX(Dim_Employee!$B$2:$B$76,MATCH(C39,Dim_Employee!$A$2:$A$76,0)),"") -> Aisha Igwe | E39: IT | F39: Procurement Audit | G39: No exceptions noted | H39: Critical | I39: In Remediation
A40: AUD0039 | B40: 45789 | C40: EMP0067 | D40: =IFERROR(INDEX(Dim_Employee!$B$2:$B$76,MATCH(C40,Dim_Employee!$A$2:$A$76,0)),"") -> Tobi Okonkwo | E40: Supply Chain | F40: Compliance Audit | G40: Asset register discrepancy | H40: Medium | I40: Closed | J40: 45862
A41: AUD0040 | B41: 45673 | C41: EMP0066 | D41: =IFERROR(INDEX(Dim_Employee!$B$2:$B$76,MATCH(C41,Dim_Employee!$A$2:$A$76,0)),"") -> Aisha Aliyu | E41: Human Resources | F41: Compliance Audit | G41: Segregation of duties gap | H41: Low | I41: Closed | J41: 45707
A42: AUD0041 | B42: 45949 | C42: EMP0067 | D42: =IFERROR(INDEX(Dim_Employee!$B$2:$B$76,MATCH(C42,Dim_Employee!$A$2:$A$76,0)),"") -> Tobi Okonkwo | E42: Admin | F42: Compliance Audit | G42: Segregation of duties gap | H42: High | I42: In Remediation
A43: AUD0042 | B43: 46005 | C43: EMP0069 | D43: =IFERROR(INDEX(Dim_Employee!$B$2:$B$76,MATCH(C43,Dim_Employee!$A$2:$A$76,0)),"") -> Segun Okafor | E43: Legal | F43: Operational Audit | G43: Late reconciliation | H43: Critical | I43: In Remediation
A44: AUD0043 | B44: 45674 | C44: EMP0067 | D44: =IFERROR(INDEX(Dim_Employee!$B$2:$B$76,MATCH(C44,Dim_Employee!$A$2:$A$76,0)),"") -> Tobi Okonkwo | E44: Admin | F44: Compliance Audit | G44: Segregation of duties gap | H44: High | I44: In Remediation
A45: AUD0044 | B45: 45800 | C45: EMP0069 | D45: =IFERROR(INDEX(Dim_Employee!$B$2:$B$76,MATCH(C45,Dim_Employee!$A$2:$A$76,0)),"") -> Segun Okafor | E45: Operations | F45: Operational Audit | G45: Asset register discrepancy | H45: Critical | I45: Open
A46: AUD0045 | B46: 45951 | C46: EMP0065 | D46: =IFERROR(INDEX(Dim_Employee!$B$2:$B$76,MATCH(C46,Dim_Employee!$A$2:$A$76,0)),"") -> Aisha Igwe | E46: Customer Service | F46: Operational Audit | G46: No exceptions noted | H46: Critical | I46: Closed | J46: 45968
A47: AUD0046 | B47: 45904 | C47: EMP0068 | D47: =IFERROR(INDEX(Dim_Employee!$B$2:$B$76,MATCH(C47,Dim_Employee!$A$2:$A$76,0)),"") -> Segun Onyeka | E47: Supply Chain | F47: IT General Controls Audit | G47: Segregation of duties gap | H47: High | I47: Open
A48: AUD0047 | B48: 45671 | C48: EMP0068 | D48: =IFERROR(INDEX(Dim_Employee!$B$2:$B$76,MATCH(C48,Dim_Employee!$A$2:$A$76,0)),"") -> Segun Onyeka | E48: Customer Service | F48: IT General Controls Audit | G48: Late reconciliation | H48: Medium | I48: Open
A49: AUD0048 | B49: 45772 | C49: EMP0067 | D49: =IFERROR(INDEX(Dim_Employee!$B$2:$B$76,MATCH(C49,Dim_Employee!$A$2:$A$76,0)),"") -> Tobi Okonkwo | E49: Customer Service | F49: Financial Audit | G49: Policy non-adherence | H49: High | I49: Open
A50: AUD0049 | B50: 45933 | C50: EMP0066 | D50: =IFERROR(INDEX(Dim_Employee!$B$2:$B$76,MATCH(C50,Dim_Employee!$A$2:$A$76,0)),"") -> Aisha Aliyu | E50: Operations | F50: IT General Controls Audit | G50: Policy non-adherence | H50: Low | I50: In Remediation
A51: AUD0050 | B51: 45743 | C51: EMP0068 | D51: =IFERROR(INDEX(Dim_Employee!$B$2:$B$76,MATCH(C51,Dim_Employee!$A$2:$A$76,0)),"") -> Segun Onyeka | E51: Supply Chain | F51: Procurement Audit | G51: Late reconciliation | H51: Critical | I51: Open
A52: AUD0051 | B52: 45873 | C52: EMP0066 | D52: =IFERROR(INDEX(Dim_Employee!$B$2:$B$76,MATCH(C52,Dim_Employee!$A$2:$A$76,0)),"") -> Aisha Aliyu | E52: Human Resources | F52: Compliance Audit | G52: Asset register discrepancy | H52: Critical | I52: Open
A53: AUD0052 | B53: 45898 | C53: EMP0068 | D53: =IFERROR(INDEX(Dim_Employee!$B$2:$B$76,MATCH(C53,Dim_Employee!$A$2:$A$76,0)),"") -> Segun Onyeka | E53: Operations | F53: Procurement Audit | G53: No exceptions noted | H53: Critical | I53: Open
A54: AUD0053 | B54: 45782 | C54: EMP0067 | D54: =IFERROR(INDEX(Dim_Employee!$B$2:$B$76,MATCH(C54,Dim_Employee!$A$2:$A$76,0)),"") -> Tobi Okonkwo | E54: Legal | F54: Procurement Audit | G54: No exceptions noted | H54: Low | I54: Closed | J54: 45830
A55: AUD0054 | B55: 45748 | C55: EMP0069 | D55: =IFERROR(INDEX(Dim_Employee!$B$2:$B$76,MATCH(C55,Dim_Employee!$A$2:$A$76,0)),"") -> Segun Okafor | E55: IT | F55: Operational Audit | G55: Budget variance unexplained | H55: High | I55: Closed | J55: 45767
A56: AUD0055 | B56: 45687 | C56: EMP0068 | D56: =IFERROR(INDEX(Dim_Employee!$B$2:$B$76,MATCH(C56,Dim_Employee!$A$2:$A$76,0)),"") -> Segun Onyeka | E56: Accounts and Finance | F56: Compliance Audit | G56: Asset register discrepancy | H56: High | I56: Open
A57: AUD0056 | B57: 45852 | C57: EMP0067 | D57: =IFERROR(INDEX(Dim_Employee!$B$2:$B$76,MATCH(C57,Dim_Employee!$A$2:$A$76,0)),"") -> Tobi Okonkwo | E57: Operations | F57: Operational Audit | G57: Late reconciliation | H57: Critical | I57: Open
A58: AUD0057 | B58: 45671 | C58: EMP0066 | D58: =IFERROR(INDEX(Dim_Employee!$B$2:$B$76,MATCH(C58,Dim_Employee!$A$2:$A$76,0)),"") -> Aisha Aliyu | E58: Legal | F58: Operational Audit | G58: Budget variance unexplained | H58: Medium | I58: Closed | J58: 45758
A59: AUD0058 | B59: 46010 | C59: EMP0069 | D59: =IFERROR(INDEX(Dim_Employee!$B$2:$B$76,MATCH(C59,Dim_Employee!$A$2:$A$76,0)),"") -> Segun Okafor | E59: Operations | F59: Compliance Audit | G59: Policy non-adherence | H59: Critical | I59: In Remediation
A60: AUD0059 | B60: 45710 | C60: EMP0065 | D60: =IFERROR(INDEX(Dim_Employee!$B$2:$B$76,MATCH(C60,Dim_Employee!$A$2:$A$76,0)),"") -> Aisha Igwe | E60: Operations | F60: Compliance Audit | G60: Segregation of duties gap | H60: High | I60: Open
A61: AUD0060 | B61: 45672 | C61: EMP0068 | D61: =IFERROR(INDEX(Dim_Employee!$B$2:$B$76,MATCH(C61,Dim_Employee!$A$2:$A$76,0)),"") -> Segun Onyeka | E61: Operations | F61: Compliance Audit | G61: Budget variance unexplained | H61: Critical | I61: Open
A62: AUD0061 | B62: 45702 | C62: EMP0068 | D62: =IFERROR(INDEX(Dim_Employee!$B$2:$B$76,MATCH(C62,Dim_Employee!$A$2:$A$76,0)),"") -> Segun Onyeka | E62: Legal | F62: Procurement Audit | G62: Asset register discrepancy | H62: Medium | I62: In Remediation
A63: AUD0062 | B63: 46021 | C63: EMP0066 | D63: =IFERROR(INDEX(Dim_Employee!$B$2:$B$76,MATCH(C63,Dim_Employee!$A$2:$A$76,0)),"") -> Aisha Aliyu | E63: Human Resources | F63: Financial Audit | G63: No exceptions noted | H63: Critical | I63: Closed | J63: 46073
A64: AUD0063 | B64: 45913 | C64: EMP0066 | D64: =IFERROR(INDEX(Dim_Employee!$B$2:$B$76,MATCH(C64,Dim_Employee!$A$2:$A$76,0)),"") -> Aisha Aliyu | E64: Human Resources | F64: Procurement Audit | G64: Asset register discrepancy | H64: Low | I64: Open
A65: AUD0064 | B65: 45776 | C65: EMP0066 | D65: =IFERROR(INDEX(Dim_Employee!$B$2:$B$76,MATCH(C65,Dim_Employee!$A$2:$A$76,0)),"") -> Aisha Aliyu | E65: Customer Service | F65: Operational Audit | G65: Policy non-adherence | H65: Medium | I65: In Remediation
A66: AUD0065 | B66: 45703 | C66: EMP0068 | D66: =IFERROR(INDEX(Dim_Employee!$B$2:$B$76,MATCH(C66,Dim_Employee!$A$2:$A$76,0)),"") -> Segun Onyeka | E66: Human Resources | F66: Operational Audit | G66: Budget variance unexplained | H66: Medium | I66: Closed | J66: 45738
A67: AUD0066 | B67: 45687 | C67: EMP0066 | D67: =IFERROR(INDEX(Dim_Employee!$B$2:$B$76,MATCH(C67,Dim_Employee!$A$2:$A$76,0)),"") -> Aisha Aliyu | E67: Human Resources | F67: IT General Controls Audit | G67: Segregation of duties gap | H67: High | I67: Open
A68: AUD0067 | B68: 45939 | C68: EMP0065 | D68: =IFERROR(INDEX(Dim_Employee!$B$2:$B$76,MATCH(C68,Dim_Employee!$A$2:$A$76,0)),"") -> Aisha Igwe | E68: Admin | F68: Compliance Audit | G68: Policy non-adherence | H68: Medium | I68: Open
A69: AUD0068 | B69: 45814 | C69: EMP0065 | D69: =IFERROR(INDEX(Dim_Employee!$B$2:$B$76,MATCH(C69,Dim_Employee!$A$2:$A$76,0)),"") -> Aisha Igwe | E69: Supply Chain | F69: Procurement Audit | G69: No exceptions noted | H69: Low | I69: Open
A70: AUD0069 | B70: 45738 | C70: EMP0066 | D70: =IFERROR(INDEX(Dim_Employee!$B$2:$B$76,MATCH(C70,Dim_Employee!$A$2:$A$76,0)),"") -> Aisha Aliyu | E70: Admin | F70: Procurement Audit | G70: Asset register discrepancy | H70: High | I70: Open
A71: AUD0070 | B71: 45754 | C71: EMP0065 | D71: =IFERROR(INDEX(Dim_Employee!$B$2:$B$76,MATCH(C71,Dim_Employee!$A$2:$A$76,0)),"") -> Aisha Igwe | E71: Supply Chain | F71: Procurement Audit | G71: Asset register discrepancy | H71: Critical | I71: Closed | J71: 45805
A72: AUD0071 | B72: 45661 | C72: EMP0069 | D72: =IFERROR(INDEX(Dim_Employee!$B$2:$B$76,MATCH(C72,Dim_Employee!$A$2:$A$76,0)),"") -> Segun Okafor | E72: Human Resources | F72: Procurement Audit | G72: Segregation of duties gap | H72: High | I72: Closed | J72: 45740
A73: AUD0072 | B73: 45953 | C73: EMP0065 | D73: =IFERROR(INDEX(Dim_Employee!$B$2:$B$76,MATCH(C73,Dim_Employee!$A$2:$A$76,0)),"") -> Aisha Igwe | E73: Supply Chain | F73: Financial Audit | G73: Late reconciliation | H73: Critical | I73: Closed | J73: 46032
A74: AUD0073 | B74: 45936 | C74: EMP0065 | D74: =IFERROR(INDEX(Dim_Employee!$B$2:$B$76,MATCH(C74,Dim_Employee!$A$2:$A$76,0)),"") -> Aisha Igwe | E74: Legal | F74: Procurement Audit | G74: Asset register discrepancy | H74: Medium | I74: Closed | J74: 46017
A75: AUD0074 | B75: 45714 | C75: EMP0069 | D75: =IFERROR(INDEX(Dim_Employee!$B$2:$B$76,MATCH(C75,Dim_Employee!$A$2:$A$76,0)),"") -> Segun Okafor | E75: Supply Chain | F75: Operational Audit | G75: Segregation of duties gap | H75: Low | I75: In Remediation
A76: AUD0075 | B76: 45699 | C76: EMP0065 | D76: =IFERROR(INDEX(Dim_Employee!$B$2:$B$76,MATCH(C76,Dim_Employee!$A$2:$A$76,0)),"") -> Aisha Igwe | E76: Legal | F76: Financial Audit | G76: Missing approval documentation | H76: High | I76: In Remediation
A77: AUD0076 | B77: 46016 | C77: EMP0068 | D77: =IFERROR(INDEX(Dim_Employee!$B$2:$B$76,MATCH(C77,Dim_Employee!$A$2:$A$76,0)),"") -> Segun Onyeka | E77: Supply Chain | F77: Compliance Audit | G77: Policy non-adherence | H77: Critical | I77: Closed | J77: 46048
A78: AUD0077 | B78: 45785 | C78: EMP0067 | D78: =IFERROR(INDEX(Dim_Employee!$B$2:$B$76,MATCH(C78,Dim_Employee!$A$2:$A$76,0)),"") -> Tobi Okonkwo | E78: Operations | F78: Operational Audit | G78: Late reconciliation | H78: Medium | I78: In Remediation
A79: AUD0078 | B79: 45705 | C79: EMP0066 | D79: =IFERROR(INDEX(Dim_Employee!$B$2:$B$76,MATCH(C79,Dim_Employee!$A$2:$A$76,0)),"") -> Aisha Aliyu | E79: Supply Chain | F79: Procurement Audit | G79: Segregation of duties gap | H79: Critical | I79: Closed | J79: 45747
A80: AUD0079 | B80: 45953 | C80: EMP0067 | D80: =IFERROR(INDEX(Dim_Employee!$B$2:$B$76,MATCH(C80,Dim_Employee!$A$2:$A$76,0)),"") -> Tobi Okonkwo | E80: Accounts and Finance | F80: Procurement Audit | G80: No exceptions noted | H80: Medium | I80: Closed | J80: 46006
A81: AUD0080 | B81: 45681 | C81: EMP0068 | D81: =IFERROR(INDEX(Dim_Employee!$B$2:$B$76,MATCH(C81,Dim_Employee!$A$2:$A$76,0)),"") -> Segun Onyeka | E81: Supply Chain | F81: IT General Controls Audit | G81: Missing approval documentation | H81: High | I81: In Remediation

Sheet Risk_Mgmt_Compliance
A1: Risk_ID | B1: Date_Identified | C1: Employee_ID | D1: Employee_Name | E1: Department_Linked | F1: Risk_Category | G1: Risk_Description | H1: Likelihood_1to5 | I1: Impact_1to5 | J1: Risk_Score | K1: Mitigation_Plan | L1: Status
A2: RSK0001 | B2: 45758 | C2: EMP0073 | D2: =IFERROR(INDEX(Dim_Employee!$B$2:$B$76,MATCH(C2,Dim_Employee!$A$2:$A$76,0)),"") -> Grace Chukwu | E2: Operations | F2: HSE | G2: Gas supply disruption risk | H2: 3 | I2: 5 | J2: =H2*I2 -> 15 | K2: Diversify gas suppliers | L2: Closed
A3: RSK0002 | B3: 45894 | C3: EMP0074 | D3: =IFERROR(INDEX(Dim_Employee!$B$2:$B$76,MATCH(C3,Dim_Employee!$A$2:$A$76,0)),"") -> Tobi Danjuma | E3: IT | F3: Compliance/Regulatory | G3: Gas supply disruption risk | H3: 2 | I3: 5 | J3: =H3*I3 -> 10 | K3: Diversify gas suppliers | L3: Closed
A4: RSK0003 | B4: 45970 | C4: EMP0075 | D4: =IFERROR(INDEX(Dim_Employee!$B$2:$B$76,MATCH(C4,Dim_Employee!$A$2:$A$76,0)),"") -> Halima Okafor | E4: Legal | F4: Financial | G4: Delayed capital project risk | H4: 2 | I4: 2 | J4: =H4*I4 -> 4 | K4: Enhance project governance and monitoring | L4: Open
A5: RSK0004 | B5: 45743 | C5: EMP0071 | D5: =IFERROR(INDEX(Dim_Employee!$B$2:$B$76,MATCH(C5,Dim_Employee!$A$2:$A$76,0)),"") -> Bola Bakare | E5: Human Resources | F5: HSE | G5: NERC tariff review risk | H5: 1 | I5: 2 | J5: =H5*I5 -> 2 | K5: Engage regulator proactively | L5: Open
A6: RSK0005 | B6: 45794 | C6: EMP0072 | D6: =IFERROR(INDEX(Dim_Employee!$B$2:$B$76,MATCH(C6,Dim_Employee!$A$2:$A$76,0)),"") -> Tobi Adebayo | E6: Supply Chain | F6: Operational | G6: Data breach on SCADA network | H6: 1 | I6: 5 | J6: =H6*I6 -> 5 | K6: Deploy network segmentation and monitoring | L6: Monitoring
A7: RSK0006 | B7: 45710 | C7: EMP0073 | D7: =IFERROR(INDEX(Dim_Employee!$B$2:$B$76,MATCH(C7,Dim_Employee!$A$2:$A$76,0)),"") -> Grace Chukwu | E7: Legal | F7: Compliance/Regulatory | G7: Foreign exchange exposure on spares | H7: 4 | I7: 2 | J7: =H7*I7 -> 8 | K7: Hedge FX exposure | L7: Monitoring
A8: RSK0007 | B8: 45961 | C8: EMP0072 | D8: =IFERROR(INDEX(Dim_Employee!$B$2:$B$76,MATCH(C8,Dim_Employee!$A$2:$A$76,0)),"") -> Tobi Adebayo | E8: Admin | F8: Cybersecurity | G8: Gas supply disruption risk | H8: 1 | I8: 2 | J8: =H8*I8 -> 2 | K8: Diversify gas suppliers | L8: Monitoring
A9: RSK0008 | B9: 45982 | C9: EMP0070 | D9: =IFERROR(INDEX(Dim_Employee!$B$2:$B$76,MATCH(C9,Dim_Employee!$A$2:$A$76,0)),"") -> Chukwudi Yakubu | E9: Human Resources | F9: Financial | G9: NERC tariff review risk | H9: 2 | I9: 5 | J9: =H9*I9 -> 10 | K9: Engage regulator proactively | L9: Closed
A10: RSK0009 | B10: 45754 | C10: EMP0072 | D10: =IFERROR(INDEX(Dim_Employee!$B$2:$B$76,MATCH(C10,Dim_Employee!$A$2:$A$76,0)),"") -> Tobi Adebayo | E10: IT | F10: Financial | G10: Data breach on SCADA network | H10: 1 | I10: 5 | J10: =H10*I10 -> 5 | K10: Deploy network segmentation and monitoring | L10: Mitigated
A11: RSK0010 | B11: 46021 | C11: EMP0072 | D11: =IFERROR(INDEX(Dim_Employee!$B$2:$B$76,MATCH(C11,Dim_Employee!$A$2:$A$76,0)),"") -> Tobi Adebayo | E11: Human Resources | F11: HSE | G11: Community/host relations risk | H11: 1 | I11: 2 | J11: =H11*I11 -> 2 | K11: Strengthen community engagement program | L11: Open
A12: RSK0011 | B12: 45875 | C12: EMP0070 | D12: =IFERROR(INDEX(Dim_Employee!$B$2:$B$76,MATCH(C12,Dim_Employee!$A$2:$A$76,0)),"") -> Chukwudi Yakubu | E12: IT | F12: Cybersecurity | G12: Key personnel attrition risk | H12: 2 | I12: 3 | J12: =H12*I12 -> 6 | K12: Succession planning and retention plan | L12: Closed
A13: RSK0012 | B13: 45976 | C13: EMP0070 | D13: =IFERROR(INDEX(Dim_Employee!$B$2:$B$76,MATCH(C13,Dim_Employee!$A$2:$A$76,0)),"") -> Chukwudi Yakubu | E13: Legal | F13: Compliance/Regulatory | G13: Data breach on SCADA network | H13: 4 | I13: 4 | J13: =H13*I13 -> 16 | K13: Deploy network segmentation and monitoring | L13: Mitigated
... A71: RSK0070 | B71: 45718 | C71: EMP0074 | D71: =IFERROR(INDEX(Dim_Employee!$B$2:$B$76,MATCH(C71,Dim_Employee!$A$2:$A$76,0)),"") -> Tobi Danjuma | E71: Human Resources | F71: Compliance/Regulatory | G71: Data breach on SCADA network | H71: 2 | I71: 5 | J71: =H71*I71 -> 10 | K71: Deploy network segmentation and monitoring | L71: Closed
